# Comparing `tmp/pyc3dtools-0.2.5.win-amd64.zip` & `tmp/pyc3dtools-0.2.6.win-amd64.zip`

## zipinfo {}

```diff
@@ -1,17 +1,17 @@
-Zip file size: 11541 bytes, number of entries: 15
-drwxrwxrwx  2.0 fat        0 b- stor 23-May-28 18:19 Python311/
-drwxrwxrwx  2.0 fat        0 b- stor 23-May-28 18:19 Python311/Lib/
-drwxrwxrwx  2.0 fat        0 b- stor 23-May-28 18:19 Python311/Lib/site-packages/
-drwxrwxrwx  2.0 fat        0 b- stor 23-May-28 18:19 Python311/Lib/site-packages/pyc3dtools/
-drwxrwxrwx  2.0 fat        0 b- stor 23-May-28 18:19 Python311/Lib/site-packages/pyc3dtools-0.2.5-py3.11.egg-info/
-drwxrwxrwx  2.0 fat        0 b- stor 23-May-28 18:19 Python311/Lib/site-packages/pyc3dtools/__pycache__/
--rw-rw-rw-  2.0 fat     6121 b- defN 23-May-28 18:13 Python311/Lib/site-packages/pyc3dtools/pyc3dtools.py
+Zip file size: 11707 bytes, number of entries: 15
+drwxrwxrwx  2.0 fat        0 b- stor 23-Jun-25 11:48 Python311/
+drwxrwxrwx  2.0 fat        0 b- stor 23-Jun-25 11:48 Python311/Lib/
+drwxrwxrwx  2.0 fat        0 b- stor 23-Jun-25 11:48 Python311/Lib/site-packages/
+drwxrwxrwx  2.0 fat        0 b- stor 23-Jun-25 11:48 Python311/Lib/site-packages/pyc3dtools/
+drwxrwxrwx  2.0 fat        0 b- stor 23-Jun-25 11:48 Python311/Lib/site-packages/pyc3dtools-0.2.6-py3.11.egg-info/
+drwxrwxrwx  2.0 fat        0 b- stor 23-Jun-25 11:48 Python311/Lib/site-packages/pyc3dtools/__pycache__/
+-rw-rw-rw-  2.0 fat     6520 b- defN 23-Jun-25 11:44 Python311/Lib/site-packages/pyc3dtools/pyc3dtools.py
 -rw-rw-rw-  2.0 fat       88 b- defN 23-May-08 18:15 Python311/Lib/site-packages/pyc3dtools/__init__.py
--rw-rw-rw-  2.0 fat    10611 b- defN 23-May-28 18:19 Python311/Lib/site-packages/pyc3dtools/__pycache__/pyc3dtools.cpython-311.pyc
--rw-rw-rw-  2.0 fat      275 b- defN 23-May-28 18:19 Python311/Lib/site-packages/pyc3dtools/__pycache__/__init__.cpython-311.pyc
--rw-rw-rw-  2.0 fat        1 b- defN 23-May-28 18:19 Python311/Lib/site-packages/pyc3dtools-0.2.5-py3.11.egg-info/dependency_links.txt
--rw-rw-rw-  2.0 fat     9057 b- defN 23-May-28 18:19 Python311/Lib/site-packages/pyc3dtools-0.2.5-py3.11.egg-info/PKG-INFO
--rw-rw-rw-  2.0 fat       20 b- defN 23-May-28 18:19 Python311/Lib/site-packages/pyc3dtools-0.2.5-py3.11.egg-info/requires.txt
--rw-rw-rw-  2.0 fat      243 b- defN 23-May-28 18:19 Python311/Lib/site-packages/pyc3dtools-0.2.5-py3.11.egg-info/SOURCES.txt
--rw-rw-rw-  2.0 fat       11 b- defN 23-May-28 18:19 Python311/Lib/site-packages/pyc3dtools-0.2.5-py3.11.egg-info/top_level.txt
-15 files, 26427 bytes uncompressed, 8727 bytes compressed:  67.0%
+-rw-rw-rw-  2.0 fat    10813 b- defN 23-Jun-25 11:48 Python311/Lib/site-packages/pyc3dtools/__pycache__/pyc3dtools.cpython-311.pyc
+-rw-rw-rw-  2.0 fat      275 b- defN 23-Jun-25 11:48 Python311/Lib/site-packages/pyc3dtools/__pycache__/__init__.cpython-311.pyc
+-rw-rw-rw-  2.0 fat        1 b- defN 23-Jun-25 11:48 Python311/Lib/site-packages/pyc3dtools-0.2.6-py3.11.egg-info/dependency_links.txt
+-rw-rw-rw-  2.0 fat     9057 b- defN 23-Jun-25 11:48 Python311/Lib/site-packages/pyc3dtools-0.2.6-py3.11.egg-info/PKG-INFO
+-rw-rw-rw-  2.0 fat       20 b- defN 23-Jun-25 11:48 Python311/Lib/site-packages/pyc3dtools-0.2.6-py3.11.egg-info/requires.txt
+-rw-rw-rw-  2.0 fat      243 b- defN 23-Jun-25 11:48 Python311/Lib/site-packages/pyc3dtools-0.2.6-py3.11.egg-info/SOURCES.txt
+-rw-rw-rw-  2.0 fat       11 b- defN 23-Jun-25 11:48 Python311/Lib/site-packages/pyc3dtools-0.2.6-py3.11.egg-info/top_level.txt
+15 files, 27028 bytes uncompressed, 8893 bytes compressed:  67.1%
```

## zipnote {}

```diff
@@ -6,15 +6,15 @@
 
 Filename: Python311/Lib/site-packages/
 Comment: 
 
 Filename: Python311/Lib/site-packages/pyc3dtools/
 Comment: 
 
-Filename: Python311/Lib/site-packages/pyc3dtools-0.2.5-py3.11.egg-info/
+Filename: Python311/Lib/site-packages/pyc3dtools-0.2.6-py3.11.egg-info/
 Comment: 
 
 Filename: Python311/Lib/site-packages/pyc3dtools/__pycache__/
 Comment: 
 
 Filename: Python311/Lib/site-packages/pyc3dtools/pyc3dtools.py
 Comment: 
@@ -24,23 +24,23 @@
 
 Filename: Python311/Lib/site-packages/pyc3dtools/__pycache__/pyc3dtools.cpython-311.pyc
 Comment: 
 
 Filename: Python311/Lib/site-packages/pyc3dtools/__pycache__/__init__.cpython-311.pyc
 Comment: 
 
-Filename: Python311/Lib/site-packages/pyc3dtools-0.2.5-py3.11.egg-info/dependency_links.txt
+Filename: Python311/Lib/site-packages/pyc3dtools-0.2.6-py3.11.egg-info/dependency_links.txt
 Comment: 
 
-Filename: Python311/Lib/site-packages/pyc3dtools-0.2.5-py3.11.egg-info/PKG-INFO
+Filename: Python311/Lib/site-packages/pyc3dtools-0.2.6-py3.11.egg-info/PKG-INFO
 Comment: 
 
-Filename: Python311/Lib/site-packages/pyc3dtools-0.2.5-py3.11.egg-info/requires.txt
+Filename: Python311/Lib/site-packages/pyc3dtools-0.2.6-py3.11.egg-info/requires.txt
 Comment: 
 
-Filename: Python311/Lib/site-packages/pyc3dtools-0.2.5-py3.11.egg-info/SOURCES.txt
+Filename: Python311/Lib/site-packages/pyc3dtools-0.2.6-py3.11.egg-info/SOURCES.txt
 Comment: 
 
-Filename: Python311/Lib/site-packages/pyc3dtools-0.2.5-py3.11.egg-info/top_level.txt
+Filename: Python311/Lib/site-packages/pyc3dtools-0.2.6-py3.11.egg-info/top_level.txt
 Comment: 
 
 Zip file comment:
```

## Python311/Lib/site-packages/pyc3dtools/pyc3dtools.py

```diff
@@ -84,76 +84,86 @@
     GP =  result["GP"]
     Point = result["Point"]
     Real_marker_index = result["Real_marker_index"]
     Analog = result["Analog"]
     Header = result["Header"]
     Forceplates = result["Forceplate_list"]
     Real_Markers = np.array(Point)
-    Real_Markers = Real_Markers[:,Real_marker_index,:]
-    result["Markers"] = Real_Markers
-
-    # List of Markers Label
-    gp_point_lbl_i = [
-        index for index in range(len(GP))
-        if GP[index]['Group_Name'] == 'POINT'
-    ][0]    
-    gp_point_lbl_ii = [
-        index for index in range(len(GP[gp_point_lbl_i]['List_Parameters']))
-        if GP[gp_point_lbl_i]['List_Parameters'][index]['Param_Name'] == 'LABELS'
-    ][0] 
-    gp_point_unit_i = [
-        index for index in range(len(GP[gp_point_lbl_i]['List_Parameters']))
-        if GP[gp_point_lbl_i]['List_Parameters'][index]['Param_Name'] == 'UNITS'
-    ][0] 
-    gp_point_Yscreen_i = [
-        index for index in range(len(GP[gp_point_lbl_i]['List_Parameters']))
-        if GP[gp_point_lbl_i]['List_Parameters'][index]['Param_Name'] == 'Y_SCREEN'
-    ][0] 
-    gp_point_Xscreen_i = [
-        index for index in range(len(GP[gp_point_lbl_i]['List_Parameters']))
-        if GP[gp_point_lbl_i]['List_Parameters'][index]['Param_Name'] == 'X_SCREEN'
-    ][0] 
-    Markers_lbl = GP[gp_point_lbl_i]['List_Parameters'][gp_point_lbl_ii]['Param_data']
-    Markers_Units = GP[gp_point_lbl_i]['List_Parameters'][gp_point_unit_i]['Param_data'][0]
-    Markers_YSCREEN = GP[gp_point_lbl_i]['List_Parameters'][gp_point_Yscreen_i]['Param_data'][0]
-    Markers_XSCREEN = GP[gp_point_lbl_i]['List_Parameters'][gp_point_Xscreen_i]['Param_data'][0]
+    Markers_lbl = []
+    Analog_lbl = []
+    Markers_Units = ''
+    Markers_XSCREEN = ''
+    Markers_YSCREEN = ''
+
+
+    if len(Point[0]) > 0 :
+        Real_Markers = Real_Markers[:,Real_marker_index,:]
+        result["Markers"] = Real_Markers
+
+        # List of Markers Label
+        gp_point_lbl_i = [
+            index for index in range(len(GP))
+            if GP[index]['Group_Name'] == 'POINT'
+        ][0]    
+        gp_point_lbl_ii = [
+            index for index in range(len(GP[gp_point_lbl_i]['List_Parameters']))
+            if GP[gp_point_lbl_i]['List_Parameters'][index]['Param_Name'] == 'LABELS'
+        ][0] 
+        gp_point_unit_i = [
+            index for index in range(len(GP[gp_point_lbl_i]['List_Parameters']))
+            if GP[gp_point_lbl_i]['List_Parameters'][index]['Param_Name'] == 'UNITS'
+        ][0] 
+        gp_point_Yscreen_i = [
+            index for index in range(len(GP[gp_point_lbl_i]['List_Parameters']))
+            if GP[gp_point_lbl_i]['List_Parameters'][index]['Param_Name'] == 'Y_SCREEN'
+        ][0] 
+        gp_point_Xscreen_i = [
+            index for index in range(len(GP[gp_point_lbl_i]['List_Parameters']))
+            if GP[gp_point_lbl_i]['List_Parameters'][index]['Param_Name'] == 'X_SCREEN'
+        ][0] 
+        Markers_lbl = GP[gp_point_lbl_i]['List_Parameters'][gp_point_lbl_ii]['Param_data']
+        Markers_Units = GP[gp_point_lbl_i]['List_Parameters'][gp_point_unit_i]['Param_data'][0]
+        Markers_YSCREEN = GP[gp_point_lbl_i]['List_Parameters'][gp_point_Yscreen_i]['Param_data'][0]
+        Markers_XSCREEN = GP[gp_point_lbl_i]['List_Parameters'][gp_point_Xscreen_i]['Param_data'][0]
+    
 
     #List of Analog channel Label
-    gp_analog_lbl_i = [
-        index for index in range(len(GP))
-        if GP[index]['Group_Name'] == 'ANALOG'
-    ][0]    
-    gp_analog_lbl_ii = [
-        index for index in range(len(GP[gp_analog_lbl_i]['List_Parameters']))
-        if GP[gp_analog_lbl_i]['List_Parameters'][index]['Param_Name'] == 'LABELS'
-    ][0] 
-    Analog_lbl = GP[gp_analog_lbl_i]['List_Parameters'][gp_analog_lbl_ii]['Param_data']
-
-
-   
-    for f in Forceplates:
-            f['Origin'] = f['orgin']     ## SORRY :)
-            f['COP'] = np.array(f['COP'][:][:], dtype=object)
-            f['GRF_VECTOR'] = np.array(f['GRF_VECTOR'][:][:], dtype=object)           
+    if len(Analog[0]) > 0 :
+        gp_analog_lbl_i = [
+            index for index in range(len(GP))
+            if GP[index]['Group_Name'] == 'ANALOG'
+        ][0]    
+        gp_analog_lbl_ii = [
+            index for index in range(len(GP[gp_analog_lbl_i]['List_Parameters']))
+            if GP[gp_analog_lbl_i]['List_Parameters'][index]['Param_Name'] == 'LABELS'
+        ][0] 
+        Analog_lbl = GP[gp_analog_lbl_i]['List_Parameters'][gp_analog_lbl_ii]['Param_data']
+
 
     
-    # convert all analog data to np array
-    Analog = np.array(Analog)
-    NewAnalog =[]
-    for f in Analog:
-        main_row = []
-        for j in range(int((len(f)/len(Analog_lbl)))-1):
-            row = []
-            for k in range(j*len(Analog_lbl),(j+1)*len(Analog_lbl)):
-                row.append(f[k])
-            main_row.append(row)
+        for f in Forceplates:
+                f['Origin'] = f['orgin']     ## SORRY :)
+                f['COP'] = np.array(f['COP'][:][:], dtype=object)
+                f['GRF_VECTOR'] = np.array(f['GRF_VECTOR'][:][:], dtype=object)           
+
+        
+        # convert all analog data to np array
+        Analog = np.array(Analog)
+        NewAnalog =[]
+        for f in Analog:
+            main_row = []
+            for j in range(int((len(f)/len(Analog_lbl)))-1):
+                row = []
+                for k in range(j*len(Analog_lbl),(j+1)*len(Analog_lbl)):
+                    row.append(f[k])
+                main_row.append(row)
 
-        NewAnalog.append(main_row)    
+            NewAnalog.append(main_row)    
 
-    Analog = np.array(NewAnalog)
+        Analog = np.array(NewAnalog)
 
 
     return({
         'Status' : 'Success',
         'GP' : GP,
         'Markers' : Real_Markers,
         'Points' : Point,
```

## Python311/Lib/site-packages/pyc3dtools/__pycache__/pyc3dtools.cpython-311.pyc

### Python bytecode

```diff
@@ -1,10 +1,10 @@
 magic:    0xa70d0d0a
-moddate:  0xaf687364 (Sun May 28 14:43:59 2023 UTC)
-files sz: 6121
+moddate:  0x7cf79764 (Sun Jun 25 08:14:52 2023 UTC)
+files sz: 6520
 code
    argcount  : 0
    nlocals   : 0
    stacksize : 2
    flags     : 0
    code
       0x9700640064016c005a00640064016c015a01640064016c025a03640064
@@ -728,77 +728,81 @@
          stacksize : 12
          flags     : 3
          code
             0x87178718871997007c006401190000000000000000008a177c00640219
             0000000000000000007d017c006403190000000000000000007d027c0064
             04190000000000000000007d037c006405190000000000000000007d047c
             006406190000000000000000007d057401000000000000000000006a0100
-            000000000000007c01a6010000ab0100000000000000007d067c06640064
-            0085027c026400640085026603190000000000000000007d067c067c0064
-            073c00000088176601640884087405000000000000000000007407000000
-            000000000000008917a6010000ab010000000000000000a6010000ab0100
-            000000000000004400a6000000ab00000000000000000064091900000000
-            00000000008a19881788196602640a840874050000000000000000000074
-            07000000000000000000008917891919000000000000000000640b190000
-            00000000000000a6010000ab010000000000000000a6010000ab01000000
-            00000000004400a6000000ab000000000000000000640919000000000000
-            0000007d07881788196602640c8408740500000000000000000000740700
-            0000000000000000008917891919000000000000000000640b1900000000
-            0000000000a6010000ab010000000000000000a6010000ab010000000000
-            0000004400a6000000ab0000000000000000006409190000000000000000
-            007d08881788196602640d84087405000000000000000000007407000000
-            000000000000008917891919000000000000000000640b19000000000000
-            000000a6010000ab010000000000000000a6010000ab0100000000000000
-            004400a6000000ab0000000000000000006409190000000000000000007d
-            09881788196602640e840874050000000000000000000074070000000000
-            00000000008917891919000000000000000000640b190000000000000000
-            00a6010000ab010000000000000000a6010000ab01000000000000000044
-            00a6000000ab0000000000000000006409190000000000000000007d0a89
-            17891919000000000000000000640b190000000000000000007c07190000
-            00000000000000640f190000000000000000007d0b891789191900000000
-            0000000000640b190000000000000000007c081900000000000000000064
-            0f190000000000000000006409190000000000000000007d0c8917891919
-            000000000000000000640b190000000000000000007c0919000000000000
-            000000640f190000000000000000006409190000000000000000007d0d89
-            17891919000000000000000000640b190000000000000000007c0a190000
-            00000000000000640f190000000000000000006409190000000000000000
-            007d0e881766016410840874050000000000000000000074070000000000
-            00000000008917a6010000ab010000000000000000a6010000ab01000000
-            00000000004400a6000000ab000000000000000000640919000000000000
-            0000008a1888178818660264118408740500000000000000000000740700
-            0000000000000000008917891819000000000000000000640b1900000000
-            0000000000a6010000ab010000000000000000a6010000ab010000000000
-            0000004400a6000000ab0000000000000000006409190000000000000000
-            007d0f8917891819000000000000000000640b190000000000000000007c
-            0f19000000000000000000640f190000000000000000007d107c0544005d
-            757d117c116412190000000000000000007c1164133c0000007401000000
-            000000000000006a0100000000000000007c116414190000000000000000
-            006400640085021900000000000000000064006400850219000000000000
-            000000740800000000000000000000ac15a6020000ab0200000000000000
-            007c1164143c0000007401000000000000000000006a0100000000000000
-            007c11641619000000000000000000640064008502190000000000000000
-            0064006400850219000000000000000000740800000000000000000000ac
-            15a6020000ab0200000000000000007c1164163c0000008c767401000000
-            000000000000006a0100000000000000007c03a6010000ab010000000000
-            0000007d0367007d127c0344005dc07d1167007d13740500000000000000
-            000000740b000000000000000000007407000000000000000000007c11a6
-            010000ab0100000000000000007407000000000000000000007c10a60100
-            00ab0100000000000000007a0b0000a6010000ab01000000000000000064
-            177a0a0000a6010000ab01000000000000000044005d6a7d1467007d1574
-            05000000000000000000007c147407000000000000000000007c10a60100
-            00ab0100000000000000007a0500007c1464177a00000074070000000000
-            00000000007c10a6010000ab0100000000000000007a050000a6020000ab
-            02000000000000000044005d1d7d167c15a0060000000000000000000000
-            0000000000000000007c117c1619000000000000000000a6010000ab0100
-            0000000000000001008c1e7c13a006000000000000000000000000000000
-            00000000007c15a6010000ab01000000000000000001008c6b7c12a00600
-            000000000000000000000000000000000000007c13a6010000ab01000000
-            000000000001008cc17401000000000000000000006a0100000000000000
-            007c12a6010000ab0100000000000000007d03641889177c067c017c037c
-            047c057c0b7c107c0c7c0e7c0d670264199c0b5300
+            000000000000007c01a6010000ab0100000000000000007d0667007d0767
+            007d0864077d0964077d0a64077d0b7405000000000000000000007c0164
+            0819000000000000000000a6010000ab01000000000000000064086b0400
+            000000900172a87c066400640085027c0264006400850266031900000000
+            00000000007d067c067c0064093c00000088176601640a84087407000000
+            000000000000007405000000000000000000008917a6010000ab01000000
+            0000000000a6010000ab0100000000000000004400a6000000ab00000000
+            00000000006408190000000000000000008a19881788196602640b840874
+            070000000000000000000074050000000000000000000089178919190000
+            00000000000000640c19000000000000000000a6010000ab010000000000
+            000000a6010000ab0100000000000000004400a6000000ab000000000000
+            0000006408190000000000000000007d0c881788196602640d8408740700
+            000000000000000000740500000000000000000000891789191900000000
+            0000000000640c19000000000000000000a6010000ab0100000000000000
+            00a6010000ab0100000000000000004400a6000000ab0000000000000000
+            006408190000000000000000007d0d881788196602640e84087407000000
+            000000000000007405000000000000000000008917891919000000000000
+            000000640c19000000000000000000a6010000ab010000000000000000a6
+            010000ab0100000000000000004400a6000000ab00000000000000000064
+            08190000000000000000007d0e881788196602640f840874070000000000
+            000000000074050000000000000000000089178919190000000000000000
+            00640c19000000000000000000a6010000ab010000000000000000a60100
+            00ab0100000000000000004400a6000000ab000000000000000000640819
+            0000000000000000007d0f8917891919000000000000000000640c190000
+            000000000000007c0c190000000000000000006410190000000000000000
+            007d078917891919000000000000000000640c190000000000000000007c
+            0d1900000000000000000064101900000000000000000064081900000000
+            00000000007d098917891919000000000000000000640c19000000000000
+            0000007c0e19000000000000000000641019000000000000000000640819
+            0000000000000000007d0b8917891919000000000000000000640c190000
+            000000000000007c0f190000000000000000006410190000000000000000
+            006408190000000000000000007d0a7405000000000000000000007c0364
+            0819000000000000000000a6010000ab01000000000000000064086b0400
+            000000900172e88817660164118408740700000000000000000000740500
+            0000000000000000008917a6010000ab010000000000000000a6010000ab
+            0100000000000000004400a6000000ab0000000000000000006408190000
+            000000000000008a18881788186602641284087407000000000000000000
+            007405000000000000000000008917891819000000000000000000640c19
+            000000000000000000a6010000ab010000000000000000a6010000ab0100
+            000000000000004400a6000000ab00000000000000000064081900000000
+            00000000007d108917891819000000000000000000640c19000000000000
+            0000007c10190000000000000000006410190000000000000000007d087c
+            0544005d757d117c116413190000000000000000007c1164143c00000074
+            01000000000000000000006a0100000000000000007c1164151900000000
+            000000000064006400850219000000000000000000640064008502190000
+            00000000000000740800000000000000000000ac16a6020000ab02000000
+            00000000007c1164153c0000007401000000000000000000006a01000000
+            00000000007c116417190000000000000000006400640085021900000000
+            000000000064006400850219000000000000000000740800000000000000
+            000000ac16a6020000ab0200000000000000007c1164173c0000008c7674
+            01000000000000000000006a0100000000000000007c03a6010000ab0100
+            000000000000007d0367007d127c0344005dc07d1167007d137407000000
+            00000000000000740b000000000000000000007405000000000000000000
+            007c11a6010000ab0100000000000000007405000000000000000000007c
+            08a6010000ab0100000000000000007a0b0000a6010000ab010000000000
+            00000064187a0a0000a6010000ab01000000000000000044005d6a7d1467
+            007d157407000000000000000000007c147405000000000000000000007c
+            08a6010000ab0100000000000000007a0500007c1464187a000000740500
+            0000000000000000007c08a6010000ab0100000000000000007a050000a6
+            020000ab02000000000000000044005d1d7d167c15a00600000000000000
+            000000000000000000000000007c117c1619000000000000000000a60100
+            00ab01000000000000000001008c1e7c13a0060000000000000000000000
+            0000000000000000007c15a6010000ab01000000000000000001008c6b7c
+            12a00600000000000000000000000000000000000000007c13a6010000ab
+            01000000000000000001008cc17401000000000000000000006a01000000
+            00000000007c12a6010000ab0100000000000000007d03641989177c067c
+            017c037c047c057c077c087c097c0a7c0b6702641a9c0b5300
                        0 MAKE_CELL               23 (GP)
                        2 MAKE_CELL               24 (gp_analog_lbl_i)
                        4 MAKE_CELL               25 (gp_point_lbl_i)
          
           83           6 RESUME                   0
          
           84           8 LOAD_FAST                0 (result)
@@ -834,814 +838,852 @@
           90         104 LOAD_GLOBAL              1 (NULL + np)
                      116 LOAD_ATTR                1 (array)
                      126 LOAD_FAST                1 (Point)
                      128 PRECALL                  1
                      132 CALL                     1
                      142 STORE_FAST               6 (Real_Markers)
          
-          91         144 LOAD_FAST                6 (Real_Markers)
-                     146 LOAD_CONST               0 (None)
-                     148 LOAD_CONST               0 (None)
-                     150 BUILD_SLICE              2
-                     152 LOAD_FAST                2 (Real_marker_index)
-                     154 LOAD_CONST               0 (None)
-                     156 LOAD_CONST               0 (None)
-                     158 BUILD_SLICE              2
-                     160 BUILD_TUPLE              3
-                     162 BINARY_SUBSCR
-                     172 STORE_FAST               6 (Real_Markers)
-         
-          92         174 LOAD_FAST                6 (Real_Markers)
-                     176 LOAD_FAST                0 (result)
-                     178 LOAD_CONST               7 ('Markers')
-                     180 STORE_SUBSCR
-         
-          95         184 LOAD_CLOSURE            23 (GP)
-                     186 BUILD_TUPLE              1
-                     188 LOAD_CONST               8 (<code object <listcomp>, file "\Python311\Lib\site-packages\pyc3dtools\pyc3dtools.py", line 95>)
-                     190 MAKE_FUNCTION            8 (closure)
-         
-          96         192 LOAD_GLOBAL              5 (NULL + range)
-                     204 LOAD_GLOBAL              7 (NULL + len)
-                     216 LOAD_DEREF              23 (GP)
-                     218 PRECALL                  1
-                     222 CALL                     1
-                     232 PRECALL                  1
-                     236 CALL                     1
-         
-          95         246 GET_ITER
-                     248 PRECALL                  0
-                     252 CALL                     0
-         
-          98         262 LOAD_CONST               9 (0)
-         
-          95         264 BINARY_SUBSCR
-                     274 STORE_DEREF             25 (gp_point_lbl_i)
-         
-          99         276 LOAD_CLOSURE            23 (GP)
-                     278 LOAD_CLOSURE            25 (gp_point_lbl_i)
-                     280 BUILD_TUPLE              2
-                     282 LOAD_CONST              10 (<code object <listcomp>, file "\Python311\Lib\site-packages\pyc3dtools\pyc3dtools.py", line 99>)
-                     284 MAKE_FUNCTION            8 (closure)
-         
-         100         286 LOAD_GLOBAL              5 (NULL + range)
-                     298 LOAD_GLOBAL              7 (NULL + len)
-                     310 LOAD_DEREF              23 (GP)
-                     312 LOAD_DEREF              25 (gp_point_lbl_i)
-                     314 BINARY_SUBSCR
-                     324 LOAD_CONST              11 ('List_Parameters')
-                     326 BINARY_SUBSCR
-                     336 PRECALL                  1
-                     340 CALL                     1
-                     350 PRECALL                  1
-                     354 CALL                     1
-         
-          99         364 GET_ITER
-                     366 PRECALL                  0
-                     370 CALL                     0
-         
-         102         380 LOAD_CONST               9 (0)
-         
-          99         382 BINARY_SUBSCR
-                     392 STORE_FAST               7 (gp_point_lbl_ii)
-         
-         103         394 LOAD_CLOSURE            23 (GP)
-                     396 LOAD_CLOSURE            25 (gp_point_lbl_i)
-                     398 BUILD_TUPLE              2
-                     400 LOAD_CONST              12 (<code object <listcomp>, file "\Python311\Lib\site-packages\pyc3dtools\pyc3dtools.py", line 103>)
-                     402 MAKE_FUNCTION            8 (closure)
-         
-         104         404 LOAD_GLOBAL              5 (NULL + range)
-                     416 LOAD_GLOBAL              7 (NULL + len)
-                     428 LOAD_DEREF              23 (GP)
-                     430 LOAD_DEREF              25 (gp_point_lbl_i)
-                     432 BINARY_SUBSCR
-                     442 LOAD_CONST              11 ('List_Parameters')
-                     444 BINARY_SUBSCR
-                     454 PRECALL                  1
-                     458 CALL                     1
-                     468 PRECALL                  1
-                     472 CALL                     1
-         
-         103         482 GET_ITER
-                     484 PRECALL                  0
-                     488 CALL                     0
-         
-         106         498 LOAD_CONST               9 (0)
-         
-         103         500 BINARY_SUBSCR
-                     510 STORE_FAST               8 (gp_point_unit_i)
-         
-         107         512 LOAD_CLOSURE            23 (GP)
-                     514 LOAD_CLOSURE            25 (gp_point_lbl_i)
-                     516 BUILD_TUPLE              2
-                     518 LOAD_CONST              13 (<code object <listcomp>, file "\Python311\Lib\site-packages\pyc3dtools\pyc3dtools.py", line 107>)
-                     520 MAKE_FUNCTION            8 (closure)
-         
-         108         522 LOAD_GLOBAL              5 (NULL + range)
-                     534 LOAD_GLOBAL              7 (NULL + len)
-                     546 LOAD_DEREF              23 (GP)
-                     548 LOAD_DEREF              25 (gp_point_lbl_i)
-                     550 BINARY_SUBSCR
-                     560 LOAD_CONST              11 ('List_Parameters')
-                     562 BINARY_SUBSCR
-                     572 PRECALL                  1
-                     576 CALL                     1
-                     586 PRECALL                  1
-                     590 CALL                     1
-         
-         107         600 GET_ITER
-                     602 PRECALL                  0
-                     606 CALL                     0
-         
-         110         616 LOAD_CONST               9 (0)
-         
-         107         618 BINARY_SUBSCR
-                     628 STORE_FAST               9 (gp_point_Yscreen_i)
-         
-         111         630 LOAD_CLOSURE            23 (GP)
-                     632 LOAD_CLOSURE            25 (gp_point_lbl_i)
-                     634 BUILD_TUPLE              2
-                     636 LOAD_CONST              14 (<code object <listcomp>, file "\Python311\Lib\site-packages\pyc3dtools\pyc3dtools.py", line 111>)
-                     638 MAKE_FUNCTION            8 (closure)
-         
-         112         640 LOAD_GLOBAL              5 (NULL + range)
-                     652 LOAD_GLOBAL              7 (NULL + len)
-                     664 LOAD_DEREF              23 (GP)
-                     666 LOAD_DEREF              25 (gp_point_lbl_i)
-                     668 BINARY_SUBSCR
-                     678 LOAD_CONST              11 ('List_Parameters')
-                     680 BINARY_SUBSCR
-                     690 PRECALL                  1
-                     694 CALL                     1
-                     704 PRECALL                  1
-                     708 CALL                     1
-         
-         111         718 GET_ITER
-                     720 PRECALL                  0
-                     724 CALL                     0
+          91         144 BUILD_LIST               0
+                     146 STORE_FAST               7 (Markers_lbl)
          
-         114         734 LOAD_CONST               9 (0)
+          92         148 BUILD_LIST               0
+                     150 STORE_FAST               8 (Analog_lbl)
          
-         111         736 BINARY_SUBSCR
-                     746 STORE_FAST              10 (gp_point_Xscreen_i)
+          93         152 LOAD_CONST               7 ('')
+                     154 STORE_FAST               9 (Markers_Units)
          
-         115         748 LOAD_DEREF              23 (GP)
-                     750 LOAD_DEREF              25 (gp_point_lbl_i)
+          94         156 LOAD_CONST               7 ('')
+                     158 STORE_FAST              10 (Markers_XSCREEN)
+         
+          95         160 LOAD_CONST               7 ('')
+                     162 STORE_FAST              11 (Markers_YSCREEN)
+         
+          98         164 LOAD_GLOBAL              5 (NULL + len)
+                     176 LOAD_FAST                1 (Point)
+                     178 LOAD_CONST               8 (0)
+                     180 BINARY_SUBSCR
+                     190 PRECALL                  1
+                     194 CALL                     1
+                     204 LOAD_CONST               8 (0)
+                     206 COMPARE_OP               4 (>)
+                     212 EXTENDED_ARG             1
+                     214 POP_JUMP_FORWARD_IF_FALSE   424 (to 1064)
+         
+          99         216 LOAD_FAST                6 (Real_Markers)
+                     218 LOAD_CONST               0 (None)
+                     220 LOAD_CONST               0 (None)
+                     222 BUILD_SLICE              2
+                     224 LOAD_FAST                2 (Real_marker_index)
+                     226 LOAD_CONST               0 (None)
+                     228 LOAD_CONST               0 (None)
+                     230 BUILD_SLICE              2
+                     232 BUILD_TUPLE              3
+                     234 BINARY_SUBSCR
+                     244 STORE_FAST               6 (Real_Markers)
+         
+         100         246 LOAD_FAST                6 (Real_Markers)
+                     248 LOAD_FAST                0 (result)
+                     250 LOAD_CONST               9 ('Markers')
+                     252 STORE_SUBSCR
+         
+         103         256 LOAD_CLOSURE            23 (GP)
+                     258 BUILD_TUPLE              1
+                     260 LOAD_CONST              10 (<code object <listcomp>, file "\Python311\Lib\site-packages\pyc3dtools\pyc3dtools.py", line 103>)
+                     262 MAKE_FUNCTION            8 (closure)
+         
+         104         264 LOAD_GLOBAL              7 (NULL + range)
+                     276 LOAD_GLOBAL              5 (NULL + len)
+                     288 LOAD_DEREF              23 (GP)
+                     290 PRECALL                  1
+                     294 CALL                     1
+                     304 PRECALL                  1
+                     308 CALL                     1
+         
+         103         318 GET_ITER
+                     320 PRECALL                  0
+                     324 CALL                     0
+         
+         106         334 LOAD_CONST               8 (0)
+         
+         103         336 BINARY_SUBSCR
+                     346 STORE_DEREF             25 (gp_point_lbl_i)
+         
+         107         348 LOAD_CLOSURE            23 (GP)
+                     350 LOAD_CLOSURE            25 (gp_point_lbl_i)
+                     352 BUILD_TUPLE              2
+                     354 LOAD_CONST              11 (<code object <listcomp>, file "\Python311\Lib\site-packages\pyc3dtools\pyc3dtools.py", line 107>)
+                     356 MAKE_FUNCTION            8 (closure)
+         
+         108         358 LOAD_GLOBAL              7 (NULL + range)
+                     370 LOAD_GLOBAL              5 (NULL + len)
+                     382 LOAD_DEREF              23 (GP)
+                     384 LOAD_DEREF              25 (gp_point_lbl_i)
+                     386 BINARY_SUBSCR
+                     396 LOAD_CONST              12 ('List_Parameters')
+                     398 BINARY_SUBSCR
+                     408 PRECALL                  1
+                     412 CALL                     1
+                     422 PRECALL                  1
+                     426 CALL                     1
+         
+         107         436 GET_ITER
+                     438 PRECALL                  0
+                     442 CALL                     0
+         
+         110         452 LOAD_CONST               8 (0)
+         
+         107         454 BINARY_SUBSCR
+                     464 STORE_FAST              12 (gp_point_lbl_ii)
+         
+         111         466 LOAD_CLOSURE            23 (GP)
+                     468 LOAD_CLOSURE            25 (gp_point_lbl_i)
+                     470 BUILD_TUPLE              2
+                     472 LOAD_CONST              13 (<code object <listcomp>, file "\Python311\Lib\site-packages\pyc3dtools\pyc3dtools.py", line 111>)
+                     474 MAKE_FUNCTION            8 (closure)
+         
+         112         476 LOAD_GLOBAL              7 (NULL + range)
+                     488 LOAD_GLOBAL              5 (NULL + len)
+                     500 LOAD_DEREF              23 (GP)
+                     502 LOAD_DEREF              25 (gp_point_lbl_i)
+                     504 BINARY_SUBSCR
+                     514 LOAD_CONST              12 ('List_Parameters')
+                     516 BINARY_SUBSCR
+                     526 PRECALL                  1
+                     530 CALL                     1
+                     540 PRECALL                  1
+                     544 CALL                     1
+         
+         111         554 GET_ITER
+                     556 PRECALL                  0
+                     560 CALL                     0
+         
+         114         570 LOAD_CONST               8 (0)
+         
+         111         572 BINARY_SUBSCR
+                     582 STORE_FAST              13 (gp_point_unit_i)
+         
+         115         584 LOAD_CLOSURE            23 (GP)
+                     586 LOAD_CLOSURE            25 (gp_point_lbl_i)
+                     588 BUILD_TUPLE              2
+                     590 LOAD_CONST              14 (<code object <listcomp>, file "\Python311\Lib\site-packages\pyc3dtools\pyc3dtools.py", line 115>)
+                     592 MAKE_FUNCTION            8 (closure)
+         
+         116         594 LOAD_GLOBAL              7 (NULL + range)
+                     606 LOAD_GLOBAL              5 (NULL + len)
+                     618 LOAD_DEREF              23 (GP)
+                     620 LOAD_DEREF              25 (gp_point_lbl_i)
+                     622 BINARY_SUBSCR
+                     632 LOAD_CONST              12 ('List_Parameters')
+                     634 BINARY_SUBSCR
+                     644 PRECALL                  1
+                     648 CALL                     1
+                     658 PRECALL                  1
+                     662 CALL                     1
+         
+         115         672 GET_ITER
+                     674 PRECALL                  0
+                     678 CALL                     0
+         
+         118         688 LOAD_CONST               8 (0)
+         
+         115         690 BINARY_SUBSCR
+                     700 STORE_FAST              14 (gp_point_Yscreen_i)
+         
+         119         702 LOAD_CLOSURE            23 (GP)
+                     704 LOAD_CLOSURE            25 (gp_point_lbl_i)
+                     706 BUILD_TUPLE              2
+                     708 LOAD_CONST              15 (<code object <listcomp>, file "\Python311\Lib\site-packages\pyc3dtools\pyc3dtools.py", line 119>)
+                     710 MAKE_FUNCTION            8 (closure)
+         
+         120         712 LOAD_GLOBAL              7 (NULL + range)
+                     724 LOAD_GLOBAL              5 (NULL + len)
+                     736 LOAD_DEREF              23 (GP)
+                     738 LOAD_DEREF              25 (gp_point_lbl_i)
+                     740 BINARY_SUBSCR
+                     750 LOAD_CONST              12 ('List_Parameters')
                      752 BINARY_SUBSCR
-                     762 LOAD_CONST              11 ('List_Parameters')
-                     764 BINARY_SUBSCR
-                     774 LOAD_FAST                7 (gp_point_lbl_ii)
-                     776 BINARY_SUBSCR
-                     786 LOAD_CONST              15 ('Param_data')
-                     788 BINARY_SUBSCR
-                     798 STORE_FAST              11 (Markers_lbl)
-         
-         116         800 LOAD_DEREF              23 (GP)
-                     802 LOAD_DEREF              25 (gp_point_lbl_i)
-                     804 BINARY_SUBSCR
-                     814 LOAD_CONST              11 ('List_Parameters')
-                     816 BINARY_SUBSCR
-                     826 LOAD_FAST                8 (gp_point_unit_i)
-                     828 BINARY_SUBSCR
-                     838 LOAD_CONST              15 ('Param_data')
-                     840 BINARY_SUBSCR
-                     850 LOAD_CONST               9 (0)
-                     852 BINARY_SUBSCR
-                     862 STORE_FAST              12 (Markers_Units)
-         
-         117         864 LOAD_DEREF              23 (GP)
-                     866 LOAD_DEREF              25 (gp_point_lbl_i)
-                     868 BINARY_SUBSCR
-                     878 LOAD_CONST              11 ('List_Parameters')
-                     880 BINARY_SUBSCR
-                     890 LOAD_FAST                9 (gp_point_Yscreen_i)
-                     892 BINARY_SUBSCR
-                     902 LOAD_CONST              15 ('Param_data')
-                     904 BINARY_SUBSCR
-                     914 LOAD_CONST               9 (0)
-                     916 BINARY_SUBSCR
-                     926 STORE_FAST              13 (Markers_YSCREEN)
-         
-         118         928 LOAD_DEREF              23 (GP)
-                     930 LOAD_DEREF              25 (gp_point_lbl_i)
-                     932 BINARY_SUBSCR
-                     942 LOAD_CONST              11 ('List_Parameters')
-                     944 BINARY_SUBSCR
-                     954 LOAD_FAST               10 (gp_point_Xscreen_i)
-                     956 BINARY_SUBSCR
-                     966 LOAD_CONST              15 ('Param_data')
-                     968 BINARY_SUBSCR
-                     978 LOAD_CONST               9 (0)
-                     980 BINARY_SUBSCR
-                     990 STORE_FAST              14 (Markers_XSCREEN)
-         
-         121         992 LOAD_CLOSURE            23 (GP)
-                     994 BUILD_TUPLE              1
-                     996 LOAD_CONST              16 (<code object <listcomp>, file "\Python311\Lib\site-packages\pyc3dtools\pyc3dtools.py", line 121>)
-                     998 MAKE_FUNCTION            8 (closure)
-         
-         122        1000 LOAD_GLOBAL              5 (NULL + range)
-                    1012 LOAD_GLOBAL              7 (NULL + len)
-                    1024 LOAD_DEREF              23 (GP)
-                    1026 PRECALL                  1
-                    1030 CALL                     1
-                    1040 PRECALL                  1
-                    1044 CALL                     1
-         
-         121        1054 GET_ITER
-                    1056 PRECALL                  0
-                    1060 CALL                     0
-         
-         124        1070 LOAD_CONST               9 (0)
-         
-         121        1072 BINARY_SUBSCR
-                    1082 STORE_DEREF             24 (gp_analog_lbl_i)
-         
-         125        1084 LOAD_CLOSURE            23 (GP)
-                    1086 LOAD_CLOSURE            24 (gp_analog_lbl_i)
-                    1088 BUILD_TUPLE              2
-                    1090 LOAD_CONST              17 (<code object <listcomp>, file "\Python311\Lib\site-packages\pyc3dtools\pyc3dtools.py", line 125>)
-                    1092 MAKE_FUNCTION            8 (closure)
-         
-         126        1094 LOAD_GLOBAL              5 (NULL + range)
-                    1106 LOAD_GLOBAL              7 (NULL + len)
-                    1118 LOAD_DEREF              23 (GP)
-                    1120 LOAD_DEREF              24 (gp_analog_lbl_i)
-                    1122 BINARY_SUBSCR
-                    1132 LOAD_CONST              11 ('List_Parameters')
-                    1134 BINARY_SUBSCR
-                    1144 PRECALL                  1
-                    1148 CALL                     1
-                    1158 PRECALL                  1
-                    1162 CALL                     1
-         
-         125        1172 GET_ITER
-                    1174 PRECALL                  0
-                    1178 CALL                     0
-         
-         128        1188 LOAD_CONST               9 (0)
-         
-         125        1190 BINARY_SUBSCR
-                    1200 STORE_FAST              15 (gp_analog_lbl_ii)
-         
-         129        1202 LOAD_DEREF              23 (GP)
-                    1204 LOAD_DEREF              24 (gp_analog_lbl_i)
-                    1206 BINARY_SUBSCR
-                    1216 LOAD_CONST              11 ('List_Parameters')
-                    1218 BINARY_SUBSCR
-                    1228 LOAD_FAST               15 (gp_analog_lbl_ii)
-                    1230 BINARY_SUBSCR
-                    1240 LOAD_CONST              15 ('Param_data')
-                    1242 BINARY_SUBSCR
-                    1252 STORE_FAST              16 (Analog_lbl)
-         
-         133        1254 LOAD_FAST                5 (Forceplates)
-                    1256 GET_ITER
-                 >> 1258 FOR_ITER               117 (to 1494)
-                    1260 STORE_FAST              17 (f)
-         
-         134        1262 LOAD_FAST               17 (f)
-                    1264 LOAD_CONST              18 ('orgin')
-                    1266 BINARY_SUBSCR
-                    1276 LOAD_FAST               17 (f)
-                    1278 LOAD_CONST              19 ('Origin')
-                    1280 STORE_SUBSCR
-         
-         135        1284 LOAD_GLOBAL              1 (NULL + np)
-                    1296 LOAD_ATTR                1 (array)
-                    1306 LOAD_FAST               17 (f)
-                    1308 LOAD_CONST              20 ('COP')
-                    1310 BINARY_SUBSCR
-                    1320 LOAD_CONST               0 (None)
-                    1322 LOAD_CONST               0 (None)
-                    1324 BUILD_SLICE              2
-                    1326 BINARY_SUBSCR
-                    1336 LOAD_CONST               0 (None)
-                    1338 LOAD_CONST               0 (None)
-                    1340 BUILD_SLICE              2
+                     762 PRECALL                  1
+                     766 CALL                     1
+                     776 PRECALL                  1
+                     780 CALL                     1
+         
+         119         790 GET_ITER
+                     792 PRECALL                  0
+                     796 CALL                     0
+         
+         122         806 LOAD_CONST               8 (0)
+         
+         119         808 BINARY_SUBSCR
+                     818 STORE_FAST              15 (gp_point_Xscreen_i)
+         
+         123         820 LOAD_DEREF              23 (GP)
+                     822 LOAD_DEREF              25 (gp_point_lbl_i)
+                     824 BINARY_SUBSCR
+                     834 LOAD_CONST              12 ('List_Parameters')
+                     836 BINARY_SUBSCR
+                     846 LOAD_FAST               12 (gp_point_lbl_ii)
+                     848 BINARY_SUBSCR
+                     858 LOAD_CONST              16 ('Param_data')
+                     860 BINARY_SUBSCR
+                     870 STORE_FAST               7 (Markers_lbl)
+         
+         124         872 LOAD_DEREF              23 (GP)
+                     874 LOAD_DEREF              25 (gp_point_lbl_i)
+                     876 BINARY_SUBSCR
+                     886 LOAD_CONST              12 ('List_Parameters')
+                     888 BINARY_SUBSCR
+                     898 LOAD_FAST               13 (gp_point_unit_i)
+                     900 BINARY_SUBSCR
+                     910 LOAD_CONST              16 ('Param_data')
+                     912 BINARY_SUBSCR
+                     922 LOAD_CONST               8 (0)
+                     924 BINARY_SUBSCR
+                     934 STORE_FAST               9 (Markers_Units)
+         
+         125         936 LOAD_DEREF              23 (GP)
+                     938 LOAD_DEREF              25 (gp_point_lbl_i)
+                     940 BINARY_SUBSCR
+                     950 LOAD_CONST              12 ('List_Parameters')
+                     952 BINARY_SUBSCR
+                     962 LOAD_FAST               14 (gp_point_Yscreen_i)
+                     964 BINARY_SUBSCR
+                     974 LOAD_CONST              16 ('Param_data')
+                     976 BINARY_SUBSCR
+                     986 LOAD_CONST               8 (0)
+                     988 BINARY_SUBSCR
+                     998 STORE_FAST              11 (Markers_YSCREEN)
+         
+         126        1000 LOAD_DEREF              23 (GP)
+                    1002 LOAD_DEREF              25 (gp_point_lbl_i)
+                    1004 BINARY_SUBSCR
+                    1014 LOAD_CONST              12 ('List_Parameters')
+                    1016 BINARY_SUBSCR
+                    1026 LOAD_FAST               15 (gp_point_Xscreen_i)
+                    1028 BINARY_SUBSCR
+                    1038 LOAD_CONST              16 ('Param_data')
+                    1040 BINARY_SUBSCR
+                    1050 LOAD_CONST               8 (0)
+                    1052 BINARY_SUBSCR
+                    1062 STORE_FAST              10 (Markers_XSCREEN)
+         
+         130     >> 1064 LOAD_GLOBAL              5 (NULL + len)
+                    1076 LOAD_FAST                3 (Analog)
+                    1078 LOAD_CONST               8 (0)
+                    1080 BINARY_SUBSCR
+                    1090 PRECALL                  1
+                    1094 CALL                     1
+                    1104 LOAD_CONST               8 (0)
+                    1106 COMPARE_OP               4 (>)
+                    1112 EXTENDED_ARG             1
+                    1114 POP_JUMP_FORWARD_IF_FALSE   488 (to 2092)
+         
+         131        1116 LOAD_CLOSURE            23 (GP)
+                    1118 BUILD_TUPLE              1
+                    1120 LOAD_CONST              17 (<code object <listcomp>, file "\Python311\Lib\site-packages\pyc3dtools\pyc3dtools.py", line 131>)
+                    1122 MAKE_FUNCTION            8 (closure)
+         
+         132        1124 LOAD_GLOBAL              7 (NULL + range)
+                    1136 LOAD_GLOBAL              5 (NULL + len)
+                    1148 LOAD_DEREF              23 (GP)
+                    1150 PRECALL                  1
+                    1154 CALL                     1
+                    1164 PRECALL                  1
+                    1168 CALL                     1
+         
+         131        1178 GET_ITER
+                    1180 PRECALL                  0
+                    1184 CALL                     0
+         
+         134        1194 LOAD_CONST               8 (0)
+         
+         131        1196 BINARY_SUBSCR
+                    1206 STORE_DEREF             24 (gp_analog_lbl_i)
+         
+         135        1208 LOAD_CLOSURE            23 (GP)
+                    1210 LOAD_CLOSURE            24 (gp_analog_lbl_i)
+                    1212 BUILD_TUPLE              2
+                    1214 LOAD_CONST              18 (<code object <listcomp>, file "\Python311\Lib\site-packages\pyc3dtools\pyc3dtools.py", line 135>)
+                    1216 MAKE_FUNCTION            8 (closure)
+         
+         136        1218 LOAD_GLOBAL              7 (NULL + range)
+                    1230 LOAD_GLOBAL              5 (NULL + len)
+                    1242 LOAD_DEREF              23 (GP)
+                    1244 LOAD_DEREF              24 (gp_analog_lbl_i)
+                    1246 BINARY_SUBSCR
+                    1256 LOAD_CONST              12 ('List_Parameters')
+                    1258 BINARY_SUBSCR
+                    1268 PRECALL                  1
+                    1272 CALL                     1
+                    1282 PRECALL                  1
+                    1286 CALL                     1
+         
+         135        1296 GET_ITER
+                    1298 PRECALL                  0
+                    1302 CALL                     0
+         
+         138        1312 LOAD_CONST               8 (0)
+         
+         135        1314 BINARY_SUBSCR
+                    1324 STORE_FAST              16 (gp_analog_lbl_ii)
+         
+         139        1326 LOAD_DEREF              23 (GP)
+                    1328 LOAD_DEREF              24 (gp_analog_lbl_i)
+                    1330 BINARY_SUBSCR
+                    1340 LOAD_CONST              12 ('List_Parameters')
                     1342 BINARY_SUBSCR
-                    1352 LOAD_GLOBAL              8 (object)
-                    1364 KW_NAMES                21
-                    1366 PRECALL                  2
-                    1370 CALL                     2
-                    1380 LOAD_FAST               17 (f)
-                    1382 LOAD_CONST              20 ('COP')
-                    1384 STORE_SUBSCR
-         
-         136        1388 LOAD_GLOBAL              1 (NULL + np)
-                    1400 LOAD_ATTR                1 (array)
-                    1410 LOAD_FAST               17 (f)
-                    1412 LOAD_CONST              22 ('GRF_VECTOR')
-                    1414 BINARY_SUBSCR
-                    1424 LOAD_CONST               0 (None)
-                    1426 LOAD_CONST               0 (None)
-                    1428 BUILD_SLICE              2
-                    1430 BINARY_SUBSCR
-                    1440 LOAD_CONST               0 (None)
-                    1442 LOAD_CONST               0 (None)
-                    1444 BUILD_SLICE              2
-                    1446 BINARY_SUBSCR
-                    1456 LOAD_GLOBAL              8 (object)
-                    1468 KW_NAMES                21
-                    1470 PRECALL                  2
-                    1474 CALL                     2
-                    1484 LOAD_FAST               17 (f)
-                    1486 LOAD_CONST              22 ('GRF_VECTOR')
-                    1488 STORE_SUBSCR
-                    1492 JUMP_BACKWARD          118 (to 1258)
-         
-         140     >> 1494 LOAD_GLOBAL              1 (NULL + np)
-                    1506 LOAD_ATTR                1 (array)
-                    1516 LOAD_FAST                3 (Analog)
-                    1518 PRECALL                  1
-                    1522 CALL                     1
-                    1532 STORE_FAST               3 (Analog)
-         
-         141        1534 BUILD_LIST               0
-                    1536 STORE_FAST              18 (NewAnalog)
-         
-         142        1538 LOAD_FAST                3 (Analog)
-                    1540 GET_ITER
-                 >> 1542 FOR_ITER               192 (to 1928)
-                    1544 STORE_FAST              17 (f)
-         
-         143        1546 BUILD_LIST               0
-                    1548 STORE_FAST              19 (main_row)
-         
-         144        1550 LOAD_GLOBAL              5 (NULL + range)
-                    1562 LOAD_GLOBAL             11 (NULL + int)
-                    1574 LOAD_GLOBAL              7 (NULL + len)
-                    1586 LOAD_FAST               17 (f)
-                    1588 PRECALL                  1
-                    1592 CALL                     1
-                    1602 LOAD_GLOBAL              7 (NULL + len)
-                    1614 LOAD_FAST               16 (Analog_lbl)
-                    1616 PRECALL                  1
-                    1620 CALL                     1
-                    1630 BINARY_OP               11 (/)
-                    1634 PRECALL                  1
-                    1638 CALL                     1
-                    1648 LOAD_CONST              23 (1)
-                    1650 BINARY_OP               10 (-)
-                    1654 PRECALL                  1
-                    1658 CALL                     1
-                    1668 GET_ITER
-                 >> 1670 FOR_ITER               106 (to 1884)
-                    1672 STORE_FAST              20 (j)
-         
-         145        1674 BUILD_LIST               0
-                    1676 STORE_FAST              21 (row)
-         
-         146        1678 LOAD_GLOBAL              5 (NULL + range)
-                    1690 LOAD_FAST               20 (j)
-                    1692 LOAD_GLOBAL              7 (NULL + len)
-                    1704 LOAD_FAST               16 (Analog_lbl)
-                    1706 PRECALL                  1
-                    1710 CALL                     1
-                    1720 BINARY_OP                5 (*)
-                    1724 LOAD_FAST               20 (j)
-                    1726 LOAD_CONST              23 (1)
-                    1728 BINARY_OP                0 (+)
-                    1732 LOAD_GLOBAL              7 (NULL + len)
-                    1744 LOAD_FAST               16 (Analog_lbl)
-                    1746 PRECALL                  1
-                    1750 CALL                     1
-                    1760 BINARY_OP                5 (*)
-                    1764 PRECALL                  2
-                    1768 CALL                     2
-                    1778 GET_ITER
-                 >> 1780 FOR_ITER                29 (to 1840)
-                    1782 STORE_FAST              22 (k)
-         
-         147        1784 LOAD_FAST               21 (row)
-                    1786 LOAD_METHOD              6 (append)
-                    1808 LOAD_FAST               17 (f)
-                    1810 LOAD_FAST               22 (k)
-                    1812 BINARY_SUBSCR
-                    1822 PRECALL                  1
-                    1826 CALL                     1
-                    1836 POP_TOP
-                    1838 JUMP_BACKWARD           30 (to 1780)
-         
-         148     >> 1840 LOAD_FAST               19 (main_row)
-                    1842 LOAD_METHOD              6 (append)
-                    1864 LOAD_FAST               21 (row)
-                    1866 PRECALL                  1
-                    1870 CALL                     1
-                    1880 POP_TOP
-                    1882 JUMP_BACKWARD          107 (to 1670)
-         
-         150     >> 1884 LOAD_FAST               18 (NewAnalog)
-                    1886 LOAD_METHOD              6 (append)
-                    1908 LOAD_FAST               19 (main_row)
-                    1910 PRECALL                  1
-                    1914 CALL                     1
-                    1924 POP_TOP
-                    1926 JUMP_BACKWARD          193 (to 1542)
-         
-         152     >> 1928 LOAD_GLOBAL              1 (NULL + np)
-                    1940 LOAD_ATTR                1 (array)
-                    1950 LOAD_FAST               18 (NewAnalog)
-                    1952 PRECALL                  1
-                    1956 CALL                     1
-                    1966 STORE_FAST               3 (Analog)
-         
-         156        1968 LOAD_CONST              24 ('Success')
-         
-         157        1970 LOAD_DEREF              23 (GP)
-         
-         158        1972 LOAD_FAST                6 (Real_Markers)
-         
-         159        1974 LOAD_FAST                1 (Point)
-         
-         160        1976 LOAD_FAST                3 (Analog)
-         
-         161        1978 LOAD_FAST                4 (Header)
-         
-         162        1980 LOAD_FAST                5 (Forceplates)
-         
-         163        1982 LOAD_FAST               11 (Markers_lbl)
-         
-         164        1984 LOAD_FAST               16 (Analog_lbl)
-         
-         165        1986 LOAD_FAST               12 (Markers_Units)
-         
-         166        1988 LOAD_FAST               14 (Markers_XSCREEN)
-                    1990 LOAD_FAST               13 (Markers_YSCREEN)
-                    1992 BUILD_LIST               2
-         
-         155        1994 LOAD_CONST              25 (('Status', 'GP', 'Markers', 'Points', 'Analog', 'Header', 'ForcePlate', 'Markers Label', 'Analog Label', 'Units', 'Coordinate system'))
-                    1996 BUILD_CONST_KEY_MAP     11
-                    1998 RETURN_VALUE
+                    1352 LOAD_FAST               16 (gp_analog_lbl_ii)
+                    1354 BINARY_SUBSCR
+                    1364 LOAD_CONST              16 ('Param_data')
+                    1366 BINARY_SUBSCR
+                    1376 STORE_FAST               8 (Analog_lbl)
+         
+         143        1378 LOAD_FAST                5 (Forceplates)
+                    1380 GET_ITER
+                 >> 1382 FOR_ITER               117 (to 1618)
+                    1384 STORE_FAST              17 (f)
+         
+         144        1386 LOAD_FAST               17 (f)
+                    1388 LOAD_CONST              19 ('orgin')
+                    1390 BINARY_SUBSCR
+                    1400 LOAD_FAST               17 (f)
+                    1402 LOAD_CONST              20 ('Origin')
+                    1404 STORE_SUBSCR
+         
+         145        1408 LOAD_GLOBAL              1 (NULL + np)
+                    1420 LOAD_ATTR                1 (array)
+                    1430 LOAD_FAST               17 (f)
+                    1432 LOAD_CONST              21 ('COP')
+                    1434 BINARY_SUBSCR
+                    1444 LOAD_CONST               0 (None)
+                    1446 LOAD_CONST               0 (None)
+                    1448 BUILD_SLICE              2
+                    1450 BINARY_SUBSCR
+                    1460 LOAD_CONST               0 (None)
+                    1462 LOAD_CONST               0 (None)
+                    1464 BUILD_SLICE              2
+                    1466 BINARY_SUBSCR
+                    1476 LOAD_GLOBAL              8 (object)
+                    1488 KW_NAMES                22
+                    1490 PRECALL                  2
+                    1494 CALL                     2
+                    1504 LOAD_FAST               17 (f)
+                    1506 LOAD_CONST              21 ('COP')
+                    1508 STORE_SUBSCR
+         
+         146        1512 LOAD_GLOBAL              1 (NULL + np)
+                    1524 LOAD_ATTR                1 (array)
+                    1534 LOAD_FAST               17 (f)
+                    1536 LOAD_CONST              23 ('GRF_VECTOR')
+                    1538 BINARY_SUBSCR
+                    1548 LOAD_CONST               0 (None)
+                    1550 LOAD_CONST               0 (None)
+                    1552 BUILD_SLICE              2
+                    1554 BINARY_SUBSCR
+                    1564 LOAD_CONST               0 (None)
+                    1566 LOAD_CONST               0 (None)
+                    1568 BUILD_SLICE              2
+                    1570 BINARY_SUBSCR
+                    1580 LOAD_GLOBAL              8 (object)
+                    1592 KW_NAMES                22
+                    1594 PRECALL                  2
+                    1598 CALL                     2
+                    1608 LOAD_FAST               17 (f)
+                    1610 LOAD_CONST              23 ('GRF_VECTOR')
+                    1612 STORE_SUBSCR
+                    1616 JUMP_BACKWARD          118 (to 1382)
+         
+         150     >> 1618 LOAD_GLOBAL              1 (NULL + np)
+                    1630 LOAD_ATTR                1 (array)
+                    1640 LOAD_FAST                3 (Analog)
+                    1642 PRECALL                  1
+                    1646 CALL                     1
+                    1656 STORE_FAST               3 (Analog)
+         
+         151        1658 BUILD_LIST               0
+                    1660 STORE_FAST              18 (NewAnalog)
+         
+         152        1662 LOAD_FAST                3 (Analog)
+                    1664 GET_ITER
+                 >> 1666 FOR_ITER               192 (to 2052)
+                    1668 STORE_FAST              17 (f)
+         
+         153        1670 BUILD_LIST               0
+                    1672 STORE_FAST              19 (main_row)
+         
+         154        1674 LOAD_GLOBAL              7 (NULL + range)
+                    1686 LOAD_GLOBAL             11 (NULL + int)
+                    1698 LOAD_GLOBAL              5 (NULL + len)
+                    1710 LOAD_FAST               17 (f)
+                    1712 PRECALL                  1
+                    1716 CALL                     1
+                    1726 LOAD_GLOBAL              5 (NULL + len)
+                    1738 LOAD_FAST                8 (Analog_lbl)
+                    1740 PRECALL                  1
+                    1744 CALL                     1
+                    1754 BINARY_OP               11 (/)
+                    1758 PRECALL                  1
+                    1762 CALL                     1
+                    1772 LOAD_CONST              24 (1)
+                    1774 BINARY_OP               10 (-)
+                    1778 PRECALL                  1
+                    1782 CALL                     1
+                    1792 GET_ITER
+                 >> 1794 FOR_ITER               106 (to 2008)
+                    1796 STORE_FAST              20 (j)
+         
+         155        1798 BUILD_LIST               0
+                    1800 STORE_FAST              21 (row)
+         
+         156        1802 LOAD_GLOBAL              7 (NULL + range)
+                    1814 LOAD_FAST               20 (j)
+                    1816 LOAD_GLOBAL              5 (NULL + len)
+                    1828 LOAD_FAST                8 (Analog_lbl)
+                    1830 PRECALL                  1
+                    1834 CALL                     1
+                    1844 BINARY_OP                5 (*)
+                    1848 LOAD_FAST               20 (j)
+                    1850 LOAD_CONST              24 (1)
+                    1852 BINARY_OP                0 (+)
+                    1856 LOAD_GLOBAL              5 (NULL + len)
+                    1868 LOAD_FAST                8 (Analog_lbl)
+                    1870 PRECALL                  1
+                    1874 CALL                     1
+                    1884 BINARY_OP                5 (*)
+                    1888 PRECALL                  2
+                    1892 CALL                     2
+                    1902 GET_ITER
+                 >> 1904 FOR_ITER                29 (to 1964)
+                    1906 STORE_FAST              22 (k)
+         
+         157        1908 LOAD_FAST               21 (row)
+                    1910 LOAD_METHOD              6 (append)
+                    1932 LOAD_FAST               17 (f)
+                    1934 LOAD_FAST               22 (k)
+                    1936 BINARY_SUBSCR
+                    1946 PRECALL                  1
+                    1950 CALL                     1
+                    1960 POP_TOP
+                    1962 JUMP_BACKWARD           30 (to 1904)
+         
+         158     >> 1964 LOAD_FAST               19 (main_row)
+                    1966 LOAD_METHOD              6 (append)
+                    1988 LOAD_FAST               21 (row)
+                    1990 PRECALL                  1
+                    1994 CALL                     1
+                    2004 POP_TOP
+                    2006 JUMP_BACKWARD          107 (to 1794)
+         
+         160     >> 2008 LOAD_FAST               18 (NewAnalog)
+                    2010 LOAD_METHOD              6 (append)
+                    2032 LOAD_FAST               19 (main_row)
+                    2034 PRECALL                  1
+                    2038 CALL                     1
+                    2048 POP_TOP
+                    2050 JUMP_BACKWARD          193 (to 1666)
+         
+         162     >> 2052 LOAD_GLOBAL              1 (NULL + np)
+                    2064 LOAD_ATTR                1 (array)
+                    2074 LOAD_FAST               18 (NewAnalog)
+                    2076 PRECALL                  1
+                    2080 CALL                     1
+                    2090 STORE_FAST               3 (Analog)
+         
+         166     >> 2092 LOAD_CONST              25 ('Success')
+         
+         167        2094 LOAD_DEREF              23 (GP)
+         
+         168        2096 LOAD_FAST                6 (Real_Markers)
+         
+         169        2098 LOAD_FAST                1 (Point)
+         
+         170        2100 LOAD_FAST                3 (Analog)
+         
+         171        2102 LOAD_FAST                4 (Header)
+         
+         172        2104 LOAD_FAST                5 (Forceplates)
+         
+         173        2106 LOAD_FAST                7 (Markers_lbl)
+         
+         174        2108 LOAD_FAST                8 (Analog_lbl)
+         
+         175        2110 LOAD_FAST                9 (Markers_Units)
+         
+         176        2112 LOAD_FAST               10 (Markers_XSCREEN)
+                    2114 LOAD_FAST               11 (Markers_YSCREEN)
+                    2116 BUILD_LIST               2
+         
+         165        2118 LOAD_CONST              26 (('Status', 'GP', 'Markers', 'Points', 'Analog', 'Header', 'ForcePlate', 'Markers Label', 'Analog Label', 'Units', 'Coordinate system'))
+                    2120 BUILD_CONST_KEY_MAP     11
+                    2122 RETURN_VALUE
          consts
             None
             'GP'
             'Point'
             'Real_marker_index'
             'Analog'
             'Header'
             'Forceplate_list'
+            ''
+            0
             'Markers'
             code
                argcount  : 1
                nlocals   : 2
                stacksize : 4
                flags     : 19
                code
                   0x9501970067007c005d167d0189027c0119000000000000000000640019
                   00000000000000000064016b0200000000af147c0191028c175300
                              0 COPY_FREE_VARS           1
                
-                95           2 RESUME                   0
+               103           2 RESUME                   0
                              4 BUILD_LIST               0
                              6 LOAD_FAST                0 (.0)
                        >>    8 FOR_ITER                22 (to 54)
                
-                96          10 STORE_FAST               1 (index)
+               104          10 STORE_FAST               1 (index)
                
-                97          12 LOAD_DEREF               2 (GP)
+               105          12 LOAD_DEREF               2 (GP)
                             14 LOAD_FAST                1 (index)
                             16 BINARY_SUBSCR
                             26 LOAD_CONST               0 ('Group_Name')
                             28 BINARY_SUBSCR
                             38 LOAD_CONST               1 ('POINT')
                             40 COMPARE_OP               2 (==)
                
-                95          46 POP_JUMP_BACKWARD_IF_FALSE    20 (to 8)
+               103          46 POP_JUMP_BACKWARD_IF_FALSE    20 (to 8)
                
-                96          48 LOAD_FAST                1 (index)
+               104          48 LOAD_FAST                1 (index)
                
-                95          50 LIST_APPEND              2
+               103          50 LIST_APPEND              2
                             52 JUMP_BACKWARD           23 (to 8)
                        >>   54 RETURN_VALUE
                consts
                   'Group_Name'
                   'POINT'
                names      ()
                varnames   ('.0', 'index')
                freevars   ('GP',)
                cellvars   ()
                filename   '\\Python311\\Lib\\site-packages\\pyc3dtools\\pyc3dtools.py'
                name       '<listcomp>'
-               firstlineno 95
+               firstlineno 103
                lnotab 0x0a01020122fe020102ff
-            0
             code
                argcount  : 1
                nlocals   : 2
                stacksize : 4
                flags     : 19
                code
                   0x9502970067007c005d227d018902890319000000000000000000640019
                   0000000000000000007c0119000000000000000000640119000000000000
                   00000064026b0200000000af207c0191028c235300
                              0 COPY_FREE_VARS           2
                
-                99           2 RESUME                   0
+               107           2 RESUME                   0
                              4 BUILD_LIST               0
                              6 LOAD_FAST                0 (.0)
                        >>    8 FOR_ITER                34 (to 78)
                
-               100          10 STORE_FAST               1 (index)
+               108          10 STORE_FAST               1 (index)
                
-               101          12 LOAD_DEREF               2 (GP)
+               109          12 LOAD_DEREF               2 (GP)
                             14 LOAD_DEREF               3 (gp_point_lbl_i)
                             16 BINARY_SUBSCR
                             26 LOAD_CONST               0 ('List_Parameters')
                             28 BINARY_SUBSCR
                             38 LOAD_FAST                1 (index)
                             40 BINARY_SUBSCR
                             50 LOAD_CONST               1 ('Param_Name')
                             52 BINARY_SUBSCR
                             62 LOAD_CONST               2 ('LABELS')
                             64 COMPARE_OP               2 (==)
                
-                99          70 POP_JUMP_BACKWARD_IF_FALSE    32 (to 8)
+               107          70 POP_JUMP_BACKWARD_IF_FALSE    32 (to 8)
                
-               100          72 LOAD_FAST                1 (index)
+               108          72 LOAD_FAST                1 (index)
                
-                99          74 LIST_APPEND              2
+               107          74 LIST_APPEND              2
                             76 JUMP_BACKWARD           35 (to 8)
                        >>   78 RETURN_VALUE
                consts
                   'List_Parameters'
                   'Param_Name'
                   'LABELS'
                names      ()
                varnames   ('.0', 'index')
                freevars   ('GP', 'gp_point_lbl_i')
                cellvars   ()
                filename   '\\Python311\\Lib\\site-packages\\pyc3dtools\\pyc3dtools.py'
                name       '<listcomp>'
-               firstlineno 99
+               firstlineno 107
                lnotab 0x0a0102013afe020102ff
             'List_Parameters'
             code
                argcount  : 1
                nlocals   : 2
                stacksize : 4
                flags     : 19
                code
                   0x9502970067007c005d227d018902890319000000000000000000640019
                   0000000000000000007c0119000000000000000000640119000000000000
                   00000064026b0200000000af207c0191028c235300
                              0 COPY_FREE_VARS           2
                
-               103           2 RESUME                   0
+               111           2 RESUME                   0
                              4 BUILD_LIST               0
                              6 LOAD_FAST                0 (.0)
                        >>    8 FOR_ITER                34 (to 78)
                
-               104          10 STORE_FAST               1 (index)
+               112          10 STORE_FAST               1 (index)
                
-               105          12 LOAD_DEREF               2 (GP)
+               113          12 LOAD_DEREF               2 (GP)
                             14 LOAD_DEREF               3 (gp_point_lbl_i)
                             16 BINARY_SUBSCR
                             26 LOAD_CONST               0 ('List_Parameters')
                             28 BINARY_SUBSCR
                             38 LOAD_FAST                1 (index)
                             40 BINARY_SUBSCR
                             50 LOAD_CONST               1 ('Param_Name')
                             52 BINARY_SUBSCR
                             62 LOAD_CONST               2 ('UNITS')
                             64 COMPARE_OP               2 (==)
                
-               103          70 POP_JUMP_BACKWARD_IF_FALSE    32 (to 8)
+               111          70 POP_JUMP_BACKWARD_IF_FALSE    32 (to 8)
                
-               104          72 LOAD_FAST                1 (index)
+               112          72 LOAD_FAST                1 (index)
                
-               103          74 LIST_APPEND              2
+               111          74 LIST_APPEND              2
                             76 JUMP_BACKWARD           35 (to 8)
                        >>   78 RETURN_VALUE
                consts
                   'List_Parameters'
                   'Param_Name'
                   'UNITS'
                names      ()
                varnames   ('.0', 'index')
                freevars   ('GP', 'gp_point_lbl_i')
                cellvars   ()
                filename   '\\Python311\\Lib\\site-packages\\pyc3dtools\\pyc3dtools.py'
                name       '<listcomp>'
-               firstlineno 103
+               firstlineno 111
                lnotab 0x0a0102013afe020102ff
             code
                argcount  : 1
                nlocals   : 2
                stacksize : 4
                flags     : 19
                code
                   0x9502970067007c005d227d018902890319000000000000000000640019
                   0000000000000000007c0119000000000000000000640119000000000000
                   00000064026b0200000000af207c0191028c235300
                              0 COPY_FREE_VARS           2
                
-               107           2 RESUME                   0
+               115           2 RESUME                   0
                              4 BUILD_LIST               0
                              6 LOAD_FAST                0 (.0)
                        >>    8 FOR_ITER                34 (to 78)
                
-               108          10 STORE_FAST               1 (index)
+               116          10 STORE_FAST               1 (index)
                
-               109          12 LOAD_DEREF               2 (GP)
+               117          12 LOAD_DEREF               2 (GP)
                             14 LOAD_DEREF               3 (gp_point_lbl_i)
                             16 BINARY_SUBSCR
                             26 LOAD_CONST               0 ('List_Parameters')
                             28 BINARY_SUBSCR
                             38 LOAD_FAST                1 (index)
                             40 BINARY_SUBSCR
                             50 LOAD_CONST               1 ('Param_Name')
                             52 BINARY_SUBSCR
                             62 LOAD_CONST               2 ('Y_SCREEN')
                             64 COMPARE_OP               2 (==)
                
-               107          70 POP_JUMP_BACKWARD_IF_FALSE    32 (to 8)
+               115          70 POP_JUMP_BACKWARD_IF_FALSE    32 (to 8)
                
-               108          72 LOAD_FAST                1 (index)
+               116          72 LOAD_FAST                1 (index)
                
-               107          74 LIST_APPEND              2
+               115          74 LIST_APPEND              2
                             76 JUMP_BACKWARD           35 (to 8)
                        >>   78 RETURN_VALUE
                consts
                   'List_Parameters'
                   'Param_Name'
                   'Y_SCREEN'
                names      ()
                varnames   ('.0', 'index')
                freevars   ('GP', 'gp_point_lbl_i')
                cellvars   ()
                filename   '\\Python311\\Lib\\site-packages\\pyc3dtools\\pyc3dtools.py'
                name       '<listcomp>'
-               firstlineno 107
+               firstlineno 115
                lnotab 0x0a0102013afe020102ff
             code
                argcount  : 1
                nlocals   : 2
                stacksize : 4
                flags     : 19
                code
                   0x9502970067007c005d227d018902890319000000000000000000640019
                   0000000000000000007c0119000000000000000000640119000000000000
                   00000064026b0200000000af207c0191028c235300
                              0 COPY_FREE_VARS           2
                
-               111           2 RESUME                   0
+               119           2 RESUME                   0
                              4 BUILD_LIST               0
                              6 LOAD_FAST                0 (.0)
                        >>    8 FOR_ITER                34 (to 78)
                
-               112          10 STORE_FAST               1 (index)
+               120          10 STORE_FAST               1 (index)
                
-               113          12 LOAD_DEREF               2 (GP)
+               121          12 LOAD_DEREF               2 (GP)
                             14 LOAD_DEREF               3 (gp_point_lbl_i)
                             16 BINARY_SUBSCR
                             26 LOAD_CONST               0 ('List_Parameters')
                             28 BINARY_SUBSCR
                             38 LOAD_FAST                1 (index)
                             40 BINARY_SUBSCR
                             50 LOAD_CONST               1 ('Param_Name')
                             52 BINARY_SUBSCR
                             62 LOAD_CONST               2 ('X_SCREEN')
                             64 COMPARE_OP               2 (==)
                
-               111          70 POP_JUMP_BACKWARD_IF_FALSE    32 (to 8)
+               119          70 POP_JUMP_BACKWARD_IF_FALSE    32 (to 8)
                
-               112          72 LOAD_FAST                1 (index)
+               120          72 LOAD_FAST                1 (index)
                
-               111          74 LIST_APPEND              2
+               119          74 LIST_APPEND              2
                             76 JUMP_BACKWARD           35 (to 8)
                        >>   78 RETURN_VALUE
                consts
                   'List_Parameters'
                   'Param_Name'
                   'X_SCREEN'
                names      ()
                varnames   ('.0', 'index')
                freevars   ('GP', 'gp_point_lbl_i')
                cellvars   ()
                filename   '\\Python311\\Lib\\site-packages\\pyc3dtools\\pyc3dtools.py'
                name       '<listcomp>'
-               firstlineno 111
+               firstlineno 119
                lnotab 0x0a0102013afe020102ff
             'Param_data'
             code
                argcount  : 1
                nlocals   : 2
                stacksize : 4
                flags     : 19
                code
                   0x9501970067007c005d167d0189027c0119000000000000000000640019
                   00000000000000000064016b0200000000af147c0191028c175300
                              0 COPY_FREE_VARS           1
                
-               121           2 RESUME                   0
+               131           2 RESUME                   0
                              4 BUILD_LIST               0
                              6 LOAD_FAST                0 (.0)
                        >>    8 FOR_ITER                22 (to 54)
                
-               122          10 STORE_FAST               1 (index)
+               132          10 STORE_FAST               1 (index)
                
-               123          12 LOAD_DEREF               2 (GP)
+               133          12 LOAD_DEREF               2 (GP)
                             14 LOAD_FAST                1 (index)
                             16 BINARY_SUBSCR
                             26 LOAD_CONST               0 ('Group_Name')
                             28 BINARY_SUBSCR
                             38 LOAD_CONST               1 ('ANALOG')
                             40 COMPARE_OP               2 (==)
                
-               121          46 POP_JUMP_BACKWARD_IF_FALSE    20 (to 8)
+               131          46 POP_JUMP_BACKWARD_IF_FALSE    20 (to 8)
                
-               122          48 LOAD_FAST                1 (index)
+               132          48 LOAD_FAST                1 (index)
                
-               121          50 LIST_APPEND              2
+               131          50 LIST_APPEND              2
                             52 JUMP_BACKWARD           23 (to 8)
                        >>   54 RETURN_VALUE
                consts
                   'Group_Name'
                   'ANALOG'
                names      ()
                varnames   ('.0', 'index')
                freevars   ('GP',)
                cellvars   ()
                filename   '\\Python311\\Lib\\site-packages\\pyc3dtools\\pyc3dtools.py'
                name       '<listcomp>'
-               firstlineno 121
+               firstlineno 131
                lnotab 0x0a01020122fe020102ff
             code
                argcount  : 1
                nlocals   : 2
                stacksize : 4
                flags     : 19
                code
                   0x9502970067007c005d227d018902890319000000000000000000640019
                   0000000000000000007c0119000000000000000000640119000000000000
                   00000064026b0200000000af207c0191028c235300
                              0 COPY_FREE_VARS           2
                
-               125           2 RESUME                   0
+               135           2 RESUME                   0
                              4 BUILD_LIST               0
                              6 LOAD_FAST                0 (.0)
                        >>    8 FOR_ITER                34 (to 78)
                
-               126          10 STORE_FAST               1 (index)
+               136          10 STORE_FAST               1 (index)
                
-               127          12 LOAD_DEREF               2 (GP)
+               137          12 LOAD_DEREF               2 (GP)
                             14 LOAD_DEREF               3 (gp_analog_lbl_i)
                             16 BINARY_SUBSCR
                             26 LOAD_CONST               0 ('List_Parameters')
                             28 BINARY_SUBSCR
                             38 LOAD_FAST                1 (index)
                             40 BINARY_SUBSCR
                             50 LOAD_CONST               1 ('Param_Name')
                             52 BINARY_SUBSCR
                             62 LOAD_CONST               2 ('LABELS')
                             64 COMPARE_OP               2 (==)
                
-               125          70 POP_JUMP_BACKWARD_IF_FALSE    32 (to 8)
+               135          70 POP_JUMP_BACKWARD_IF_FALSE    32 (to 8)
                
-               126          72 LOAD_FAST                1 (index)
+               136          72 LOAD_FAST                1 (index)
                
-               125          74 LIST_APPEND              2
+               135          74 LIST_APPEND              2
                             76 JUMP_BACKWARD           35 (to 8)
                        >>   78 RETURN_VALUE
                consts
                   'List_Parameters'
                   'Param_Name'
                   'LABELS'
                names      ()
                varnames   ('.0', 'index')
                freevars   ('GP', 'gp_analog_lbl_i')
                cellvars   ()
                filename   '\\Python311\\Lib\\site-packages\\pyc3dtools\\pyc3dtools.py'
                name       '<listcomp>'
-               firstlineno 125
+               firstlineno 135
                lnotab 0x0a0102013afe020102ff
             'orgin'
             'Origin'
             'COP'
             ('dtype',)
             'GRF_VECTOR'
             1
             'Success'
             ('Status', 'GP', 'Markers', 'Points', 'Analog', 'Header', 'ForcePlate', 'Markers Label', 'Analog Label', 'Units', 'Coordinate system')
-         names      ('np', 'array', 'range', 'len', 'object', 'int', 'append')
-         varnames   ('result', 'Point', 'Real_marker_index', 'Analog', 'Header', 'Forceplates', 'Real_Markers', 'gp_point_lbl_ii', 'gp_point_unit_i', 'gp_point_Yscreen_i', 'gp_point_Xscreen_i', 'Markers_lbl', 'Markers_Units', 'Markers_YSCREEN', 'Markers_XSCREEN', 'gp_analog_lbl_ii', 'Analog_lbl', 'f', 'NewAnalog', 'main_row', 'j', 'row', 'k')
+         names      ('np', 'array', 'len', 'range', 'object', 'int', 'append')
+         varnames   ('result', 'Point', 'Real_marker_index', 'Analog', 'Header', 'Forceplates', 'Real_Markers', 'Markers_lbl', 'Analog_lbl', 'Markers_Units', 'Markers_XSCREEN', 'Markers_YSCREEN', 'gp_point_lbl_ii', 'gp_point_unit_i', 'gp_point_Yscreen_i', 'gp_point_Xscreen_i', 'gp_analog_lbl_ii', 'f', 'NewAnalog', 'main_row', 'j', 'row', 'k')
          freevars   ()
          cellvars   ('GP', 'gp_analog_lbl_i', 'gp_point_lbl_i')
          filename   '\\Python311\\Lib\\site-packages\\pyc3dtools\\pyc3dtools.py'
          name       'GenerateOutput'
          firstlineno 83
          lnotab
-            0x080110011001100110011001100128011e010a03080136ff100302fd0c
-            040a014eff100302fd0c040a014eff100302fd0c040a014eff100302fd0c
-            040a014eff100302fd0c043401400140014003080136ff100302fd0c040a
-            014eff100302fd0c0434040801160168016a0428010401080104017c0104
-            016a0138012c022c02280402010201020102010201020102010201020102
-            0106f5
+            0x080110011001100110011001100128010401040104010401040334011e
+            010a03080136ff100302fd0c040a014eff100302fd0c040a014eff100302
+            fd0c040a014eff100302fd0c040a014eff100302fd0c0434014001400140
+            043401080136ff100302fd0c040a014eff100302fd0c0434040801160168
+            016a0428010401080104017c0104016a0138012c022c0228040201020102
+            01020102010201020102010201020106f5
    names      ('requests', 'json', 'numpy', 'np', 'os', 'tqdm', 'tqdm.utils', 'CallbackIOWrapper', 'readC3D', 'getTRCMot', 'GenerateOutput')
    varnames   ()
    freevars   ()
    cellvars   ()
    filename   '\\Python311\\Lib\\site-packages\\pyc3dtools\\pyc3dtools.py'
    name       '<module>'
    firstlineno 1
```

## Comparing `Python311/Lib/site-packages/pyc3dtools-0.2.5-py3.11.egg-info/PKG-INFO` & `Python311/Lib/site-packages/pyc3dtools-0.2.6-py3.11.egg-info/PKG-INFO`

 * *Files 0% similar despite different names*

```diff
@@ -1,10 +1,10 @@
 Metadata-Version: 2.1
 Name: pyc3dtools
-Version: 0.2.5
+Version: 0.2.6
 Summary: C3Dtools API package - Read c3d files
 Home-page: https://github.com/etoshey/pyc3dtools
 Author: Soroosh.b.k (C3Dtools.com)
 Author-email: <soroosh.b.k@gmail.com>
 License: MIT
 Keywords: python,c3d,motion capture,biomechanics
 Classifier: Development Status :: 1 - Planning
```

