# Comparing `tmp/emreader-0.1.7.tar.gz` & `tmp/emreader-0.1.8.tar.gz`

## filetype from file(1)

```diff
@@ -1 +1 @@
-gzip compressed data, was "emreader-0.1.7.tar", max compression
+gzip compressed data, was "emreader-0.1.8.tar", max compression
```

## Comparing `emreader-0.1.7.tar` & `emreader-0.1.8.tar`

### file list

```diff
@@ -1,23 +1,26 @@
--rw-r--r--   0        0        0      246 2023-06-22 19:29:06.216827 emreader-0.1.7/README.md
--rw-r--r--   0        0        0      854 2023-06-22 19:56:51.953062 emreader-0.1.7/pyproject.toml
--rw-r--r--   0        0        0        0 2023-06-20 17:45:55.551587 emreader-0.1.7/src/__init__.py
--rw-r--r--   0        0        0     3677 2023-06-22 19:50:55.518572 emreader-0.1.7/src/app.py
--rw-r--r--   0        0        0        0 2023-06-22 19:19:46.699802 emreader-0.1.7/src/core/__init__.py
--rw-r--r--   0        0        0      143 2023-06-22 19:52:00.056298 emreader-0.1.7/src/core/__pycache__/__init__.cpython-310.pyc
--rw-r--r--   0        0        0      159 2023-06-22 19:35:57.735123 emreader-0.1.7/src/core/__pycache__/__init__.cpython-311.pyc
--rw-r--r--   0        0        0     4303 2023-06-22 19:52:00.059538 emreader-0.1.7/src/core/__pycache__/base.cpython-310.pyc
--rw-r--r--   0        0        0     8713 2023-06-22 19:35:57.738541 emreader-0.1.7/src/core/__pycache__/base.cpython-311.pyc
--rw-r--r--   0        0        0     2204 2023-06-22 19:52:01.171812 emreader-0.1.7/src/core/__pycache__/eml.cpython-310.pyc
--rw-r--r--   0        0        0     4634 2023-06-22 19:37:13.102413 emreader-0.1.7/src/core/__pycache__/eml.cpython-311.pyc
--rw-r--r--   0        0        0     1818 2023-06-22 19:52:01.169455 emreader-0.1.7/src/core/__pycache__/parse_tab.cpython-310.pyc
--rw-r--r--   0        0        0     3256 2023-06-22 19:37:13.099936 emreader-0.1.7/src/core/__pycache__/parse_tab.cpython-311.pyc
--rw-r--r--   0        0        0     3538 2023-06-22 19:52:01.170857 emreader-0.1.7/src/core/__pycache__/util.cpython-310.pyc
--rw-r--r--   0        0        0     7680 2023-06-22 19:37:13.101358 emreader-0.1.7/src/core/__pycache__/util.cpython-311.pyc
--rw-r--r--   0        0        0     6062 2023-06-22 19:51:14.534375 emreader-0.1.7/src/core/base.py
--rw-r--r--   0        0        0     2257 2023-06-22 19:20:24.473512 emreader-0.1.7/src/core/eml.py
--rw-r--r--   0        0        0     2326 2023-06-20 18:53:15.483548 emreader-0.1.7/src/core/parse_tab.py
--rw-r--r--   0        0        0     5540 2023-06-20 18:45:11.583746 emreader-0.1.7/src/core/util.py
--rw-r--r--   0        0        0      189 2023-06-22 19:51:55.311457 emreader-0.1.7/src/runner.py
--rw-r--r--   0        0        0        0 2023-06-22 19:55:56.070115 emreader-0.1.7/src/storage/output/.gitkeep
--rw-r--r--   0        0        0        0 2023-06-22 19:56:09.592388 emreader-0.1.7/src/storage/source/emails/.gitkeep
--rw-r--r--   0        0        0     1725 1970-01-01 00:00:00.000000 emreader-0.1.7/PKG-INFO
+-rw-r--r--   0        0        0      246 2023-06-22 19:29:06.216827 emreader-0.1.8/README.md
+-rw-r--r--   0        0        0      898 2023-06-25 17:26:45.673016 emreader-0.1.8/pyproject.toml
+-rw-r--r--   0        0        0        0 2023-06-20 17:45:55.551587 emreader-0.1.8/src/__init__.py
+-rw-r--r--   0        0        0     3828 2023-06-25 17:15:52.721516 emreader-0.1.8/src/app.py
+-rw-r--r--   0        0        0        0 2023-06-22 19:19:46.699802 emreader-0.1.8/src/core/__init__.py
+-rw-r--r--   0        0        0      143 2023-06-22 19:52:00.056298 emreader-0.1.8/src/core/__pycache__/__init__.cpython-310.pyc
+-rw-r--r--   0        0        0      159 2023-06-22 19:35:57.735123 emreader-0.1.8/src/core/__pycache__/__init__.cpython-311.pyc
+-rw-r--r--   0        0        0     4388 2023-06-25 17:24:33.737509 emreader-0.1.8/src/core/__pycache__/base.cpython-310.pyc
+-rw-r--r--   0        0        0     8710 2023-06-22 20:20:06.352156 emreader-0.1.8/src/core/__pycache__/base.cpython-311.pyc
+-rw-r--r--   0        0        0     2771 2023-06-25 17:25:23.728843 emreader-0.1.8/src/core/__pycache__/eml.cpython-310.pyc
+-rw-r--r--   0        0        0     6300 2023-06-22 20:18:38.256286 emreader-0.1.8/src/core/__pycache__/eml.cpython-311.pyc
+-rw-r--r--   0        0        0     1818 2023-06-22 19:52:01.169455 emreader-0.1.8/src/core/__pycache__/parse_tab.cpython-310.pyc
+-rw-r--r--   0        0        0     3256 2023-06-22 19:37:13.099936 emreader-0.1.8/src/core/__pycache__/parse_tab.cpython-311.pyc
+-rw-r--r--   0        0        0      830 2023-06-25 17:07:44.040581 emreader-0.1.8/src/core/__pycache__/store.cpython-310.pyc
+-rw-r--r--   0        0        0     3538 2023-06-22 19:52:01.170857 emreader-0.1.8/src/core/__pycache__/util.cpython-310.pyc
+-rw-r--r--   0        0        0     7680 2023-06-22 19:37:13.101358 emreader-0.1.8/src/core/__pycache__/util.cpython-311.pyc
+-rw-r--r--   0        0        0     6204 2023-06-25 17:24:18.772026 emreader-0.1.8/src/core/base.py
+-rw-r--r--   0        0        0     3228 2023-06-25 17:25:20.263466 emreader-0.1.8/src/core/eml.py
+-rw-r--r--   0        0        0     2326 2023-06-20 18:53:15.483548 emreader-0.1.8/src/core/parse_tab.py
+-rw-r--r--   0        0        0      597 2023-06-25 17:02:25.950652 emreader-0.1.8/src/core/store.py
+-rw-r--r--   0        0        0     5540 2023-06-20 18:45:11.583746 emreader-0.1.8/src/core/util.py
+-rw-r--r--   0        0        0        0 2023-06-22 19:55:56.070115 emreader-0.1.8/src/db/.gitkeep
+-rw-r--r--   0        0        0      189 2023-06-22 19:51:55.311457 emreader-0.1.8/src/runner.py
+-rw-r--r--   0        0        0        0 2023-06-22 19:55:56.070115 emreader-0.1.8/src/storage/output/.gitkeep
+-rw-r--r--   0        0        0        0 2023-06-22 19:56:09.592388 emreader-0.1.8/src/storage/source/emails/.gitkeep
+-rw-r--r--   0        0        0     1812 1970-01-01 00:00:00.000000 emreader-0.1.8/PKG-INFO
```

### Comparing `emreader-0.1.7/pyproject.toml` & `emreader-0.1.8/pyproject.toml`

 * *Files 20% similar despite different names*

```diff
@@ -1,10 +1,10 @@
 [tool.poetry]
 name = "emreader"
-version = "0.1.7"
+version = "0.1.8"
 description = ""
 authors = ["themba <themba@advantch.com>"]
 readme = "README.md"
 license = "Commercial"
 packages = [{include = "src"}]
 
 [tool.poetry.dependencies]
@@ -28,14 +28,16 @@
 setuptools = "^67.7.2"
 tabula-py = "2.7.0"
 tzdata = "^2023.3"
 wheel = "^0.40.0"
 rich = "^13.4.2"
 streamlit = "^1.23.1"
 pymupdf = "^1.22.5"
+filestorage = "^0.0.6"
+aiofiles = "^23.1.0"
 
 [tool.poetry.scripts]
 emreader = "src.runner:run"
 
 [build-system]
 requires = ["poetry-core"]
 build-backend = "poetry.core.masonry.api"
```

### Comparing `emreader-0.1.7/src/app.py` & `emreader-0.1.8/src/app.py`

 * *Files 4% similar despite different names*

```diff
@@ -1,49 +1,49 @@
 import os
 
 import pandas as pd
 import rich
 import streamlit as st
-import zipfile
+
 from core.base import extract_from_files
 from core.util import transform_dataframe
-from core.eml import extract_emails
-
+from core.eml import extract_emails, extract_from_file
+from core import store
 
-@st.cache_data
+#@st.cache_data
 def convert_df(df):
     # IMPORTANT: Cache the conversion to prevent computation on every rerun
     return df.to_csv().encode("utf-8")
 
 
-@st.cache_data
+#@st.cache_data
 def get_emails():
     rich.print("Extracting attachments from emails")
     extract_emails()
 
-@st.cache_data
+#@st.cache_data
 def load_and_parse(pivot_value="Seller"):
     data = extract_from_files()
     rich.print("Running dataframe transformation...")
     rich.print(f"Using pivot value: {data}")
     transforms = transform_dataframe(data, pivot_value=pivot_value)
     rich.print(transforms[0],"rwa")
     rich.print(transforms[1],"format")
     return transforms
 
 
 def handle_uploaded_file(uploads, target_dir):
     for upload in uploads:
         if upload is not None:
-            if upload.name.endswith('.zip'):
-                with zipfile.ZipFile(upload, 'r') as zip_ref:
-                    zip_ref.extractall(target_dir)
-            else:
-                with open(os.path.join(target_dir, upload.name), "wb") as f:
-                    f.write(upload.getvalue())
+            #if upload.name.endswith('.zip'):
+            #    with zipfile.ZipFile(upload, 'r') as zip_ref:
+            #        zip_ref.extractall(target_dir)
+            #else:
+            #with open(os.path.join(target_dir, upload.name), "wb") as f:
+            extract_from_file(upload)
 
 
 def run_app():
     """
     Runs a small streamlit app to transform emails to df
 
     - Expects emails to be in the storage/source/emails folder.
@@ -53,15 +53,15 @@
     :return:
     """
     
     tab1, tab2 = st.tabs(["Upload", "Download"])
     
     base_dir = os.path.dirname(os.path.abspath(__file__))
     with tab1:
-        uploaded_file = st.file_uploader("Choose a file", type=['eml', 'zip'],accept_multiple_files=True)
+        uploaded_file = st.file_uploader("Choose a file", type=['eml'], accept_multiple_files=True)
         if uploaded_file is not None:
             handle_uploaded_file(uploaded_file, os.path.join(base_dir, "storage", "source", "emails"))
     
         # click to extract emails
         if st.button("Extract emails"):
             get_emails()
             rich.print("Done extracting emails")
@@ -70,15 +70,15 @@
         output_dir = os.path.join(base_dir, "storage", "output")
         files = os.listdir(output_dir)
         
         with st.expander("Uploaded files"):
             st.write("Files in the output folder:")
             # dataframe so we can show in table
             # add actions colum
-            df =  pd.DataFrame(files, columns=["Filename"])
+            df = pd.DataFrame(files, columns=["Filename"])
             # add actions column
             df["actions"] = ""
             
             st.data_editor(df, column_config={
                     "actions": st.column_config.CheckboxColumn(
                         "Delete",
                         help="Select your **favorite** widgets",
@@ -86,35 +86,36 @@
                     )
             })
         
     with tab2:
 
         st.write("App to transform emails to df")
         # inputs here for pivot value
-        option = st.selectbox(
-            "Which pivot value would you like to use?", ("Seller", "Buyer")
-        )
-    
-        df, original_df = load_and_parse(pivot_value=option)
-        st.write(df)
+        if st.button("Transform data"):
+            option = st.selectbox(
+                "Which pivot value would you like to use?", ("Seller", "Buyer")
+            )
         
-        with st.expander("Original data"):
-            st.write(
-                """
-                Here is the original dataframe:
-                It shows the data as it was extracted from the emails.
-                """
+            df, original_df = load_and_parse(pivot_value=option)
+            st.write(df)
+            
+            with st.expander("Original data"):
+                st.write(
+                    """
+                    Here is the original dataframe:
+                    It shows the data as it was extracted from the emails.
+                    """
+                )
+                st.write(original_df)
+        
+            csv = convert_df(df)
+        
+            st.download_button(
+                label="Download data as CSV",
+                data=csv,
+                file_name="sob.csv",
+                mime="text/csv",
             )
-            st.write(original_df)
-    
-        csv = convert_df(df)
-    
-        st.download_button(
-            label="Download data as CSV",
-            data=csv,
-            file_name="sob.csv",
-            mime="text/csv",
-        )
 
 
 if __name__ == "__main__":
     run_app()
```

### Comparing `emreader-0.1.7/src/core/__pycache__/base.cpython-310.pyc` & `emreader-0.1.8/src/core/__pycache__/base.cpython-310.pyc`

 * *Format-specific differences are supported for Python .pyc files but no file-specific differences were detected; falling back to a binary diff. file(1) reports: Byte-compiled Python module for CPython 3.10, timestamp-based, .py timestamp: Thu Jun 22 19:51:14 2023 UTC, .py size: 6062 bytes*

 * *Could not decompile bytecode: bad marshal data (unknown type code)*

 * *Files 12% similar despite different names*

```diff
@@ -1,269 +1,275 @@
-00000000: 6f0d 0d0a 0000 0000 32a6 9464 ae17 0000  o.......2..d....
+00000000: 6f0d 0d0a 0000 0000 4278 9864 3c18 0000  o.......Bx.d<...
 00000010: e300 0000 0000 0000 0000 0000 0000 0000  ................
-00000020: 000e 0000 0040 0000 0073 9600 0000 6400  .....@...s....d.
+00000020: 000e 0000 0040 0000 0073 ce00 0000 6400  .....@...s....d.
 00000030: 6401 6c00 5a00 6400 6401 6c01 5a01 6400  d.l.Z.d.d.l.Z.d.
 00000040: 6401 6c02 5a02 6400 6401 6c03 5a03 6400  d.l.Z.d.d.l.Z.d.
 00000050: 6402 6c04 6d05 5a05 0100 6403 6404 6c06  d.l.m.Z...d.d.l.
 00000060: 6d07 5a07 0100 6501 6a08 a009 6501 6a08  m.Z...e.j...e.j.
-00000070: a00a 650b a101 a101 5a0c 6405 6406 6407  ..e.....Z.d.d.d.
-00000080: 6408 6409 640a 640b 640c 640d 640e 640f  d.d.d.d.d.d.d.d.
-00000090: 6410 6700 6411 a201 6412 9c0d 5a0d 641c  d.g.d...d...Z.d.
-000000a0: 6414 6415 8401 5a0e 6416 6417 8400 5a0f  d.d...Z.d.d...Z.
-000000b0: 6418 6419 8400 5a10 641a 641b 8400 5a11  d.d...Z.d.d...Z.
-000000c0: 6401 5300 291d e900 0000 004e 2901 da06  d.S.)......N)...
-000000d0: 7061 7273 6572 e901 0000 00a9 01da 0850  parser.........P
-000000e0: 6172 7365 5461 62da 0131 da01 32da 0133  arseTab..1..2..3
-000000f0: da01 34da 0135 da01 36da 0137 da01 38da  ..4..5..6..7..8.
-00000100: 0139 da02 3130 da02 3131 da02 3132 2903  .9..10..11..12).
-00000110: 720f 0000 0072 1000 0000 7211 0000 0029  r....r....r....)
-00000120: 0dda 034a 414e da03 4645 42da 034d 4152  ...JAN..FEB..MAR
-00000130: da03 4150 52da 034d 4159 da03 4a55 4eda  ..APR..MAY..JUN.
-00000140: 034a 554c da03 4155 47da 0353 4550 da03  .JUL..AUG..SEP..
-00000150: 4f43 54da 034e 4f56 da03 4445 435a 034f  OCT..NOV..DECZ.O
-00000160: 4e44 da00 6302 0000 0000 0000 0000 0000  ND..c...........
-00000170: 000f 0000 0010 0000 0043 0000 0073 fc02  .........C...s..
-00000180: 0000 7c00 6401 1900 6401 1900 6401 1900  ..|.d...d...d...
-00000190: 7d02 7c00 6402 1900 6401 1900 6401 1900  }.|.d...d...d...
-000001a0: 7d03 7c00 6402 1900 6402 1900 6401 1900  }.|.d...d...d...
-000001b0: 7d04 6403 6701 7c04 a000 6404 a101 1700  }.d.g.|...d.....
-000001c0: 7d04 7c00 6402 1900 6405 6400 8502 1900  }.|.d...d.d.....
-000001d0: 7d05 7c02 6700 6406 9c02 7d06 7c05 4400  }.|.g.d...}.|.D.
-000001e0: 9001 5d14 7d07 7c07 6401 1900 a000 6404  ..].}.|.d.....d.
-000001f0: a101 7d08 6407 7c08 6401 1900 7600 72ed  ..}.d.|.d...v.r.
-00000200: 7c08 6401 1900 a000 6407 a101 7d09 7c09  |.d.....d...}.|.
-00000210: 4400 5da3 7d0a 7c0a a001 a100 73d6 7a4d  D.].}.|.....s.zM
-00000220: 7a06 7402 7c0a 1900 7d0a 5700 6e0b 0400  z.t.|...}.W.n...
-00000230: 7403 7960 0100 0100 0100 6408 7d0a 5900  t.y`......d.}.Y.
-00000240: 6e01 7700 5700 7404 7402 7c0a 1900 7405  n.w.W.t.t.|...t.
-00000250: 8302 7286 7402 7c0a 1900 4400 5d17 7d0b  ..r.t.|...D.].}.
-00000260: 7406 7407 7c04 7c0b 6701 7c08 6402 6400  t.t.|.|.g.|.d.d.
-00000270: 8502 1900 1700 8302 8301 7d0c 7c06 6409  ..........}.|.d.
-00000280: 1900 a008 7c0c a101 0100 716d 7148 7406  ....|.....qmqHt.
-00000290: 7407 7c04 7c0a 6701 7c08 6402 6400 8502  t.|.|.g.|.d.d...
-000002a0: 1900 1700 8302 8301 7d0c 7c06 6409 1900  ........}.|.d...
-000002b0: a008 7c0c a101 0100 7148 7404 7402 7c0a  ..|.....qHt.t.|.
-000002c0: 1900 7405 8302 72c0 7402 7c0a 1900 4400  ..t...r.t.|...D.
-000002d0: 5d17 7d0b 7406 7407 7c04 7c0b 6701 7c08  ].}.t.t.|.|.g.|.
-000002e0: 6402 6400 8502 1900 1700 8302 8301 7d0c  d.d...........}.
-000002f0: 7c06 6409 1900 a008 7c0c a101 0100 71a7  |.d.....|.....q.
-00000300: 7700 7406 7407 7c04 7c0a 6701 7c08 6402  w.t.t.|.|.g.|.d.
-00000310: 6400 8502 1900 1700 8302 8301 7d0c 7c06  d...........}.|.
-00000320: 6409 1900 a008 7c0c a101 0100 7700 7406  d.....|.....w.t.
-00000330: 7407 7c04 7c0a 6701 7c08 6402 6400 8502  t.|.|.g.|.d.d...
-00000340: 1900 1700 8302 8301 7d0c 7c06 6409 1900  ........}.|.d...
-00000350: a008 7c0c a101 0100 7148 712f 7402 a009  ..|.....qHq/t...
-00000360: 7c08 6401 1900 6400 a102 6400 7501 9001  |.d...d...d.u...
-00000370: 7236 7402 7c08 6401 1900 1900 7d0d 7404  r6t.|.d.....}.t.
-00000380: 7c0d 7405 8302 9001 7220 7c0d 4400 5d18  |.t.....r |.D.].
-00000390: 7d0b 7406 7407 7c04 7c0b 6701 7c08 6402  }.t.t.|.|.g.|.d.
-000003a0: 6400 8502 1900 1700 8302 8301 7d0c 7c06  d...........}.|.
-000003b0: 6409 1900 a008 7c0c a101 0100 9001 7106  d.....|.......q.
-000003c0: 712f 7406 7407 7c04 7c0d 6701 7c08 6402  q/t.t.|.|.g.|.d.
-000003d0: 6400 8502 1900 1700 8302 8301 7d0c 7c06  d...........}.|.
-000003e0: 6409 1900 a008 7c0c a101 0100 712f 7406  d.....|.....q/t.
-000003f0: 7407 7c04 7c08 8302 8301 7d0c 7c06 6409  t.|.|.....}.|.d.
-00000400: 1900 a008 7c0c a101 0100 712f 7c03 7c06  ....|.....q/|.|.
-00000410: 640a 3c00 7c06 6409 1900 4400 5d2e 7d0c  d.<.|.d...D.].}.
-00000420: 7a11 7c0c a00a 640b a101 7c0c 640c 3c00  z.|...d...|.d.<.
-00000430: 7c0c a00a 640d a101 7c0c 640e 3c00 5700  |...d...|.d.<.W.
-00000440: 9001 714d 0400 740b 9001 797b 0100 7d0e  ..qM..t...y{..}.
-00000450: 0100 7a0e 7c06 6409 1900 a00c 7c0c a101  ..z.|.d.....|...
-00000460: 0100 5700 5900 6400 7d0e 7e0e 9001 714d  ..W.Y.d.}.~...qM
-00000470: 6400 7d0e 7e0e 7701 7700 7c06 5300 290f  d.}.~.w.w.|.S.).
-00000480: 4e72 0100 0000 7203 0000 00da 056d 6f6e  Nr....r......mon
-00000490: 7468 fa01 20e9 0200 0000 2902 da04 6461  th.. .....)...da
-000004a0: 7465 da07 7265 636f 7264 73fa 012f da07  te..records../..
-000004b0: 756e 6b6e 6f77 6e72 2300 0000 da05 7469  unknownr#.....ti
-000004c0: 746c 655a 0452 6570 6cda 054f 6666 6572  tleZ.Repl..Offer
-000004d0: 5a03 4f66 66da 0643 6861 6e67 6529 0dda  Z.Off..Change)..
-000004e0: 0573 706c 6974 da09 6973 6e75 6d65 7269  .split..isnumeri
-000004f0: 63da 096d 6f6e 7468 5f6d 6170 da08 4b65  c..month_map..Ke
-00000500: 7945 7272 6f72 da0a 6973 696e 7374 616e  yError..isinstan
-00000510: 6365 da04 6c69 7374 da04 6469 6374 da03  ce..list..dict..
-00000520: 7a69 70da 0661 7070 656e 64da 0367 6574  zip..append..get
-00000530: da03 706f 70da 0945 7863 6570 7469 6f6e  ..pop..Exception
-00000540: da06 7265 6d6f 7665 290f da04 6461 7461  ..remove)...data
-00000550: da07 7061 7474 6572 6e72 2200 0000 7226  ..patternr"...r&
-00000560: 0000 00da 0768 6561 6465 7273 da04 726f  .....headers..ro
-00000570: 7773 da06 7265 7375 6c74 da03 726f 77da  ws..result..row.
-00000580: 0865 6c65 6d65 6e74 73da 066d 6f6e 7468  .elements..month
-00000590: 7372 1f00 0000 da01 6dda 0672 6563 6f72  sr......m..recor
-000005a0: 645a 0f6d 6f6e 7468 5f6f 725f 6d6f 6e74  dZ.month_or_mont
-000005b0: 6873 da01 65a9 0072 4100 0000 fa2e 2f55  hs..e..rA...../U
-000005c0: 7365 7273 2f74 6865 6d62 612f 7365 6374  sers/themba/sect
-000005d0: 696f 6e33 322f 6572 6a65 6e2f 7372 632f  ion32/erjen/src/
-000005e0: 636f 7265 2f62 6173 652e 7079 da0c 6c69  core/base.py..li
-000005f0: 7374 5f74 6f5f 6469 6374 1c00 0000 7370  st_to_dict....sp
-00000600: 0000 0010 0210 0110 0110 0110 010a 030a  ................
-00000610: 020e 020c 010e 0108 0408 0104 010c 010c  ................
-00000620: 0108 0102 ff02 800e 030c 011c 0110 0102  ................
-00000630: fe1c 0410 010e fa0c 011c 0110 0102 fe1c  ................
-00000640: 0410 011c 0310 0102 ef16 150c 010c 0108  ................
-00000650: 011c 0112 0102 fe1c 0410 010e 0310 0108  ................
-00000660: 020c 0102 010e 0214 0110 011c 0208 8002  ................
-00000670: fe04 0472 4300 0000 6301 0000 0000 0000  ...rC...c.......
-00000680: 0000 0000 0004 0000 0004 0000 0003 0000  ................
-00000690: 0073 5e00 0000 7400 a001 8800 6401 1900  .s^...t.....d...
-000006a0: 6a02 a101 0100 8800 6401 1900 6a02 6a03  j.......d...j.j.
-000006b0: 8902 8800 6401 1900 6a02 6a04 8901 8700  ....d...j.j.....
-000006c0: 8701 8702 6603 6402 6403 8408 7d01 7c01  ....f.d.d...}.|.
-000006d0: 8300 7d02 7405 a006 7c02 6401 1900 6401  ..}.t...|.d...d.
-000006e0: 1900 6401 1900 a101 a007 6404 a101 7d03  ..d.......d...}.
-000006f0: 7c03 5300 2905 4e72 0100 0000 6300 0000  |.S.).Nr....c...
-00000700: 0000 0000 0000 0000 0000 0000 0007 0000  ................
-00000710: 0013 0000 00f3 2e00 0000 7400 8800 6401  ..........t...d.
-00000720: 1900 6401 8801 6402 1400 6403 1b00 8802  ..d...d...d.....
-00000730: 6402 1400 6404 1b00 8801 6402 1400 6405  d...d.....d...d.
-00000740: 1b00 6704 8302 5300 a906 6104 0100 000a  ..g...S...a.....
-00000750: 2020 2020 2020 2020 786d 696e 3a20 3020          xmin: 0 
-00000760: 2853 7461 7274 2066 726f 6d20 7468 6520  (Start from the 
-00000770: 6c65 6674 2065 6467 6529 0a20 2020 2020  left edge).     
-00000780: 2020 2079 6d69 6e3a 2038 3431 202a 2034     ymin: 841 * 4
-00000790: 2f35 2028 5374 6172 7420 312f 3520 646f  /5 (Start 1/5 do
-000007a0: 776e 2066 726f 6d20 7468 6520 746f 702e  wn from the top.
-000007b0: 2052 656d 656d 6265 7220 7920 7661 6c75   Remember y valu
-000007c0: 6573 2069 6e63 7265 6173 6520 7570 7761  es increase upwa
-000007d0: 7264 7329 0a20 2020 2020 2020 2078 6d61  rds).        xma
-000007e0: 783a 2035 3935 202a 2031 2f35 2028 436f  x: 595 * 1/5 (Co
-000007f0: 7665 7220 312f 3520 6f66 2074 6865 2077  ver 1/5 of the w
-00000800: 6964 7468 206f 6620 7468 6520 7061 6765  idth of the page
-00000810: 290a 2020 2020 2020 2020 796d 6178 3a20  ).        ymax: 
-00000820: 3834 3120 2845 6e64 2061 7420 7468 6520  841 (End at the 
-00000830: 746f 7020 6564 6765 290a 2020 2020 2020  top edge).      
-00000840: 2020 3a72 6574 7572 6e3a 0a20 2020 2020    :return:.     
-00000850: 2020 2072 0100 0000 7203 0000 00e9 0800     r....r.......
-00000860: 0000 7221 0000 00e9 0400 0000 7204 0000  ..r!........r...
-00000870: 0072 4100 0000 a903 da03 646f 63da 0168  .rA.......doc..h
-00000880: da01 7772 4100 0000 7242 0000 00da 105f  ..wrA...rB....._
-00000890: 6461 7465 5f63 6f72 6469 6e61 7465 7366  date_cordinatesf
-000008a0: 0000 00f3 0200 0000 2e08 7a2b 6578 7472  ..........z+extr
-000008b0: 6163 745f 6669 6c65 5f64 6174 652e 3c6c  act_file_date.<l
-000008c0: 6f63 616c 733e 2e5f 6461 7465 5f63 6f72  ocals>._date_cor
-000008d0: 6469 6e61 7465 737a 0825 592d 256d 2d25  dinatesz.%Y-%m-%
-000008e0: 6429 08da 0472 6963 68da 0570 7269 6e74  d)...rich..print
-000008f0: da04 7265 6374 da05 7769 6474 68da 0668  ..rect..width..h
-00000900: 6569 6768 7472 0200 0000 da05 7061 7273  eightr......pars
-00000910: 65da 0873 7472 6674 696d 6529 0472 4900  e..strftime).rI.
-00000920: 0000 724c 0000 0072 2200 0000 5a0b 6461  ..rL...r"...Z.da
-00000930: 7465 5f64 6173 6865 6472 4100 0000 7248  te_dashedrA...rH
-00000940: 0000 0072 4200 0000 da11 6578 7472 6163  ...rB.....extrac
-00000950: 745f 6669 6c65 5f64 6174 655f 0000 0073  t_file_date_...s
-00000960: 0e00 0000 1002 0c01 0c01 1003 0609 1c01  ................
-00000970: 0401 7255 0000 0063 0100 0000 0000 0000  ..rU...c........
-00000980: 0000 0000 0400 0000 0400 0000 0300 0000  ................
-00000990: 735c 0000 0074 00a0 0188 0064 0119 006a  s\...t.....d...j
-000009a0: 02a1 0101 0088 0064 0119 006a 026a 0389  .......d...j.j..
-000009b0: 0288 0064 0119 006a 026a 0489 0187 0087  ...d...j.j......
-000009c0: 0187 0266 0364 0264 0384 087d 0187 0087  ...f.d.d...}....
-000009d0: 0187 0266 0364 0464 0584 087d 027c 0183  ...f.d.d...}.|..
-000009e0: 007c 0283 0067 027d 0374 057c 0383 0153  .|...g.}.t.|...S
-000009f0: 0029 064e 7201 0000 0063 0000 0000 0000  .).Nr....c......
-00000a00: 0000 0000 0000 0000 0000 0700 0000 1300  ................
-00000a10: 0000 7244 0000 0072 4500 0000 7204 0000  ..rD...rE...r...
-00000a20: 0072 4100 0000 7248 0000 0072 4100 0000  .rA...rH...rA...
-00000a30: 7242 0000 0072 4c00 0000 7900 0000 724d  rB...rL...y...rM
-00000a40: 0000 007a 2b65 7874 7261 6374 5f73 6f79  ...z+extract_soy
-00000a50: 5f62 6561 6e73 2e3c 6c6f 6361 6c73 3e2e  _beans.<locals>.
-00000a60: 5f64 6174 655f 636f 7264 696e 6174 6573  _date_cordinates
-00000a70: 6300 0000 0000 0000 0000 0000 0000 0000  c...............
-00000a80: 0007 0000 0013 0000 0073 2e00 0000 7400  .........s....t.
-00000a90: 8800 6401 1900 8802 6402 1400 6403 1b00  ..d.....d...d...
-00000aa0: 8801 6402 1400 6404 1b00 8802 8801 6405  ..d...d.......d.
-00000ab0: 1400 6406 1b00 6704 8302 5300 2907 610c  ..d...g...S.).a.
-00000ac0: 0100 000a 2020 2020 2020 2020 786d 696e  ....        xmin
-00000ad0: 3a20 3020 2853 7461 7274 2066 726f 6d20  : 0 (Start from 
-00000ae0: 7468 6520 6c65 6674 2065 6467 6529 0a20  the left edge). 
-00000af0: 2020 2020 2020 2079 6d69 6e3a 2038 3431         ymin: 841
-00000b00: 202a 2032 2f33 2028 5374 6172 7420 312f   * 2/3 (Start 1/
-00000b10: 3320 646f 776e 2066 726f 6d20 7468 6520  3 down from the 
-00000b20: 746f 7029 0a20 2020 2020 2020 2078 6d61  top).        xma
-00000b30: 783a 2035 3935 202a 2031 2f32 2028 436f  x: 595 * 1/2 (Co
-00000b40: 7665 7220 312f 3220 7468 6520 7769 6474  ver 1/2 the widt
-00000b50: 6820 6f66 2074 6865 2070 6167 6529 0a20  h of the page). 
-00000b60: 2020 2020 2020 2079 6d61 783a 2038 3431         ymax: 841
-00000b70: 202a 2034 2f35 2028 456e 6420 7768 6572   * 4/5 (End wher
-00000b80: 6520 7468 6520 6461 7465 2073 7461 7274  e the date start
-00000b90: 732e 2054 6869 7320 636f 756c 6420 6265  s. This could be
-00000ba0: 2061 646a 7573 7465 6420 6173 206e 6565   adjusted as nee
-00000bb0: 6465 6429 0a0a 2020 2020 2020 2020 3a72  ded)..        :r
-00000bc0: 6574 7572 6e3a 0a20 2020 2020 2020 2072  eturn:.        r
-00000bd0: 0100 0000 7203 0000 0072 2100 0000 e905  ....r....r!.....
-00000be0: 0000 00e9 0d00 0000 e920 0000 0072 0400  ......... ...r..
-00000bf0: 0000 7241 0000 0072 4800 0000 7241 0000  ..rA...rH...rA..
-00000c00: 0072 4200 0000 da13 5f73 6f79 6265 616e  .rB....._soybean
-00000c10: 5f63 6f72 6469 6e61 7465 7383 0000 0073  _cordinates....s
-00000c20: 0200 0000 2e09 7a2e 6578 7472 6163 745f  ......z.extract_
-00000c30: 736f 795f 6265 616e 732e 3c6c 6f63 616c  soy_beans.<local
-00000c40: 733e 2e5f 736f 7962 6561 6e5f 636f 7264  s>._soybean_cord
-00000c50: 696e 6174 6573 2906 724e 0000 0072 4f00  inates).rN...rO.
-00000c60: 0000 7250 0000 0072 5100 0000 7252 0000  ..rP...rQ...rR..
-00000c70: 0072 4300 0000 2904 7249 0000 0072 4c00  .rC...).rI...rL.
-00000c80: 0000 7259 0000 00da 0674 6162 6c65 7372  ..rY.....tablesr
-00000c90: 4100 0000 7248 0000 0072 4200 0000 da11  A...rH...rB.....
-00000ca0: 6578 7472 6163 745f 736f 795f 6265 616e  extract_soy_bean
-00000cb0: 7374 0000 0073 0e00 0000 1001 0c01 0c01  st...s..........
-00000cc0: 1002 100a 0c0b 0801 725b 0000 0063 0000  ........r[...c..
-00000cd0: 0000 0000 0000 0000 0000 0700 0000 0b00  ................
-00000ce0: 0000 4300 0000 73dc 0000 0074 006a 01a0  ..C...s....t.j..
-00000cf0: 0274 0364 0164 0264 03a1 047d 0074 04a0  .t.d.d.d...}.t..
-00000d00: 0474 006a 01a0 027c 0064 04a1 02a1 017d  .t.j...|.d.....}
-00000d10: 0174 05a0 0664 0574 077c 0183 019b 0064  .t...d.t.|.....d
-00000d20: 069d 03a1 0101 0067 007d 0274 077c 0183  .......g.}.t.|..
-00000d30: 0164 076b 0272 3764 0864 0964 0a64 0b64  .d.k.r7d.d.d.d.d
-00000d40: 0c64 0d64 0e64 0f64 109c 0767 0164 1164  .d.d.d.d...g.d.d
-00000d50: 1264 139c 0467 0153 007c 0144 005d 327d  .d...g.S.|.D.]2}
-00000d60: 037a 1474 08a0 097c 03a1 017d 0474 0a7c  .z.t...|...}.t.|
-00000d70: 0483 017d 057c 037c 0564 143c 007c 02a0  ...}.|.|.d.<.|..
-00000d80: 0b7c 05a1 0101 0057 0071 3904 0074 0c79  .|.....W.q9..t.y
-00000d90: 6b01 007d 0601 007a 1074 0664 157c 039b  k..}...z.t.d.|..
-00000da0: 0064 167c 069b 009d 0483 0101 0057 0059  .d.|.........W.Y
-00000db0: 0064 007d 067e 0671 3964 007d 067e 0677  .d.}.~.q9d.}.~.w
-00000dc0: 0177 007c 0253 0029 174e 7a05 2e2e 2f2e  .w.|.S.).Nz.../.
-00000dd0: 2eda 0773 746f 7261 6765 da06 6f75 7470  ...storage..outp
-00000de0: 7574 7a05 2a2e 7064 667a 0666 6f75 6e64  utz.*.pdfz.found
-00000df0: 207a 0b20 6578 7472 6163 7469 6e67 7201   z. extractingr.
-00000e00: 0000 007a 104a 756e 6520 3136 7468 202c  ...z.June 16th ,
-00000e10: 2032 3032 3372 1000 0000 7a05 2d31 3230   2023r....z.-120
-00000e20: 307a 052d 3133 3030 5a04 3130 3132 7a02  0z.-1300Z.1012z.
-00000e30: 2b39 7a13 3634 3834 3738 5f30 5f63 6c6f  +9z.648478_0_clo
-00000e40: 7365 732e 7064 667a 0731 362d 3230 3233  ses.pdfz.16-2023
-00000e50: 2907 721f 0000 00da 0653 656c 6c65 72da  ).r......Seller.
-00000e60: 0542 7579 6572 7227 0000 0072 2800 0000  .Buyerr'...r(...
-00000e70: da09 6669 6c65 5f6e 616d 655a 0973 706f  ..file_nameZ.spo
-00000e80: 745f 6461 7465 5a03 5342 4f7a 212e 2f65  t_dateZ.SBOz!./e
-00000e90: 6d6c 732f 6f75 7470 7574 2f36 3438 3437  mls/output/64847
-00000ea0: 385f 305f 636c 6f73 6573 2e70 6466 2904  8_0_closes.pdf).
-00000eb0: 7222 0000 0072 2300 0000 7226 0000 0072  r"...r#...r&...r
-00000ec0: 6000 0000 7260 0000 007a 1b45 7272 6f72  `...r`...z.Error
-00000ed0: 2065 7874 7261 6374 696e 6720 6461 7461   extracting data
-00000ee0: 2066 726f 6d20 7a02 3a20 290d da02 6f73   from z.: )...os
-00000ef0: da04 7061 7468 da04 6a6f 696e da0b 6375  ..path..join..cu
-00000f00: 7272 656e 745f 6469 72da 0467 6c6f 6272  rrent_dir..globr
-00000f10: 4e00 0000 724f 0000 00da 036c 656e da04  N...rO.....len..
-00000f20: 6669 747a 5a08 446f 6375 6d65 6e74 725b  fitzZ.Documentr[
-00000f30: 0000 0072 3100 0000 7234 0000 0029 075a  ...r1...r4...).Z
-00000f40: 0d70 6466 5f64 6972 6563 746f 7279 5a09  .pdf_directoryZ.
-00000f50: 7064 665f 6669 6c65 735a 1861 6c6c 5f66  pdf_filesZ.all_f
-00000f60: 696c 6573 5f65 7874 7261 6374 6564 5f64  iles_extracted_d
-00000f70: 6174 615a 0870 6466 5f66 696c 6572 4900  ataZ.pdf_filerI.
-00000f80: 0000 7236 0000 0072 4000 0000 7241 0000  ..r6...r@...rA..
-00000f90: 0072 4100 0000 7242 0000 00da 1265 7874  .rA...rB.....ext
-00000fa0: 7261 6374 5f66 726f 6d5f 6669 6c65 7392  ract_from_files.
-00000fb0: 0000 0073 3e00 0000 1203 1401 1601 0403  ...s>...........
-00000fc0: 0c01 0203 0203 0201 0201 0201 0201 0201  ................
-00000fd0: 0201 04f9 02ff 020b 0201 04f2 04ff 0812  ................
-00000fe0: 0202 0a01 0801 0801 0e01 0e01 1401 0c01  ................
-00000ff0: 0880 02fe 0404 7268 0000 0029 0172 1e00  ......rh...).r..
-00001000: 0000 2912 7265 0000 0072 6100 0000 7267  ..).re...ra...rg
-00001010: 0000 0072 4e00 0000 da08 6461 7465 7574  ...rN.....dateut
-00001020: 696c 7202 0000 005a 0970 6172 7365 5f74  ilr....Z.parse_t
-00001030: 6162 7205 0000 0072 6200 0000 da07 6469  abr....rb.....di
-00001040: 726e 616d 65da 0761 6273 7061 7468 da08  rname..abspath..
-00001050: 5f5f 6669 6c65 5f5f 7264 0000 0072 2b00  __file__rd...r+.
-00001060: 0000 7243 0000 0072 5500 0000 725b 0000  ..rC...rU...r[..
-00001070: 0072 6800 0000 7241 0000 0072 4100 0000  .rh...rA...rA...
-00001080: 7241 0000 0072 4200 0000 da08 3c6d 6f64  rA...rB.....<mod
-00001090: 756c 653e 0100 0000 7332 0000 0008 0008  ule>....s2......
-000010a0: 0108 0208 010c 010c 0214 0202 0202 0102  ................
-000010b0: 0102 0102 0102 0102 0102 0102 0102 0102  ................
-000010c0: 0102 0106 0106 f30a 1108 4308 150c 1e    ..........C....
+00000070: a00a 650b a101 a101 5a0c 6501 6a08 a00d  ..e.....Z.e.j...
+00000080: 650c 6405 6406 6407 6408 a105 5a0e 6501  e.d.d.d.d...Z.e.
+00000090: 6a08 a00d 650c 6405 6406 6409 a104 5a0f  j...e.d.d.d...Z.
+000000a0: 6501 6a08 a00d 650c 6405 6406 6409 a104  e.j...e.d.d.d...
+000000b0: 5a10 640a 640b 640c 640d 640e 640f 6410  Z.d.d.d.d.d.d.d.
+000000c0: 6411 6412 6413 6414 6415 6700 6416 a201  d.d.d.d.d.g.d...
+000000d0: 6417 9c0d 5a11 6421 6419 641a 8401 5a12  d...Z.d!d.d...Z.
+000000e0: 641b 641c 8400 5a13 641d 641e 8400 5a14  d.d...Z.d.d...Z.
+000000f0: 641f 6420 8400 5a15 6401 5300 2922 e900  d.d ..Z.d.S.)"..
+00000100: 0000 004e 2901 da06 7061 7273 6572 e901  ...N)...parser..
+00000110: 0000 00a9 01da 0850 6172 7365 5461 627a  .......ParseTabz
+00000120: 022e 2eda 0773 746f 7261 6765 da06 736f  .....storage..so
+00000130: 7572 6365 da06 656d 6169 6c73 da06 6f75  urce..emails..ou
+00000140: 7470 7574 da01 31da 0132 da01 33da 0134  tput..1..2..3..4
+00000150: da01 35da 0136 da01 37da 0138 da01 39da  ..5..6..7..8..9.
+00000160: 0231 30da 0231 31da 0231 3229 0372 1300  .10..11..12).r..
+00000170: 0000 7214 0000 0072 1500 0000 290d da03  ..r....r....)...
+00000180: 4a41 4eda 0346 4542 da03 4d41 52da 0341  JAN..FEB..MAR..A
+00000190: 5052 da03 4d41 59da 034a 554e da03 4a55  PR..MAY..JUN..JU
+000001a0: 4cda 0341 5547 da03 5345 50da 034f 4354  L..AUG..SEP..OCT
+000001b0: da03 4e4f 56da 0344 4543 da03 4f4e 44da  ..NOV..DEC..OND.
+000001c0: 0063 0200 0000 0000 0000 0000 0000 0f00  .c..............
+000001d0: 0000 1000 0000 4300 0000 73fc 0200 007c  ......C...s....|
+000001e0: 0064 0119 0064 0119 0064 0119 007d 027c  .d...d...d...}.|
+000001f0: 0064 0219 0064 0119 0064 0119 007d 037c  .d...d...d...}.|
+00000200: 0064 0219 0064 0219 0064 0119 007d 0464  .d...d...d...}.d
+00000210: 0367 017c 04a0 0064 04a1 0117 007d 047c  .g.|...d.....}.|
+00000220: 0064 0219 0064 0564 0085 0219 007d 057c  .d...d.d.....}.|
+00000230: 0267 0064 069c 027d 067c 0544 0090 015d  .g.d...}.|.D...]
+00000240: 147d 077c 0764 0119 00a0 0064 04a1 017d  .}.|.d.....d...}
+00000250: 0864 077c 0864 0119 0076 0072 ed7c 0864  .d.|.d...v.r.|.d
+00000260: 0119 00a0 0064 07a1 017d 097c 0944 005d  .....d...}.|.D.]
+00000270: a37d 0a7c 0aa0 01a1 0073 d67a 4d7a 0674  .}.|.....s.zMz.t
+00000280: 027c 0a19 007d 0a57 006e 0b04 0074 0379  .|...}.W.n...t.y
+00000290: 6001 0001 0001 0064 087d 0a59 006e 0177  `......d.}.Y.n.w
+000002a0: 0057 0074 0474 027c 0a19 0074 0583 0272  .W.t.t.|...t...r
+000002b0: 8674 027c 0a19 0044 005d 177d 0b74 0674  .t.|...D.].}.t.t
+000002c0: 077c 047c 0b67 017c 0864 0264 0085 0219  .|.|.g.|.d.d....
+000002d0: 0017 0083 0283 017d 0c7c 0664 0919 00a0  .......}.|.d....
+000002e0: 087c 0ca1 0101 0071 6d71 4874 0674 077c  .|.....qmqHt.t.|
+000002f0: 047c 0a67 017c 0864 0264 0085 0219 0017  .|.g.|.d.d......
+00000300: 0083 0283 017d 0c7c 0664 0919 00a0 087c  .....}.|.d.....|
+00000310: 0ca1 0101 0071 4874 0474 027c 0a19 0074  .....qHt.t.|...t
+00000320: 0583 0272 c074 027c 0a19 0044 005d 177d  ...r.t.|...D.].}
+00000330: 0b74 0674 077c 047c 0b67 017c 0864 0264  .t.t.|.|.g.|.d.d
+00000340: 0085 0219 0017 0083 0283 017d 0c7c 0664  ...........}.|.d
+00000350: 0919 00a0 087c 0ca1 0101 0071 a777 0074  .....|.....q.w.t
+00000360: 0674 077c 047c 0a67 017c 0864 0264 0085  .t.|.|.g.|.d.d..
+00000370: 0219 0017 0083 0283 017d 0c7c 0664 0919  .........}.|.d..
+00000380: 00a0 087c 0ca1 0101 0077 0074 0674 077c  ...|.....w.t.t.|
+00000390: 047c 0a67 017c 0864 0264 0085 0219 0017  .|.g.|.d.d......
+000003a0: 0083 0283 017d 0c7c 0664 0919 00a0 087c  .....}.|.d.....|
+000003b0: 0ca1 0101 0071 4871 2f74 02a0 097c 0864  .....qHq/t...|.d
+000003c0: 0119 0064 00a1 0264 0075 0190 0172 3674  ...d...d.u...r6t
+000003d0: 027c 0864 0119 0019 007d 0d74 047c 0d74  .|.d.....}.t.|.t
+000003e0: 0583 0290 0172 207c 0d44 005d 187d 0b74  .....r |.D.].}.t
+000003f0: 0674 077c 047c 0b67 017c 0864 0264 0085  .t.|.|.g.|.d.d..
+00000400: 0219 0017 0083 0283 017d 0c7c 0664 0919  .........}.|.d..
+00000410: 00a0 087c 0ca1 0101 0090 0171 0671 2f74  ...|.......q.q/t
+00000420: 0674 077c 047c 0d67 017c 0864 0264 0085  .t.|.|.g.|.d.d..
+00000430: 0219 0017 0083 0283 017d 0c7c 0664 0919  .........}.|.d..
+00000440: 00a0 087c 0ca1 0101 0071 2f74 0674 077c  ...|.....q/t.t.|
+00000450: 047c 0883 0283 017d 0c7c 0664 0919 00a0  .|.....}.|.d....
+00000460: 087c 0ca1 0101 0071 2f7c 037c 0664 0a3c  .|.....q/|.|.d.<
+00000470: 007c 0664 0919 0044 005d 2e7d 0c7a 117c  .|.d...D.].}.z.|
+00000480: 0ca0 0a64 0ba1 017c 0c64 0c3c 007c 0ca0  ...d...|.d.<.|..
+00000490: 0a64 0da1 017c 0c64 0e3c 0057 0090 0171  .d...|.d.<.W...q
+000004a0: 4d04 0074 0b90 0179 7b01 007d 0e01 007a  M..t...y{..}...z
+000004b0: 0e7c 0664 0919 00a0 0c7c 0ca1 0101 0057  .|.d.....|.....W
+000004c0: 0059 0064 007d 0e7e 0e90 0171 4d64 007d  .Y.d.}.~...qMd.}
+000004d0: 0e7e 0e77 0177 007c 0653 0029 0f4e 7201  .~.w.w.|.S.).Nr.
+000004e0: 0000 0072 0300 0000 da05 6d6f 6e74 68fa  ...r......month.
+000004f0: 0120 e902 0000 0029 02da 0464 6174 65da  . .....)...date.
+00000500: 0772 6563 6f72 6473 fa01 2fda 0775 6e6b  .records../..unk
+00000510: 6e6f 776e 7228 0000 00da 0574 6974 6c65  nownr(.....title
+00000520: da04 5265 706c da05 4f66 6665 72da 034f  ..Repl..Offer..O
+00000530: 6666 da06 4368 616e 6765 290d da05 7370  ff..Change)...sp
+00000540: 6c69 74da 0969 736e 756d 6572 6963 da09  lit..isnumeric..
+00000550: 6d6f 6e74 685f 6d61 70da 084b 6579 4572  month_map..KeyEr
+00000560: 726f 72da 0a69 7369 6e73 7461 6e63 65da  ror..isinstance.
+00000570: 046c 6973 74da 0464 6963 74da 037a 6970  .list..dict..zip
+00000580: da06 6170 7065 6e64 da03 6765 74da 0370  ..append..get..p
+00000590: 6f70 da09 4578 6365 7074 696f 6eda 0672  op..Exception..r
+000005a0: 656d 6f76 6529 0fda 0464 6174 61da 0770  emove)...data..p
+000005b0: 6174 7465 726e 7227 0000 0072 2b00 0000  atternr'...r+...
+000005c0: da07 6865 6164 6572 73da 0472 6f77 73da  ..headers..rows.
+000005d0: 0672 6573 756c 74da 0372 6f77 da08 656c  .result..row..el
+000005e0: 656d 656e 7473 da06 6d6f 6e74 6873 7224  ements..monthsr$
+000005f0: 0000 00da 016d da06 7265 636f 7264 da0f  .....m..record..
+00000600: 6d6f 6e74 685f 6f72 5f6d 6f6e 7468 73da  month_or_months.
+00000610: 0165 a900 7249 0000 00fa 2e2f 5573 6572  .e..rI...../User
+00000620: 732f 7468 656d 6261 2f73 6563 7469 6f6e  s/themba/section
+00000630: 3332 2f65 726a 656e 2f73 7263 2f63 6f72  32/erjen/src/cor
+00000640: 652f 6261 7365 2e70 79da 0c6c 6973 745f  e/base.py..list_
+00000650: 746f 5f64 6963 7420 0000 0073 7000 0000  to_dict ...sp...
+00000660: 1002 1001 1001 1001 1001 0a03 0a02 0e02  ................
+00000670: 0c01 0e01 0804 0801 0401 0c01 0c01 0801  ................
+00000680: 02ff 0280 0e03 0c01 1c01 1001 02fe 1c04  ................
+00000690: 1001 0efa 0c01 1c01 1001 02fe 1c04 1001  ................
+000006a0: 1c03 1001 02ef 1615 0c01 0c01 0801 1c01  ................
+000006b0: 1201 02fe 1c04 1001 0e03 1001 0802 0c01  ................
+000006c0: 0201 0e02 1401 1001 1c02 0880 02fe 0404  ................
+000006d0: 724b 0000 0063 0100 0000 0000 0000 0000  rK...c..........
+000006e0: 0000 0400 0000 0400 0000 0300 0000 735e  ..............s^
+000006f0: 0000 0074 00a0 0188 0064 0119 006a 02a1  ...t.....d...j..
+00000700: 0101 0088 0064 0119 006a 026a 0389 0288  .....d...j.j....
+00000710: 0064 0119 006a 026a 0489 0187 0087 0187  .d...j.j........
+00000720: 0266 0364 0264 0384 087d 017c 0183 007d  .f.d.d...}.|...}
+00000730: 0274 05a0 067c 0264 0119 0064 0119 0064  .t...|.d...d...d
+00000740: 0119 00a1 01a0 0764 04a1 017d 037c 0353  .......d...}.|.S
+00000750: 0029 054e 7201 0000 0063 0000 0000 0000  .).Nr....c......
+00000760: 0000 0000 0000 0000 0000 0700 0000 1300  ................
+00000770: 0000 f32e 0000 0074 0088 0064 0119 0064  .......t...d...d
+00000780: 0188 0164 0214 0064 031b 0088 0264 0214  ...d...d.....d..
+00000790: 0064 041b 0088 0164 0214 0064 051b 0067  .d.....d...d...g
+000007a0: 0483 0253 00a9 0661 0401 0000 0a20 2020  ...S...a.....   
+000007b0: 2020 2020 2078 6d69 6e3a 2030 2028 5374       xmin: 0 (St
+000007c0: 6172 7420 6672 6f6d 2074 6865 206c 6566  art from the lef
+000007d0: 7420 6564 6765 290a 2020 2020 2020 2020  t edge).        
+000007e0: 796d 696e 3a20 3834 3120 2a20 342f 3520  ymin: 841 * 4/5 
+000007f0: 2853 7461 7274 2031 2f35 2064 6f77 6e20  (Start 1/5 down 
+00000800: 6672 6f6d 2074 6865 2074 6f70 2e20 5265  from the top. Re
+00000810: 6d65 6d62 6572 2079 2076 616c 7565 7320  member y values 
+00000820: 696e 6372 6561 7365 2075 7077 6172 6473  increase upwards
+00000830: 290a 2020 2020 2020 2020 786d 6178 3a20  ).        xmax: 
+00000840: 3539 3520 2a20 312f 3520 2843 6f76 6572  595 * 1/5 (Cover
+00000850: 2031 2f35 206f 6620 7468 6520 7769 6474   1/5 of the widt
+00000860: 6820 6f66 2074 6865 2070 6167 6529 0a20  h of the page). 
+00000870: 2020 2020 2020 2079 6d61 783a 2038 3431         ymax: 841
+00000880: 2028 456e 6420 6174 2074 6865 2074 6f70   (End at the top
+00000890: 2065 6467 6529 0a20 2020 2020 2020 203a   edge).        :
+000008a0: 7265 7475 726e 3a0a 2020 2020 2020 2020  return:.        
+000008b0: 7201 0000 0072 0300 0000 e908 0000 0072  r....r.........r
+000008c0: 2600 0000 e904 0000 0072 0400 0000 7249  &........r....rI
+000008d0: 0000 00a9 03da 0364 6f63 da01 68da 0177  .......doc..h..w
+000008e0: 7249 0000 0072 4a00 0000 da10 5f64 6174  rI...rJ....._dat
+000008f0: 655f 636f 7264 696e 6174 6573 6a00 0000  e_cordinatesj...
+00000900: f302 0000 002e 087a 2b65 7874 7261 6374  .......z+extract
+00000910: 5f66 696c 655f 6461 7465 2e3c 6c6f 6361  _file_date.<loca
+00000920: 6c73 3e2e 5f64 6174 655f 636f 7264 696e  ls>._date_cordin
+00000930: 6174 6573 7a08 2559 2d25 6d2d 2564 2908  atesz.%Y-%m-%d).
+00000940: da04 7269 6368 da05 7072 696e 74da 0472  ..rich..print..r
+00000950: 6563 74da 0577 6964 7468 da06 6865 6967  ect..width..heig
+00000960: 6874 7202 0000 00da 0570 6172 7365 da08  htr......parse..
+00000970: 7374 7266 7469 6d65 2904 7251 0000 0072  strftime).rQ...r
+00000980: 5400 0000 7227 0000 00da 0b64 6174 655f  T...r'.....date_
+00000990: 6461 7368 6564 7249 0000 0072 5000 0000  dashedrI...rP...
+000009a0: 724a 0000 00da 1165 7874 7261 6374 5f66  rJ.....extract_f
+000009b0: 696c 655f 6461 7465 6300 0000 730e 0000  ile_datec...s...
+000009c0: 0010 020c 010c 0110 0306 091c 0104 0172  ...............r
+000009d0: 5e00 0000 6301 0000 0000 0000 0000 0000  ^...c...........
+000009e0: 0004 0000 0004 0000 0003 0000 0073 5c00  .............s\.
+000009f0: 0000 7400 a001 8800 6401 1900 6a02 a101  ..t.....d...j...
+00000a00: 0100 8800 6401 1900 6a02 6a03 8902 8800  ....d...j.j.....
+00000a10: 6401 1900 6a02 6a04 8901 8700 8701 8702  d...j.j.........
+00000a20: 6603 6402 6403 8408 7d01 8700 8701 8702  f.d.d...}.......
+00000a30: 6603 6404 6405 8408 7d02 7c01 8300 7c02  f.d.d...}.|...|.
+00000a40: 8300 6702 7d03 7405 7c03 8301 5300 2906  ..g.}.t.|...S.).
+00000a50: 4e72 0100 0000 6300 0000 0000 0000 0000  Nr....c.........
+00000a60: 0000 0000 0000 0007 0000 0013 0000 0072  ...............r
+00000a70: 4c00 0000 724d 0000 0072 0400 0000 7249  L...rM...r....rI
+00000a80: 0000 0072 5000 0000 7249 0000 0072 4a00  ...rP...rI...rJ.
+00000a90: 0000 7254 0000 007d 0000 0072 5500 0000  ..rT...}...rU...
+00000aa0: 7a2b 6578 7472 6163 745f 736f 795f 6265  z+extract_soy_be
+00000ab0: 616e 732e 3c6c 6f63 616c 733e 2e5f 6461  ans.<locals>._da
+00000ac0: 7465 5f63 6f72 6469 6e61 7465 7363 0000  te_cordinatesc..
+00000ad0: 0000 0000 0000 0000 0000 0000 0000 0700  ................
+00000ae0: 0000 1300 0000 732e 0000 0074 0088 0064  ......s....t...d
+00000af0: 0119 0088 0264 0214 0064 031b 0088 0164  .....d...d.....d
+00000b00: 0214 0064 041b 0088 0288 0164 0514 0064  ...d.......d...d
+00000b10: 061b 0067 0483 0253 0029 0761 0c01 0000  ...g...S.).a....
+00000b20: 0a20 2020 2020 2020 2078 6d69 6e3a 2030  .        xmin: 0
+00000b30: 2028 5374 6172 7420 6672 6f6d 2074 6865   (Start from the
+00000b40: 206c 6566 7420 6564 6765 290a 2020 2020   left edge).    
+00000b50: 2020 2020 796d 696e 3a20 3834 3120 2a20      ymin: 841 * 
+00000b60: 322f 3320 2853 7461 7274 2031 2f33 2064  2/3 (Start 1/3 d
+00000b70: 6f77 6e20 6672 6f6d 2074 6865 2074 6f70  own from the top
+00000b80: 290a 2020 2020 2020 2020 786d 6178 3a20  ).        xmax: 
+00000b90: 3539 3520 2a20 312f 3220 2843 6f76 6572  595 * 1/2 (Cover
+00000ba0: 2031 2f32 2074 6865 2077 6964 7468 206f   1/2 the width o
+00000bb0: 6620 7468 6520 7061 6765 290a 2020 2020  f the page).    
+00000bc0: 2020 2020 796d 6178 3a20 3834 3120 2a20      ymax: 841 * 
+00000bd0: 342f 3520 2845 6e64 2077 6865 7265 2074  4/5 (End where t
+00000be0: 6865 2064 6174 6520 7374 6172 7473 2e20  he date starts. 
+00000bf0: 5468 6973 2063 6f75 6c64 2062 6520 6164  This could be ad
+00000c00: 6a75 7374 6564 2061 7320 6e65 6564 6564  justed as needed
+00000c10: 290a 0a20 2020 2020 2020 203a 7265 7475  )..        :retu
+00000c20: 726e 3a0a 2020 2020 2020 2020 7201 0000  rn:.        r...
+00000c30: 0072 0300 0000 7226 0000 00e9 0500 0000  .r....r&........
+00000c40: e90d 0000 00e9 2000 0000 7204 0000 0072  ...... ...r....r
+00000c50: 4900 0000 7250 0000 0072 4900 0000 724a  I...rP...rI...rJ
+00000c60: 0000 00da 135f 736f 7962 6561 6e5f 636f  ....._soybean_co
+00000c70: 7264 696e 6174 6573 8700 0000 7302 0000  rdinates....s...
+00000c80: 002e 097a 2e65 7874 7261 6374 5f73 6f79  ...z.extract_soy
+00000c90: 5f62 6561 6e73 2e3c 6c6f 6361 6c73 3e2e  _beans.<locals>.
+00000ca0: 5f73 6f79 6265 616e 5f63 6f72 6469 6e61  _soybean_cordina
+00000cb0: 7465 7329 0672 5600 0000 7257 0000 0072  tes).rV...rW...r
+00000cc0: 5800 0000 7259 0000 0072 5a00 0000 724b  X...rY...rZ...rK
+00000cd0: 0000 0029 0472 5100 0000 7254 0000 0072  ...).rQ...rT...r
+00000ce0: 6200 0000 da06 7461 626c 6573 7249 0000  b.....tablesrI..
+00000cf0: 0072 5000 0000 724a 0000 00da 1165 7874  .rP...rJ.....ext
+00000d00: 7261 6374 5f73 6f79 5f62 6561 6e73 7800  ract_soy_beansx.
+00000d10: 0000 730e 0000 0010 010c 010c 0110 0210  ..s.............
+00000d20: 0a0c 0b08 0172 6400 0000 6300 0000 0000  .....rd...c.....
+00000d30: 0000 0000 0000 0006 0000 000b 0000 0043  ...............C
+00000d40: 0000 0073 ca00 0000 7400 a000 7401 6a02  ...s....t...t.j.
+00000d50: a003 7404 6401 a102 a101 7d00 7405 a006  ..t.d.....}.t...
+00000d60: 6402 7407 7c00 8301 9b00 6403 9d03 a101  d.t.|.....d.....
+00000d70: 0100 6700 7d01 7407 7c00 8301 6404 6b02  ..g.}.t.|...d.k.
+00000d80: 722e 6405 6406 6407 6408 6409 640a 640b  r.d.d.d.d.d.d.d.
+00000d90: 640c 640d 9c07 6701 640e 640f 6410 9c04  d.d...g.d.d.d...
+00000da0: 6701 5300 7c00 4400 5d32 7d02 7a14 7408  g.S.|.D.]2}.z.t.
+00000db0: a009 7c02 a101 7d03 740a 7c03 8301 7d04  ..|...}.t.|...}.
+00000dc0: 7c02 7c04 6411 3c00 7c01 a00b 7c04 a101  |.|.d.<.|...|...
+00000dd0: 0100 5700 7130 0400 740c 7962 0100 7d05  ..W.q0..t.yb..}.
+00000de0: 0100 7a10 7406 6412 7c02 9b00 6413 7c05  ..z.t.d.|...d.|.
+00000df0: 9b00 9d04 8301 0100 5700 5900 6400 7d05  ........W.Y.d.}.
+00000e00: 7e05 7130 6400 7d05 7e05 7701 7700 7c01  ~.q0d.}.~.w.w.|.
+00000e10: 5300 2914 4e7a 052a 2e70 6466 7a06 666f  S.).Nz.*.pdfz.fo
+00000e20: 756e 6420 7a0b 2065 7874 7261 6374 696e  und z. extractin
+00000e30: 6772 0100 0000 7a10 4a75 6e65 2031 3674  gr....z.June 16t
+00000e40: 6820 2c20 3230 3233 7214 0000 007a 052d  h , 2023r....z.-
+00000e50: 3132 3030 7a05 2d31 3330 30da 0431 3031  1200z.-1300..101
+00000e60: 327a 022b 397a 1336 3438 3437 385f 305f  2z.+9z.648478_0_
+00000e70: 636c 6f73 6573 2e70 6466 7a07 3136 2d32  closes.pdfz.16-2
+00000e80: 3032 3329 0772 2400 0000 da06 5365 6c6c  023).r$.....Sell
+00000e90: 6572 da05 4275 7965 7272 2d00 0000 722f  er..Buyerr-...r/
+00000ea0: 0000 00da 0966 696c 655f 6e61 6d65 da09  .....file_name..
+00000eb0: 7370 6f74 5f64 6174 65da 0353 424f 7a21  spot_date..SBOz!
+00000ec0: 2e2f 656d 6c73 2f6f 7574 7075 742f 3634  ./emls/output/64
+00000ed0: 3834 3738 5f30 5f63 6c6f 7365 732e 7064  8478_0_closes.pd
+00000ee0: 6629 0472 2700 0000 7228 0000 0072 2b00  f).r'...r(...r+.
+00000ef0: 0000 7268 0000 0072 6800 0000 7a1b 4572  ..rh...rh...z.Er
+00000f00: 726f 7220 6578 7472 6163 7469 6e67 2064  ror extracting d
+00000f10: 6174 6120 6672 6f6d 207a 023a 2029 0dda  ata from z.: )..
+00000f20: 0467 6c6f 62da 026f 73da 0470 6174 68da  .glob..os..path.
+00000f30: 046a 6f69 6eda 0d70 6466 5f64 6972 6563  .join..pdf_direc
+00000f40: 746f 7279 7256 0000 0072 5700 0000 da03  toryrV...rW.....
+00000f50: 6c65 6eda 0466 6974 7ada 0844 6f63 756d  len..fitz..Docum
+00000f60: 656e 7472 6400 0000 7238 0000 0072 3b00  entrd...r8...r;.
+00000f70: 0000 2906 da09 7064 665f 6669 6c65 73da  ..)...pdf_files.
+00000f80: 1861 6c6c 5f66 696c 6573 5f65 7874 7261  .all_files_extra
+00000f90: 6374 6564 5f64 6174 61da 0870 6466 5f66  cted_data..pdf_f
+00000fa0: 696c 6572 5100 0000 723d 0000 0072 4800  ilerQ...r=...rH.
+00000fb0: 0000 7249 0000 0072 4900 0000 724a 0000  ..rI...rI...rJ..
+00000fc0: 00da 1265 7874 7261 6374 5f66 726f 6d5f  ...extract_from_
+00000fd0: 6669 6c65 7396 0000 0073 3c00 0000 1404  files....s<.....
+00000fe0: 1601 0403 0c01 0203 0203 0201 0201 0201  ................
+00000ff0: 0201 0201 0201 04f9 02ff 020b 0201 04f2  ................
+00001000: 04ff 0812 0202 0a01 0801 0801 0e01 0e01  ................
+00001010: 1401 0c01 0880 02fe 0404 7276 0000 0029  ..........rv...)
+00001020: 0172 2300 0000 2916 726b 0000 0072 6c00  .r#...).rk...rl.
+00001030: 0000 7271 0000 0072 5600 0000 da08 6461  ..rq...rV.....da
+00001040: 7465 7574 696c 7202 0000 005a 0970 6172  teutilr....Z.par
+00001050: 7365 5f74 6162 7205 0000 0072 6d00 0000  se_tabr....rm...
+00001060: da07 6469 726e 616d 65da 0761 6273 7061  ..dirname..abspa
+00001070: 7468 da08 5f5f 6669 6c65 5f5f da0b 6375  th..__file__..cu
+00001080: 7272 656e 745f 6469 7272 6e00 0000 da0b  rrent_dirrn.....
+00001090: 7374 6f72 6167 655f 6469 72da 0a6f 7574  storage_dir..out
+000010a0: 7075 745f 6469 7272 6f00 0000 7232 0000  put_dirro...r2..
+000010b0: 0072 4b00 0000 725e 0000 0072 6400 0000  .rK...r^...rd...
+000010c0: 7276 0000 0072 4900 0000 7249 0000 0072  rv...rI...rI...r
+000010d0: 4900 0000 724a 0000 00da 083c 6d6f 6475  I...rJ.....<modu
+000010e0: 6c65 3e01 0000 0073 3800 0000 0800 0801  le>....s8.......
+000010f0: 0802 0801 0c01 0c02 1402 1401 1201 1201  ................
+00001100: 0203 0201 0201 0201 0201 0201 0201 0201  ................
+00001110: 0201 0201 0201 0201 0601 06f3 0a11 0843  ...............C
+00001120: 0815 0c1e                                ....
```

### Comparing `emreader-0.1.7/src/core/__pycache__/base.cpython-311.pyc` & `emreader-0.1.8/src/core/__pycache__/base.cpython-311.pyc`

 * *Files 2% similar despite different names*

#### Python bytecode

```diff
@@ -1,10 +1,10 @@
 magic:    0xa70d0d0a
-moddate:  0xf89e9464 (Thu Jun 22 19:20:24 2023 UTC)
-files sz: 6062
+moddate:  0xebac9464 (Thu Jun 22 20:19:55 2023 UTC)
+files sz: 6059
 code
    argcount  : 0
    nlocals   : 0
    stacksize : 14
    flags     : 0
    code
       0x9700640064016c005a00640064016c015a01640064016c025a02640064
@@ -1093,15 +1093,15 @@
             067e06770177007803590077017c025300
          146           0 RESUME                   0
          
          149           2 LOAD_GLOBAL              0 (os)
                       14 LOAD_ATTR                1 (path)
                       24 LOAD_METHOD              2 (join)
                       46 LOAD_GLOBAL              6 (current_dir)
-                      58 LOAD_CONST               1 ('../..')
+                      58 LOAD_CONST               1 ('..')
                       60 LOAD_CONST               2 ('storage')
                       62 LOAD_CONST               3 ('output')
                       64 PRECALL                  4
                       68 CALL                     4
                       78 STORE_FAST               0 (pdf_directory)
          
          150          80 LOAD_GLOBAL              9 (NULL + glob)
@@ -1244,15 +1244,15 @@
          ExceptionTable:
            340 to 460 -> 464 [1]
            464 to 482 -> 546 [2] lasti
            484 to 524 -> 536 [2] lasti
            536 to 544 -> 546 [2] lasti
          consts
             None
-            '../..'
+            '..'
             'storage'
             'output'
             '*.pdf'
             'found '
             ' extracting'
             0
             'June 16th , 2023'
```

### Comparing `emreader-0.1.7/src/core/__pycache__/eml.cpython-310.pyc` & `emreader-0.1.8/src/core/__pycache__/eml.cpython-310.pyc`

 * *Format-specific differences are supported for Python .pyc files but no file-specific differences were detected; falling back to a binary diff. file(1) reports: Byte-compiled Python module for CPython 3.10, timestamp-based, .py timestamp: Thu Jun 22 19:20:24 2023 UTC, .py size: 2257 bytes*

 * *Could not decompile bytecode: bad marshal data (unknown type code)*

 * *Files 17% similar despite different names*

```diff
@@ -1,138 +1,174 @@
-00000000: 6f0d 0d0a 0000 0000 f89e 9464 d108 0000  o..........d....
+00000000: 6f0d 0d0a 0000 0000 8078 9864 9c0c 0000  o........x.d....
 00000010: e300 0000 0000 0000 0000 0000 0000 0000  ................
-00000020: 0007 0000 0040 0000 0073 8a00 0000 6400  .....@...s....d.
+00000020: 0007 0000 0040 0000 0073 9200 0000 6400  .....@...s....d.
 00000030: 6401 6c00 5a00 6400 6401 6c01 5a01 6400  d.l.Z.d.d.l.Z.d.
 00000040: 6401 6c02 5a02 6400 6402 6c02 6d03 5a03  d.l.Z.d.d.l.m.Z.
 00000050: 0100 6400 6403 6c04 6d05 5a05 0100 6400  ..d.d.l.m.Z...d.
 00000060: 6401 6c06 5a06 6404 5a07 6501 6a08 a009  d.l.Z.d.Z.e.j...
 00000070: 6501 6a08 a00a 650b a101 a101 5a0c 6501  e.j...e.....Z.e.
 00000080: 6a08 a00d 650c 6405 6406 6407 6408 a105  j...e.d.d.d.d...
 00000090: 5a0e 6501 6a08 a00d 650c 6405 6406 6409  Z.e.j...e.d.d.d.
 000000a0: a104 5a0f 640a 640b 8400 5a10 640c 640d  ..Z.d.d...Z.d.d.
-000000b0: 8400 5a11 6401 5300 290e e900 0000 004e  ..Z.d.S.)......N
-000000c0: a901 da06 706f 6c69 6379 2901 da04 506f  ....policy)...Po
-000000d0: 6f6c da03 656d 6c7a 052e 2e2f 2e2e da07  ol..emlz.../....
-000000e0: 7374 6f72 6167 65da 0673 6f75 7263 65da  storage..source.
-000000f0: 0665 6d61 696c 73da 066f 7574 7075 7463  .emails..outputc
-00000100: 0100 0000 0000 0000 0000 0000 0900 0000  ................
-00000110: 0b00 0000 4300 0000 7398 0100 0074 006a  ....C...s....t.j
-00000120: 0174 0264 0164 028d 0201 0064 037d 017a  .t.d.d.....d.}.z
-00000130: ad74 037c 0064 0483 028f 967d 0274 046a  .t.|.d.....}.t.j
-00000140: 057c 0274 066a 0764 058d 027d 0374 087c  .|.t.j.d...}.t.|
-00000150: 03a0 09a1 0083 0144 005d 725c 027d 047d  .......D.]r\.}.}
-00000160: 057a 1f7c 05a0 0aa1 00a0 0ba1 00a0 0c64  .z.|...........d
-00000170: 06a1 0172 3e7c 0364 0719 007d 067c 06a0  ...r>|.d...}.|..
-00000180: 0d64 0864 09a1 02a0 0ba1 007d 067c 069b  .d.d.......}.|..
-00000190: 0064 069d 027d 076e 0257 0071 1e57 006e  .d...}.n.W.q.W.n
-000001a0: 1204 0074 0e79 5301 0001 0001 0074 0f64  ...t.yS......t.d
-000001b0: 0a7c 026a 109b 0064 0b9d 0383 0101 0059  .|.j...d.......Y
-000001c0: 0071 1e77 007c 0772 9074 0374 006a 11a0  .q.w.|.r.t.t.j..
-000001d0: 1274 027c 07a1 0264 0c83 028f 287d 087a  .t.|...d....(}.z
-000001e0: 0f7c 08a0 137c 056a 1464 0164 0d8d 01a1  .|...|.j.d.d....
-000001f0: 0101 007c 0164 0e37 007d 0157 006e 1004  ...|.d.7.}.W.n..
-00000200: 0074 1579 8001 0001 0001 0074 0f64 0f7c  .t.y.......t.d.|
-00000210: 079b 009d 0283 0101 0059 006e 0177 0057  .........Y.n.w.W
-00000220: 0064 1004 0004 0083 0301 006e 0831 0073  .d.........n.1.s
-00000230: 8b77 0101 0001 0001 0059 0001 0071 1e7c  .w.......Y...q.|
-00000240: 0164 036b 0272 9e74 0f64 117c 026a 109b  .d.k.r.t.d.|.j..
-00000250: 0064 129d 0383 0101 0057 0064 1004 0004  .d.......W.d....
-00000260: 0083 0301 006e 0d31 0073 a877 0101 0001  .....n.1.s.w....
-00000270: 0001 0059 0001 0057 0064 0e7c 0166 0253  ...Y...W.d.|.f.S
-00000280: 0057 0064 0e7c 0166 0253 0004 0074 1679  .W.d.|.f.S...t.y
-00000290: cb01 0001 0001 0074 0f64 137c 026a 109b  .......t.d.|.j..
-000002a0: 0064 149d 0383 0101 0059 0064 0e7c 0166  .d.......Y.d.|.f
-000002b0: 0253 0077 0029 157a 3e0a 2020 2020 5472  .S.w.).z>.    Tr
-000002c0: 7920 746f 2065 7874 7261 6374 2074 6865  y to extract the
-000002d0: 2061 7474 6163 686d 656e 7473 2066 726f   attachments fro
-000002e0: 6d20 616c 6c20 6669 6c65 7320 696e 2063  m all files in c
-000002f0: 7764 0a20 2020 2054 2901 da08 6578 6973  wd.    T)...exis
-00000300: 745f 6f6b 7201 0000 00da 0172 7202 0000  t_okr......rr...
-00000310: 007a 042e 7064 66da 0773 7562 6a65 6374  .z..pdf..subject
-00000320: fa01 20da 015f 7a23 476f 7420 7374 7269  .. .._z#Got stri
-00000330: 6e67 2069 6e73 7465 6164 206f 6620 6669  ng instead of fi
-00000340: 6c65 6e61 6d65 2066 6f72 207a 0b2e 2053  lename for z.. S
-00000350: 6b69 7070 696e 672e da02 7762 2901 da06  kipping...wb)...
-00000360: 6465 636f 6465 e901 0000 007a 1943 6f75  decode.....z.Cou
-00000370: 6c64 6e27 7420 6765 7420 7061 796c 6f61  ldn't get payloa
-00000380: 6420 666f 7220 4e7a 1d4e 6f20 6174 7461  d for Nz.No atta
-00000390: 6368 6d65 6e74 2066 6f75 6e64 2066 6f72  chment found for
-000003a0: 2066 696c 6520 fa01 217a 0d50 726f 626c   file ..!z.Probl
-000003b0: 656d 2077 6974 6820 7a1b 206f 7220 6f6e  em with z. or on
-000003c0: 6520 6f66 2069 7473 2061 7474 6163 686d  e of its attachm
-000003d0: 656e 7473 2129 17da 026f 73da 086d 616b  ents!)...os..mak
-000003e0: 6564 6972 73da 0a6f 7574 7075 745f 6469  edirs..output_di
-000003f0: 72da 046f 7065 6eda 0565 6d61 696c da11  r..open..email..
-00000400: 6d65 7373 6167 655f 6672 6f6d 5f66 696c  message_from_fil
-00000410: 6572 0300 0000 da07 6465 6661 756c 74da  er......default.
-00000420: 0965 6e75 6d65 7261 7465 da10 6974 6572  .enumerate..iter
-00000430: 5f61 7474 6163 686d 656e 7473 da0c 6765  _attachments..ge
-00000440: 745f 6669 6c65 6e61 6d65 da05 6c6f 7765  t_filename..lowe
-00000450: 72da 0865 6e64 7377 6974 68da 0772 6570  r..endswith..rep
-00000460: 6c61 6365 da0e 4174 7472 6962 7574 6545  lace..AttributeE
-00000470: 7272 6f72 da05 7072 696e 74da 046e 616d  rror..print..nam
-00000480: 65da 0470 6174 68da 046a 6f69 6eda 0577  e..path..join..w
-00000490: 7269 7465 da0b 6765 745f 7061 796c 6f61  rite..get_payloa
-000004a0: 64da 0954 7970 6545 7272 6f72 da07 494f  d..TypeError..IO
-000004b0: 4572 726f 7229 09da 0866 696c 656e 616d  Error)...filenam
-000004c0: 655a 0c6f 7574 7075 745f 636f 756e 74da  eZ.output_count.
-000004d0: 0166 da03 6d73 67da 0369 6478 da0a 6174  .f..msg..idx..at
-000004e0: 7461 6368 6d65 6e74 720c 0000 005a 0f6f  tachmentr....Z.o
-000004f0: 7574 7075 745f 6669 6c65 6e61 6d65 da02  utput_filename..
-00000500: 6f66 a900 722f 0000 00fa 2d2f 5573 6572  of..r/....-/User
-00000510: 732f 7468 656d 6261 2f73 6563 7469 6f6e  s/themba/section
-00000520: 3332 2f65 726a 656e 2f73 7263 2f63 6f72  32/erjen/src/cor
-00000530: 652f 656d 6c2e 7079 da07 6578 7472 6163  e/eml.py..extrac
-00000540: 740f 0000 0073 4e00 0000 0e04 0401 0201  t....sN.........
-00000550: 0c01 1001 1401 0201 1202 0802 1001 0c01  ................
-00000560: 0402 04fe 0c03 1201 0401 02fe 0404 1601  ................
-00000570: 0201 1201 0c01 0c01 1201 02ff 0280 1cfc  ................
-00000580: 0280 0806 1201 0280 1ee8 081c 02e4 081c  ................
-00000590: 0cfd 1401 0802 02fd 7231 0000 0063 0000  ........r1...c..
-000005a0: 0000 0000 0000 0000 0000 0400 0000 0700  ................
-000005b0: 0000 4300 0000 7386 0000 0074 00a0 0164  ..C...s....t...d
-000005c0: 0174 029b 0064 029d 03a1 0101 0074 0364  .t...d.......t.d
-000005d0: 0083 017d 0074 04a0 0474 056a 06a0 0774  ...}.t...t.j...t
-000005e0: 0264 0374 089b 009d 02a1 02a1 017d 017c  .d.t.........}.|
-000005f0: 00a0 0974 0a7c 01a1 027d 027c 00a0 0ba1  ...t.|...}.|....
-00000600: 0001 007c 00a0 07a1 0001 0064 0464 0584  ...|.......d.d..
-00000610: 0074 0c7c 028e 0044 0083 017d 0374 00a0  .t.|...D...}.t..
-00000620: 0164 067c 0364 0719 009b 0064 087c 0364  .d.|.d.....d.|.d
-00000630: 0919 009b 0064 0a9d 05a1 0101 0064 0053  .....d.......d.S
-00000640: 0029 0b4e 7a03 696e 207a 132c 2065 7874  .).Nz.in z., ext
-00000650: 7261 6374 696e 6720 656d 6169 6c73 7a02  racting emailsz.
-00000660: 2a2e 6301 0000 0000 0000 0000 0000 0002  *.c.............
-00000670: 0000 0004 0000 0053 0000 0073 1400 0000  .......S...s....
-00000680: 6700 7c00 5d06 7d01 7400 7c01 8301 9102  g.|.].}.t.|.....
-00000690: 7102 5300 722f 0000 0029 01da 0373 756d  q.S.r/...)...sum
-000006a0: 2902 da02 2e30 da01 6972 2f00 0000 722f  )....0..ir/...r/
-000006b0: 0000 0072 3000 0000 da0a 3c6c 6973 7463  ...r0.....<listc
-000006c0: 6f6d 703e 3d00 0000 7302 0000 0014 007a  omp>=...s......z
-000006d0: 2265 7874 7261 6374 5f65 6d61 696c 732e  "extract_emails.
-000006e0: 3c6c 6f63 616c 733e 2e3c 6c69 7374 636f  <locals>.<listco
-000006f0: 6d70 3e7a 1044 6f6e 653a 2050 726f 6365  mp>z.Done: Proce
-00000700: 7373 6564 2072 0100 0000 7a0c 2066 696c  ssed r....z. fil
-00000710: 6573 2077 6974 6820 7211 0000 007a 0d20  es with r....z. 
-00000720: 6174 7461 6368 6d65 6e74 732e 290d da04  attachments.)...
-00000730: 7269 6368 7221 0000 00da 0b73 746f 7261  richr!.....stora
-00000740: 6765 5f64 6972 7204 0000 00da 0467 6c6f  ge_dirr......glo
-00000750: 6272 1300 0000 7223 0000 0072 2400 0000  br....r#...r$...
-00000760: da09 4558 5445 4e53 494f 4eda 036d 6170  ..EXTENSION..map
-00000770: 7231 0000 00da 0563 6c6f 7365 da03 7a69  r1.....close..zi
-00000780: 7029 04da 0470 6f6f 6c5a 0965 6d6c 5f66  p)...poolZ.eml_f
-00000790: 696c 6573 da03 7265 735a 086e 756d 6669  iles..resZ.numfi
-000007a0: 6c65 7372 2f00 0000 722f 0000 0072 3000  lesr/...r/...r0.
-000007b0: 0000 da0e 6578 7472 6163 745f 656d 6169  ....extract_emai
-000007c0: 6c73 3500 0000 7310 0000 0012 0108 011a  ls5...s.........
-000007d0: 010c 0108 0108 0112 0224 0172 3f00 0000  .........$.r?...
-000007e0: 2912 7238 0000 0072 1300 0000 7217 0000  ).r8...r....r...
-000007f0: 0072 0300 0000 da0f 6d75 6c74 6970 726f  .r......multipro
-00000800: 6365 7373 696e 6772 0400 0000 7236 0000  cessingr....r6..
-00000810: 0072 3900 0000 7223 0000 00da 0764 6972  .r9...r#.....dir
-00000820: 6e61 6d65 da07 6162 7370 6174 68da 085f  name..abspath.._
-00000830: 5f66 696c 655f 5fda 0b63 7572 7265 6e74  _file__..current
-00000840: 5f64 6972 7224 0000 0072 3700 0000 7215  _dirr$...r7...r.
-00000850: 0000 0072 3100 0000 723f 0000 0072 2f00  ...r1...r?...r/.
-00000860: 0000 722f 0000 0072 2f00 0000 7230 0000  ..r/...r/...r0..
-00000870: 00da 083c 6d6f 6475 6c65 3e01 0000 0073  ...<module>....s
-00000880: 1800 0000 0800 0801 0801 0c01 0c01 0801  ................
-00000890: 0402 1402 1401 1201 0803 0c26            ...........&
+000000b0: 8400 5a11 640e 640f 8400 5a12 6401 5300  ..Z.d.d...Z.d.S.
+000000c0: 2910 e900 0000 004e a901 da06 706f 6c69  )......N....poli
+000000d0: 6379 2901 da04 506f 6f6c da03 656d 6c7a  cy)...Pool..emlz
+000000e0: 022e 2eda 0773 746f 7261 6765 da06 736f  .....storage..so
+000000f0: 7572 6365 da06 656d 6169 6c73 da06 6f75  urce..emails..ou
+00000100: 7470 7574 6301 0000 0000 0000 0000 0000  tputc...........
+00000110: 0009 0000 000b 0000 0043 0000 0073 9801  .........C...s..
+00000120: 0000 7400 6a01 7402 6401 6402 8d02 0100  ..t.j.t.d.d.....
+00000130: 6403 7d01 7aad 7403 7c00 6404 8302 8f96  d.}.z.t.|.d.....
+00000140: 7d02 7404 6a05 7c02 7406 6a07 6405 8d02  }.t.j.|.t.j.d...
+00000150: 7d03 7408 7c03 a009 a100 8301 4400 5d72  }.t.|.......D.]r
+00000160: 5c02 7d04 7d05 7a1f 7c05 a00a a100 a00b  \.}.}.z.|.......
+00000170: a100 a00c 6406 a101 723e 7c03 6407 1900  ....d...r>|.d...
+00000180: 7d06 7c06 a00d 6408 6409 a102 a00b a100  }.|...d.d.......
+00000190: 7d06 7c06 9b00 6406 9d02 7d07 6e02 5700  }.|...d...}.n.W.
+000001a0: 711e 5700 6e12 0400 740e 7953 0100 0100  q.W.n...t.yS....
+000001b0: 0100 740f 640a 7c02 6a10 9b00 640b 9d03  ..t.d.|.j...d...
+000001c0: 8301 0100 5900 711e 7700 7c07 7290 7403  ....Y.q.w.|.r.t.
+000001d0: 7400 6a11 a012 7402 7c07 a102 640c 8302  t.j...t.|...d...
+000001e0: 8f28 7d08 7a0f 7c08 a013 7c05 6a14 6401  .(}.z.|...|.j.d.
+000001f0: 640d 8d01 a101 0100 7c01 640e 3700 7d01  d.......|.d.7.}.
+00000200: 5700 6e10 0400 7415 7980 0100 0100 0100  W.n...t.y.......
+00000210: 740f 640f 7c07 9b00 9d02 8301 0100 5900  t.d.|.........Y.
+00000220: 6e01 7700 5700 6410 0400 0400 8303 0100  n.w.W.d.........
+00000230: 6e08 3100 738b 7701 0100 0100 0100 5900  n.1.s.w.......Y.
+00000240: 0100 711e 7c01 6403 6b02 729e 740f 6411  ..q.|.d.k.r.t.d.
+00000250: 7c02 6a10 9b00 6412 9d03 8301 0100 5700  |.j...d.......W.
+00000260: 6410 0400 0400 8303 0100 6e0d 3100 73a8  d.........n.1.s.
+00000270: 7701 0100 0100 0100 5900 0100 5700 640e  w.......Y...W.d.
+00000280: 7c01 6602 5300 5700 640e 7c01 6602 5300  |.f.S.W.d.|.f.S.
+00000290: 0400 7416 79cb 0100 0100 0100 740f 6413  ..t.y.......t.d.
+000002a0: 7c02 6a10 9b00 6414 9d03 8301 0100 5900  |.j...d.......Y.
+000002b0: 640e 7c01 6602 5300 7700 2915 7a3e 0a20  d.|.f.S.w.).z>. 
+000002c0: 2020 2054 7279 2074 6f20 6578 7472 6163     Try to extrac
+000002d0: 7420 7468 6520 6174 7461 6368 6d65 6e74  t the attachment
+000002e0: 7320 6672 6f6d 2061 6c6c 2066 696c 6573  s from all files
+000002f0: 2069 6e20 6377 640a 2020 2020 5429 01da   in cwd.    T)..
+00000300: 0865 7869 7374 5f6f 6b72 0100 0000 da01  .exist_okr......
+00000310: 7272 0200 0000 fa04 2e70 6466 da07 7375  rr.......pdf..su
+00000320: 626a 6563 74fa 0120 da01 5ffa 2347 6f74  bject.. .._.#Got
+00000330: 2073 7472 696e 6720 696e 7374 6561 6420   string instead 
+00000340: 6f66 2066 696c 656e 616d 6520 666f 7220  of filename for 
+00000350: fa0b 2e20 536b 6970 7069 6e67 2eda 0277  ... Skipping...w
+00000360: 62a9 01da 0664 6563 6f64 65e9 0100 0000  b....decode.....
+00000370: fa19 436f 756c 646e 2774 2067 6574 2070  ..Couldn't get p
+00000380: 6179 6c6f 6164 2066 6f72 204e 7a1d 4e6f  ayload for Nz.No
+00000390: 2061 7474 6163 686d 656e 7420 666f 756e   attachment foun
+000003a0: 6420 666f 7220 6669 6c65 20fa 0121 7a0d  d for file ..!z.
+000003b0: 5072 6f62 6c65 6d20 7769 7468 207a 1b20  Problem with z. 
+000003c0: 6f72 206f 6e65 206f 6620 6974 7320 6174  or one of its at
+000003d0: 7461 6368 6d65 6e74 7321 2917 da02 6f73  tachments!)...os
+000003e0: da08 6d61 6b65 6469 7273 da0a 6f75 7470  ..makedirs..outp
+000003f0: 7574 5f64 6972 da04 6f70 656e da05 656d  ut_dir..open..em
+00000400: 6169 6cda 116d 6573 7361 6765 5f66 726f  ail..message_fro
+00000410: 6d5f 6669 6c65 7203 0000 00da 0764 6566  m_filer......def
+00000420: 6175 6c74 da09 656e 756d 6572 6174 65da  ault..enumerate.
+00000430: 1069 7465 725f 6174 7461 6368 6d65 6e74  .iter_attachment
+00000440: 73da 0c67 6574 5f66 696c 656e 616d 65da  s..get_filename.
+00000450: 056c 6f77 6572 da08 656e 6473 7769 7468  .lower..endswith
+00000460: da07 7265 706c 6163 65da 0e41 7474 7269  ..replace..Attri
+00000470: 6275 7465 4572 726f 72da 0570 7269 6e74  buteError..print
+00000480: da04 6e61 6d65 da04 7061 7468 da04 6a6f  ..name..path..jo
+00000490: 696e da05 7772 6974 65da 0b67 6574 5f70  in..write..get_p
+000004a0: 6179 6c6f 6164 da09 5479 7065 4572 726f  ayload..TypeErro
+000004b0: 72da 0749 4f45 7272 6f72 2909 da08 6669  r..IOError)...fi
+000004c0: 6c65 6e61 6d65 da0c 6f75 7470 7574 5f63  lename..output_c
+000004d0: 6f75 6e74 da01 66da 036d 7367 da03 6964  ount..f..msg..id
+000004e0: 78da 0a61 7474 6163 686d 656e 7472 0d00  x..attachmentr..
+000004f0: 0000 da0f 6f75 7470 7574 5f66 696c 656e  ....output_filen
+00000500: 616d 65da 026f 66a9 0072 3600 0000 fa2d  ame..of..r6....-
+00000510: 2f55 7365 7273 2f74 6865 6d62 612f 7365  /Users/themba/se
+00000520: 6374 696f 6e33 322f 6572 6a65 6e2f 7372  ction32/erjen/sr
+00000530: 632f 636f 7265 2f65 6d6c 2e70 79da 0765  c/core/eml.py..e
+00000540: 7874 7261 6374 0f00 0000 734e 0000 000e  xtract....sN....
+00000550: 0404 0102 010c 0110 0114 0102 0112 0208  ................
+00000560: 0210 010c 0104 0204 fe0c 0312 0104 0102  ................
+00000570: fe04 0416 0102 0112 010c 010c 0112 0102  ................
+00000580: ff02 801c fc02 8008 0612 0102 801e e808  ................
+00000590: 1c02 e408 1c0c fd14 0108 0202 fd72 3800  .............r8.
+000005a0: 0000 6301 0000 0000 0000 0000 0000 0007  ..c.............
+000005b0: 0000 000a 0000 0043 0000 0073 fe00 0000  .......C...s....
+000005c0: 7400 6a01 7c00 7402 6a03 6401 8d02 7d01  t.j.|.t.j.d...}.
+000005d0: 7404 7c01 a005 a100 8301 4400 5d6e 5c02  t.|.......D.]n\.
+000005e0: 7d02 7d03 7a1f 7c03 a006 a100 a007 a100  }.}.z.|.........
+000005f0: a008 6402 a101 722e 7c01 6403 1900 7d04  ..d...r.|.d...}.
+00000600: 7c04 a009 6404 6405 a102 a007 a100 7d04  |...d.d.......}.
+00000610: 7c04 9b00 6402 9d02 7d05 6e02 5700 710e  |...d...}.n.W.q.
+00000620: 5700 6e12 0400 740a 7943 0100 0100 0100  W.n...t.yC......
+00000630: 740b 6406 7c00 6a0c 9b00 6407 9d03 8301  t.d.|.j...d.....
+00000640: 0100 5900 710e 7700 7c05 727c 740d 740e  ..Y.q.w.|.r|t.t.
+00000650: 6a0f a010 7411 7c05 a102 6408 8302 8f24  j...t.|...d....$
+00000660: 7d06 7a0b 7c06 a012 7c03 6a13 6409 640a  }.z.|...|.j.d.d.
+00000670: 8d01 a101 0100 5700 6e10 0400 7414 796c  ......W.n...t.yl
+00000680: 0100 0100 0100 740b 640b 7c05 9b00 9d02  ......t.d.|.....
+00000690: 8301 0100 5900 6e01 7700 5700 6400 0400  ....Y.n.w.W.d...
+000006a0: 0400 8303 0100 6e08 3100 7377 7701 0100  ......n.1.sww...
+000006b0: 0100 0100 5900 0100 710e 640c 5300 290d  ....Y...q.d.S.).
+000006c0: 4e72 0200 0000 720c 0000 0072 0d00 0000  Nr....r....r....
+000006d0: 720e 0000 0072 0f00 0000 7210 0000 0072  r....r....r....r
+000006e0: 1100 0000 7212 0000 0054 7213 0000 0072  ....r....Tr....r
+000006f0: 1600 0000 da04 446f 6e65 2915 721c 0000  ......Done).r...
+00000700: 00da 186d 6573 7361 6765 5f66 726f 6d5f  ...message_from_
+00000710: 6269 6e61 7279 5f66 696c 6572 0300 0000  binary_filer....
+00000720: 721e 0000 0072 1f00 0000 7220 0000 0072  r....r....r ...r
+00000730: 2100 0000 7222 0000 0072 2300 0000 7224  !...r"...r#...r$
+00000740: 0000 0072 2500 0000 7226 0000 0072 2700  ...r%...r&...r'.
+00000750: 0000 721b 0000 0072 1800 0000 7228 0000  ..r....r....r(..
+00000760: 0072 2900 0000 721a 0000 0072 2a00 0000  .r)...r....r*...
+00000770: 722b 0000 0072 2c00 0000 2907 7230 0000  r+...r,...).r0..
+00000780: 0072 3100 0000 7232 0000 0072 3300 0000  .r1...r2...r3...
+00000790: 720d 0000 0072 3400 0000 7235 0000 0072  r....r4...r5...r
+000007a0: 3600 0000 7236 0000 0072 3700 0000 da11  6...r6...r7.....
+000007b0: 6578 7472 6163 745f 6672 6f6d 5f66 696c  extract_from_fil
+000007c0: 6535 0000 0073 3000 0000 1002 1401 0201  e5...s0.........
+000007d0: 1202 0802 1001 0c01 0402 04fe 0c03 1201  ................
+000007e0: 0401 02fe 0404 1601 0201 1601 0c01 1201  ................
+000007f0: 02ff 0280 1cfd 0280 0406 723b 0000 0063  ..........r;...c
+00000800: 0000 0000 0000 0000 0000 0000 0400 0000  ................
+00000810: 0700 0000 4300 0000 7378 0000 0074 00a0  ....C...sx...t..
+00000820: 0164 0174 029b 0064 029d 03a1 0101 0074  .d.t...d.......t
+00000830: 0364 0083 017d 0074 04a0 0474 056a 06a0  .d...}.t...t.j..
+00000840: 0774 0264 0374 089b 009d 02a1 02a1 017d  .t.d.t.........}
+00000850: 017c 00a0 0974 0a7c 01a1 027d 027c 00a0  .|...t.|...}.|..
+00000860: 0ba1 0001 007c 00a0 07a1 0001 0064 0464  .....|.......d.d
+00000870: 0584 0074 0c7c 028e 0044 0083 017d 0374  ...t.|...D...}.t
+00000880: 00a0 0164 067c 039b 0064 079d 03a1 0101  ...d.|...d......
+00000890: 0064 0053 0029 084e 7a03 696e 207a 132c  .d.S.).Nz.in z.,
+000008a0: 2065 7874 7261 6374 696e 6720 656d 6169   extracting emai
+000008b0: 6c73 7a02 2a2e 6301 0000 0000 0000 0000  lsz.*.c.........
+000008c0: 0000 0002 0000 0004 0000 0053 0000 0073  ...........S...s
+000008d0: 1400 0000 6700 7c00 5d06 7d01 7400 7c01  ....g.|.].}.t.|.
+000008e0: 8301 9102 7102 5300 7236 0000 0029 01da  ....q.S.r6...)..
+000008f0: 0373 756d 2902 da02 2e30 da01 6972 3600  .sum)....0..ir6.
+00000900: 0000 7236 0000 0072 3700 0000 da0a 3c6c  ..r6...r7.....<l
+00000910: 6973 7463 6f6d 703e 5900 0000 7302 0000  istcomp>Y...s...
+00000920: 0014 007a 2265 7874 7261 6374 5f65 6d61  ...z"extract_ema
+00000930: 696c 732e 3c6c 6f63 616c 733e 2e3c 6c69  ils.<locals>.<li
+00000940: 7374 636f 6d70 3e7a 1044 6f6e 653a 2050  stcomp>z.Done: P
+00000950: 726f 6365 7373 6564 20da 012e 290d da04  rocessed ...)...
+00000960: 7269 6368 7226 0000 00da 0b73 746f 7261  richr&.....stora
+00000970: 6765 5f64 6972 7204 0000 00da 0467 6c6f  ge_dirr......glo
+00000980: 6272 1800 0000 7228 0000 0072 2900 0000  br....r(...r)...
+00000990: da09 4558 5445 4e53 494f 4eda 036d 6170  ..EXTENSION..map
+000009a0: 7238 0000 00da 0563 6c6f 7365 da03 7a69  r8.....close..zi
+000009b0: 7029 04da 0470 6f6f 6cda 0965 6d6c 5f66  p)...pool..eml_f
+000009c0: 696c 6573 da03 7265 73da 086e 756d 6669  iles..res..numfi
+000009d0: 6c65 7372 3600 0000 7236 0000 0072 3700  lesr6...r6...r7.
+000009e0: 0000 da0e 6578 7472 6163 745f 656d 6169  ....extract_emai
+000009f0: 6c73 5100 0000 7310 0000 0012 0108 011a  lsQ...s.........
+00000a00: 010c 0108 0108 0112 0216 0172 4c00 0000  ...........rL...
+00000a10: 2913 7243 0000 0072 1800 0000 721c 0000  ).rC...r....r...
+00000a20: 0072 0300 0000 da0f 6d75 6c74 6970 726f  .r......multipro
+00000a30: 6365 7373 696e 6772 0400 0000 7241 0000  cessingr....rA..
+00000a40: 0072 4400 0000 7228 0000 00da 0764 6972  .rD...r(.....dir
+00000a50: 6e61 6d65 da07 6162 7370 6174 68da 085f  name..abspath.._
+00000a60: 5f66 696c 655f 5fda 0b63 7572 7265 6e74  _file__..current
+00000a70: 5f64 6972 7229 0000 0072 4200 0000 721a  _dirr)...rB...r.
+00000a80: 0000 0072 3800 0000 723b 0000 0072 4c00  ...r8...r;...rL.
+00000a90: 0000 7236 0000 0072 3600 0000 7236 0000  ..r6...r6...r6..
+00000aa0: 0072 3700 0000 da08 3c6d 6f64 756c 653e  .r7.....<module>
+00000ab0: 0100 0000 731a 0000 0008 0008 0108 010c  ....s...........
+00000ac0: 010c 0108 0104 0214 0214 0112 0108 0308  ................
+00000ad0: 260c 1c                                  &..
```

### Comparing `emreader-0.1.7/src/core/__pycache__/eml.cpython-311.pyc` & `emreader-0.1.8/src/core/__pycache__/eml.cpython-311.pyc`

 * *Files 24% similar despite different names*

#### Python bytecode

```diff
@@ -1,10 +1,10 @@
 magic:    0xa70d0d0a
-moddate:  0xf89e9464 (Thu Jun 22 19:20:24 2023 UTC)
-files sz: 2257
+moddate:  0x97ac9464 (Thu Jun 22 20:18:31 2023 UTC)
+files sz: 3285
 code
    argcount  : 0
    nlocals   : 0
    stacksize : 7
    flags     : 0
    code
       0x9700640064016c005a00640064016c015a01640064016c025a02640064
@@ -12,15 +12,16 @@
       045a0765016a080000000000000000a00900000000000000000000000000
       0000000000000065016a080000000000000000a00a000000000000000000
       0000000000000000000000650ba6010000ab010000000000000000a60100
       00ab0100000000000000005a0c65016a080000000000000000a00d000000
       0000000000000000000000000000000000650c6405640664076408a60500
       00ab0500000000000000005a0e65016a080000000000000000a00d000000
       0000000000000000000000000000000000650c640564066409a6040000ab
-      0400000000000000005a0f640a84005a10640b84005a1164015300
+      0400000000000000005a0f640a84005a10640b84005a11640c84005a1264
+      015300
      0           0 RESUME                   0
    
      1           2 LOAD_CONST               0 (0)
                  4 LOAD_CONST               1 (None)
                  6 IMPORT_NAME              0 (glob)
                  8 STORE_NAME               0 (glob)
    
@@ -69,49 +70,53 @@
                150 CALL                     1
                160 STORE_NAME              12 (current_dir)
    
     11         162 LOAD_NAME                1 (os)
                164 LOAD_ATTR                8 (path)
                174 LOAD_METHOD             13 (join)
                196 LOAD_NAME               12 (current_dir)
-               198 LOAD_CONST               5 ('../..')
+               198 LOAD_CONST               5 ('..')
                200 LOAD_CONST               6 ('storage')
                202 LOAD_CONST               7 ('source')
                204 LOAD_CONST               8 ('emails')
                206 PRECALL                  5
                210 CALL                     5
                220 STORE_NAME              14 (storage_dir)
    
     12         222 LOAD_NAME                1 (os)
                224 LOAD_ATTR                8 (path)
                234 LOAD_METHOD             13 (join)
                256 LOAD_NAME               12 (current_dir)
-               258 LOAD_CONST               5 ('../..')
+               258 LOAD_CONST               5 ('..')
                260 LOAD_CONST               6 ('storage')
                262 LOAD_CONST               9 ('output')
                264 PRECALL                  4
                268 CALL                     4
                278 STORE_NAME              15 (output_dir)
    
     15         280 LOAD_CONST              10 (<code object extract, file "/Users/themba/section32/erjen/src/core/eml.py", line 15>)
                282 MAKE_FUNCTION            0
                284 STORE_NAME              16 (extract)
    
-    53         286 LOAD_CONST              11 (<code object extract_emails, file "/Users/themba/section32/erjen/src/core/eml.py", line 53>)
+    53         286 LOAD_CONST              11 (<code object extract_from_file, file "/Users/themba/section32/erjen/src/core/eml.py", line 53>)
                288 MAKE_FUNCTION            0
-               290 STORE_NAME              17 (extract_emails)
-               292 LOAD_CONST               1 (None)
-               294 RETURN_VALUE
+               290 STORE_NAME              17 (extract_from_file)
+   
+    82         292 LOAD_CONST              12 (<code object extract_emails, file "/Users/themba/section32/erjen/src/core/eml.py", line 82>)
+               294 MAKE_FUNCTION            0
+               296 STORE_NAME              18 (extract_emails)
+               298 LOAD_CONST               1 (None)
+               300 RETURN_VALUE
    consts
       0
       None
       ('policy',)
       ('Pool',)
       'eml'
-      '../..'
+      '..'
       'storage'
       'source'
       'emails'
       'output'
       code
          argcount  : 1
          nlocals   : 9
@@ -471,14 +476,253 @@
          name       'extract'
          firstlineno 15
          lnotab
             0x0204360104010201220140014e0102027202100150010c0202fe040312
             01300104fe080404016801020152010e01120128ff08fc32060c0130e832
             19120134ff0803
       code
+         argcount  : 1
+         nlocals   : 7
+         stacksize : 7
+         flags     : 3
+         code
+            0x97007401000000000000000000006a0100000000000000007c00740400
+            0000000000000000006a030000000000000000ac01a6020000ab02000000
+            00000000007d017409000000000000000000007c01a00500000000000000
+            00000000000000000000000000a6000000ab000000000000000000a60100
+            00ab010000000000000000440090015d3a5c0200007d027d0309007c03a0
+            060000000000000000000000000000000000000000a6000000ab00000000
+            0000000000a0070000000000000000000000000000000000000000a60000
+            00ab000000000000000000a0080000000000000000000000000000000000
+            0000006402a6010000ab01000000000000000072367c0164031900000000
+            00000000007d047c04a00900000000000000000000000000000000000000
+            0064046405a6020000ab020000000000000000a007000000000000000000
+            0000000000000000000000a6000000ab0000000000000000007d047c049b
+            0064029d027d056e018c776e282300741400000000000000000000240072
+            1b010074170000000000000000000064067c006a0c00000000000000009b
+            0064079d03a6010000ab010000000000000000010059008c9c7700780359
+            0077017c057298741b00000000000000000000741c000000000000000000
+            006a0f0000000000000000a0100000000000000000000000000000000000
+            0000007422000000000000000000007c05a6020000ab0200000000000000
+            006408a6020000ab02000000000000000035007d0609007c06a012000000
+            00000000000000000000000000000000007c03a013000000000000000000
+            00000000000000000000006409ac0aa6010000ab010000000000000000a6
+            010000ab01000000000000000001006e2223007428000000000000000000
+            00240072150100741700000000000000000000640b7c059b009d02a60100
+            00ab010000000000000000010059006e0477007803590077016400640064
+            00a6020000ab02000000000000000001006e0b2300310073047702780359
+            007701010059000100010090018c3c640c5300
+          53           0 RESUME                   0
+         
+          55           2 LOAD_GLOBAL              1 (NULL + email)
+                      14 LOAD_ATTR                1 (message_from_binary_file)
+                      24 LOAD_FAST                0 (f)
+                      26 LOAD_GLOBAL              4 (policy)
+                      38 LOAD_ATTR                3 (default)
+                      48 KW_NAMES                 1
+                      50 PRECALL                  2
+                      54 CALL                     2
+                      64 STORE_FAST               1 (msg)
+         
+          56          66 LOAD_GLOBAL              9 (NULL + enumerate)
+                      78 LOAD_FAST                1 (msg)
+                      80 LOAD_METHOD              5 (iter_attachments)
+                     102 PRECALL                  0
+                     106 CALL                     0
+                     116 PRECALL                  1
+                     120 CALL                     1
+                     130 GET_ITER
+                 >>  132 EXTENDED_ARG             1
+                     134 FOR_ITER               314 (to 764)
+                     136 UNPACK_SEQUENCE          2
+                     140 STORE_FAST               2 (idx)
+                     142 STORE_FAST               3 (attachment)
+         
+          57         144 NOP
+         
+          59         146 LOAD_FAST                3 (attachment)
+                     148 LOAD_METHOD              6 (get_filename)
+                     170 PRECALL                  0
+                     174 CALL                     0
+                     184 LOAD_METHOD              7 (lower)
+                     206 PRECALL                  0
+                     210 CALL                     0
+                     220 LOAD_METHOD              8 (endswith)
+                     242 LOAD_CONST               2 ('.pdf')
+                     244 PRECALL                  1
+                     248 CALL                     1
+                     258 POP_JUMP_FORWARD_IF_FALSE    54 (to 368)
+         
+          61         260 LOAD_FAST                1 (msg)
+                     262 LOAD_CONST               3 ('subject')
+                     264 BINARY_SUBSCR
+                     274 STORE_FAST               4 (subject)
+         
+          62         276 LOAD_FAST                4 (subject)
+                     278 LOAD_METHOD              9 (replace)
+                     300 LOAD_CONST               4 (' ')
+                     302 LOAD_CONST               5 ('_')
+                     304 PRECALL                  2
+                     308 CALL                     2
+                     318 LOAD_METHOD              7 (lower)
+                     340 PRECALL                  0
+                     344 CALL                     0
+                     354 STORE_FAST               4 (subject)
+         
+          63         356 LOAD_FAST                4 (subject)
+                     358 FORMAT_VALUE             0
+                     360 LOAD_CONST               2 ('.pdf')
+                     362 BUILD_STRING             2
+                     364 STORE_FAST               5 (output_filename)
+                     366 JUMP_FORWARD             1 (to 370)
+         
+          65     >>  368 JUMP_BACKWARD          119 (to 132)
+         
+          63     >>  370 JUMP_FORWARD            40 (to 452)
+                 >>  372 PUSH_EXC_INFO
+         
+          66         374 LOAD_GLOBAL             20 (AttributeError)
+                     386 CHECK_EXC_MATCH
+                     388 POP_JUMP_FORWARD_IF_FALSE    27 (to 444)
+                     390 POP_TOP
+         
+          67         392 LOAD_GLOBAL             23 (NULL + print)
+                     404 LOAD_CONST               6 ('Got string instead of filename for ')
+                     406 LOAD_FAST                0 (f)
+                     408 LOAD_ATTR               12 (name)
+                     418 FORMAT_VALUE             0
+                     420 LOAD_CONST               7 ('. Skipping.')
+                     422 BUILD_STRING             3
+                     424 PRECALL                  1
+                     428 CALL                     1
+                     438 POP_TOP
+         
+          68         440 POP_EXCEPT
+                     442 JUMP_BACKWARD          156 (to 132)
+         
+          66     >>  444 RERAISE                  0
+                 >>  446 COPY                     3
+                     448 POP_EXCEPT
+                     450 RERAISE                  1
+         
+          70     >>  452 LOAD_FAST                5 (output_filename)
+                     454 POP_JUMP_FORWARD_IF_FALSE   152 (to 760)
+         
+          71         456 LOAD_GLOBAL             27 (NULL + open)
+                     468 LOAD_GLOBAL             28 (os)
+                     480 LOAD_ATTR               15 (path)
+                     490 LOAD_METHOD             16 (join)
+                     512 LOAD_GLOBAL             34 (output_dir)
+                     524 LOAD_FAST                5 (output_filename)
+                     526 PRECALL                  2
+                     530 CALL                     2
+                     540 LOAD_CONST               8 ('wb')
+                     542 PRECALL                  2
+                     546 CALL                     2
+                     556 BEFORE_WITH
+                     558 STORE_FAST               6 (of)
+         
+          72         560 NOP
+         
+          73         562 LOAD_FAST                6 (of)
+                     564 LOAD_METHOD             18 (write)
+                     586 LOAD_FAST                3 (attachment)
+                     588 LOAD_METHOD             19 (get_payload)
+                     610 LOAD_CONST               9 (True)
+                     612 KW_NAMES                10
+                     614 PRECALL                  1
+                     618 CALL                     1
+                     628 PRECALL                  1
+                     632 CALL                     1
+                     642 POP_TOP
+                     644 JUMP_FORWARD            34 (to 714)
+                 >>  646 PUSH_EXC_INFO
+         
+          75         648 LOAD_GLOBAL             40 (TypeError)
+                     660 CHECK_EXC_MATCH
+                     662 POP_JUMP_FORWARD_IF_FALSE    21 (to 706)
+                     664 POP_TOP
+         
+          76         666 LOAD_GLOBAL             23 (NULL + print)
+                     678 LOAD_CONST              11 ("Couldn't get payload for ")
+                     680 LOAD_FAST                5 (output_filename)
+                     682 FORMAT_VALUE             0
+                     684 BUILD_STRING             2
+                     686 PRECALL                  1
+                     690 CALL                     1
+                     700 POP_TOP
+                     702 POP_EXCEPT
+                     704 JUMP_FORWARD             4 (to 714)
+         
+          75     >>  706 RERAISE                  0
+                 >>  708 COPY                     3
+                     710 POP_EXCEPT
+                     712 RERAISE                  1
+         
+          71     >>  714 LOAD_CONST               0 (None)
+                     716 LOAD_CONST               0 (None)
+                     718 LOAD_CONST               0 (None)
+                     720 PRECALL                  2
+                     724 CALL                     2
+                     734 POP_TOP
+                     736 JUMP_FORWARD            11 (to 760)
+                 >>  738 PUSH_EXC_INFO
+                     740 WITH_EXCEPT_START
+                     742 POP_JUMP_FORWARD_IF_TRUE     4 (to 752)
+                     744 RERAISE                  2
+                 >>  746 COPY                     3
+                     748 POP_EXCEPT
+                     750 RERAISE                  1
+                 >>  752 POP_TOP
+                     754 POP_EXCEPT
+                     756 POP_TOP
+                     758 POP_TOP
+                 >>  760 EXTENDED_ARG             1
+                     762 JUMP_BACKWARD          316 (to 132)
+         
+          78     >>  764 LOAD_CONST              12 ('Done')
+                     766 RETURN_VALUE
+         ExceptionTable:
+           146 to 366 -> 372 [1]
+           372 to 438 -> 446 [2] lasti
+           444 to 444 -> 446 [2] lasti
+           558 to 558 -> 738 [2] lasti
+           562 to 642 -> 646 [2]
+           644 to 644 -> 738 [2] lasti
+           646 to 700 -> 708 [3] lasti
+           702 to 704 -> 738 [2] lasti
+           706 to 706 -> 708 [3] lasti
+           708 to 712 -> 738 [2] lasti
+           738 to 744 -> 746 [4] lasti
+           752 to 752 -> 746 [4] lasti
+         consts
+            None
+            ('policy',)
+            '.pdf'
+            'subject'
+            ' '
+            '_'
+            'Got string instead of filename for '
+            '. Skipping.'
+            'wb'
+            True
+            ('decode',)
+            "Couldn't get payload for "
+            'Done'
+         names      ('email', 'message_from_binary_file', 'policy', 'default', 'enumerate', 'iter_attachments', 'get_filename', 'lower', 'endswith', 'replace', 'AttributeError', 'print', 'name', 'open', 'os', 'path', 'join', 'output_dir', 'write', 'get_payload', 'TypeError')
+         varnames   ('f', 'msg', 'idx', 'attachment', 'subject', 'output_filename', 'of')
+         freevars   ()
+         cellvars   ()
+         filename   '/Users/themba/section32/erjen/src/core/eml.py'
+         name       'extract_from_file'
+         firstlineno 53
+         lnotab
+            0x020240014e0102027202100150010c0202fe04031201300104fe080404
+            01680102015602120128ff08fc3207
+      code
          argcount  : 0
          nlocals   : 4
          stacksize : 7
          flags     : 3
          code
             0x97007401000000000000000000006a0100000000000000006401740400
             0000000000000000009b0064029d03a6010000ab01000000000000000001
@@ -492,34 +736,34 @@
             027c00a00b0000000000000000000000000000000000000000a6000000ab
             00000000000000000001007c00a007000000000000000000000000000000
             0000000000a6000000ab0000000000000000000100640484007419000000
             000000000000007c028e004400a6000000ab0000000000000000007d0374
             01000000000000000000006a01000000000000000064057c036406190000
             000000000000009b0064077c036408190000000000000000009b0064099d
             05a6010000ab010000000000000000010064005300
-          53           0 RESUME                   0
+          82           0 RESUME                   0
          
-          54           2 LOAD_GLOBAL              1 (NULL + rich)
+          83           2 LOAD_GLOBAL              1 (NULL + rich)
                       14 LOAD_ATTR                1 (print)
                       24 LOAD_CONST               1 ('in ')
                       26 LOAD_GLOBAL              4 (storage_dir)
                       38 FORMAT_VALUE             0
                       40 LOAD_CONST               2 (', extracting emails')
                       42 BUILD_STRING             3
                       44 PRECALL                  1
                       48 CALL                     1
                       58 POP_TOP
          
-          55          60 LOAD_GLOBAL              7 (NULL + Pool)
+          84          60 LOAD_GLOBAL              7 (NULL + Pool)
                       72 LOAD_CONST               0 (None)
                       74 PRECALL                  1
                       78 CALL                     1
                       88 STORE_FAST               0 (pool)
          
-          56          90 LOAD_GLOBAL              9 (NULL + glob)
+          85          90 LOAD_GLOBAL              9 (NULL + glob)
                      102 LOAD_ATTR                4 (glob)
                      112 LOAD_GLOBAL             10 (os)
                      124 LOAD_ATTR                6 (path)
                      134 LOAD_METHOD              7 (join)
                      156 LOAD_GLOBAL              4 (storage_dir)
                      168 LOAD_CONST               3 ('*.')
                      170 LOAD_GLOBAL             16 (EXTENSION)
@@ -527,45 +771,45 @@
                      184 BUILD_STRING             2
                      186 PRECALL                  2
                      190 CALL                     2
                      200 PRECALL                  1
                      204 CALL                     1
                      214 STORE_FAST               1 (eml_files)
          
-          57         216 LOAD_FAST                0 (pool)
+          86         216 LOAD_FAST                0 (pool)
                      218 LOAD_METHOD              9 (map)
                      240 LOAD_GLOBAL             20 (extract)
                      252 LOAD_FAST                1 (eml_files)
                      254 PRECALL                  2
                      258 CALL                     2
                      268 STORE_FAST               2 (res)
          
-          58         270 LOAD_FAST                0 (pool)
+          87         270 LOAD_FAST                0 (pool)
                      272 LOAD_METHOD             11 (close)
                      294 PRECALL                  0
                      298 CALL                     0
                      308 POP_TOP
          
-          59         310 LOAD_FAST                0 (pool)
+          88         310 LOAD_FAST                0 (pool)
                      312 LOAD_METHOD              7 (join)
                      334 PRECALL                  0
                      338 CALL                     0
                      348 POP_TOP
          
-          61         350 LOAD_CONST               4 (<code object <listcomp>, file "/Users/themba/section32/erjen/src/core/eml.py", line 61>)
+          90         350 LOAD_CONST               4 (<code object <listcomp>, file "/Users/themba/section32/erjen/src/core/eml.py", line 90>)
                      352 MAKE_FUNCTION            0
                      354 LOAD_GLOBAL             25 (NULL + zip)
                      366 LOAD_FAST                2 (res)
                      368 CALL_FUNCTION_EX         0
                      370 GET_ITER
                      372 PRECALL                  0
                      376 CALL                     0
                      386 STORE_FAST               3 (numfiles)
          
-          62         388 LOAD_GLOBAL              1 (NULL + rich)
+          91         388 LOAD_GLOBAL              1 (NULL + rich)
                      400 LOAD_ATTR                1 (print)
                      410 LOAD_CONST               5 ('Done: Processed ')
                      412 LOAD_FAST                3 (numfiles)
                      414 LOAD_CONST               6 (0)
                      416 BINARY_SUBSCR
                      426 FORMAT_VALUE             0
                      428 LOAD_CONST               7 (' files with ')
@@ -589,15 +833,15 @@
                argcount  : 1
                nlocals   : 2
                stacksize : 5
                flags     : 19
                code
                   0x970067007c005d117d017401000000000000000000007c01a6010000ab
                   01000000000000000091028c125300
-                61           0 RESUME                   0
+                90           0 RESUME                   0
                              2 BUILD_LIST               0
                              4 LOAD_FAST                0 (.0)
                        >>    6 FOR_ITER                17 (to 42)
                              8 STORE_FAST               1 (i)
                             10 LOAD_GLOBAL              1 (NULL + sum)
                             22 LOAD_FAST                1 (i)
                             24 PRECALL                  1
@@ -608,30 +852,30 @@
                consts
                names      ('sum',)
                varnames   ('.0', 'i')
                freevars   ()
                cellvars   ()
                filename   '/Users/themba/section32/erjen/src/core/eml.py'
                name       '<listcomp>'
-               firstlineno 61
+               firstlineno 90
                lnotab 0x
             'Done: Processed '
             0
             ' files with '
             1
             ' attachments.'
          names      ('rich', 'print', 'storage_dir', 'Pool', 'glob', 'os', 'path', 'join', 'EXTENSION', 'map', 'extract', 'close', 'zip')
          varnames   ('pool', 'eml_files', 'res', 'numfiles')
          freevars   ()
          cellvars   ()
          filename   '/Users/themba/section32/erjen/src/core/eml.py'
          name       'extract_emails'
-         firstlineno 53
+         firstlineno 82
          lnotab 0x02013a011e017e013601280128022601
-   names      ('glob', 'os', 'email', 'policy', 'multiprocessing', 'Pool', 'rich', 'EXTENSION', 'path', 'dirname', 'abspath', '__file__', 'current_dir', 'join', 'storage_dir', 'output_dir', 'extract', 'extract_emails')
+   names      ('glob', 'os', 'email', 'policy', 'multiprocessing', 'Pool', 'rich', 'EXTENSION', 'path', 'dirname', 'abspath', '__file__', 'current_dir', 'join', 'storage_dir', 'output_dir', 'extract', 'extract_from_file', 'extract_emails')
    varnames   ()
    freevars   ()
    cellvars   ()
    filename   '/Users/themba/section32/erjen/src/core/eml.py'
    name       '<module>'
    firstlineno 1
-   lnotab 0x00ff02010801080108010c010c010802040264013c013a030626
+   lnotab 0x00ff02010801080108010c010c010802040264013c013a030626061d
```

### Comparing `emreader-0.1.7/src/core/__pycache__/parse_tab.cpython-310.pyc` & `emreader-0.1.8/src/core/__pycache__/parse_tab.cpython-310.pyc`

 * *Files identical despite different names*

### Comparing `emreader-0.1.7/src/core/__pycache__/parse_tab.cpython-311.pyc` & `emreader-0.1.8/src/core/__pycache__/parse_tab.cpython-311.pyc`

 * *Files identical despite different names*

### Comparing `emreader-0.1.7/src/core/__pycache__/util.cpython-310.pyc` & `emreader-0.1.8/src/core/__pycache__/util.cpython-310.pyc`

 * *Files identical despite different names*

### Comparing `emreader-0.1.7/src/core/__pycache__/util.cpython-311.pyc` & `emreader-0.1.8/src/core/__pycache__/util.cpython-311.pyc`

 * *Files identical despite different names*

### Comparing `emreader-0.1.7/src/core/base.py` & `emreader-0.1.8/src/core/base.py`

 * *Files 3% similar despite different names*

```diff
@@ -4,14 +4,18 @@
 import fitz
 import rich
 from dateutil import parser
 
 from .parse_tab import ParseTab
 
 current_dir = os.path.dirname(os.path.abspath(__file__))
+storage_dir = os.path.join(current_dir, "..", "storage", "source", "emails")
+output_dir = os.path.join(current_dir, "..", "storage", "output")
+pdf_directory = os.path.join(current_dir, "..", "storage", "output")
+
 month_map = {
     "JAN": "1",
     "FEB": "2",
     "MAR": "3",
     "APR": "4",
     "MAY": "5",
     "JUN": "6",
@@ -142,15 +146,15 @@
     tables = [_date_cordinates(), _soybean_cordinates()]
     return list_to_dict(tables)
 
 
 def extract_from_files():
     # Get all PDF files in ./emls/output
     
-    pdf_directory = os.path.join(current_dir, "../..", "storage", "output")
+    
     pdf_files = glob.glob(os.path.join(pdf_directory, "*.pdf"))
     rich.print(f"found {len(pdf_files)} extracting")
     
     # Loop through all PDF files
     all_files_extracted_data = []
     if len(pdf_files) == 0:
         return [
```

### Comparing `emreader-0.1.7/src/core/eml.py` & `emreader-0.1.8/src/core/eml.py`

 * *Files 20% similar despite different names*

```diff
@@ -4,16 +4,16 @@
 from email import policy
 from multiprocessing import Pool
 import rich
 
 EXTENSION = "eml"
 
 current_dir = os.path.dirname(os.path.abspath(__file__))
-storage_dir = os.path.join(current_dir, "../..", "storage", "source", "emails")
-output_dir = os.path.join(current_dir, "../..", "storage", "output")
+storage_dir = os.path.join(current_dir, "..", "storage", "source", "emails")
+output_dir = os.path.join(current_dir, "..", "storage", "output")
 
 
 def extract(filename):
     """
     Try to extract the attachments from all files in cwd
     """
     os.makedirs(output_dir, exist_ok=True)
@@ -30,33 +30,61 @@
                         subject = subject.replace(" ", "_").lower()
                         output_filename = f"{subject}.pdf"
                     else:
                         continue
                 except AttributeError:
                     print(f"Got string instead of filename for {f.name}. Skipping.")
                     continue
-
+                
                 if output_filename:
                     with open(os.path.join(output_dir, output_filename), "wb") as of:
                         try:
                             of.write(attachment.get_payload(decode=True))
                             output_count += 1
                         except TypeError:
                             print(f"Couldn't get payload for {output_filename}")
             if output_count == 0:
                 print(f"No attachment found for file {f.name}!")
     except IOError:
         print(f"Problem with {f.name} or one of its attachments!")
-
+    
     return 1, output_count
 
 
+def extract_from_file(f):
+    
+    msg = email.message_from_binary_file(f, policy=policy.default)
+    for idx, attachment in enumerate(msg.iter_attachments()):
+        try:
+            # Only proceed if the attachment is a PDF
+            if attachment.get_filename().lower().endswith(".pdf"):
+                # Generate a short uuid
+                subject = msg['subject']
+                subject = subject.replace(" ", "_").lower()
+                output_filename = f"{subject}.pdf"
+            else:
+                continue
+        except AttributeError:
+            print(f"Got string instead of filename for {f.name}. Skipping.")
+            continue
+        
+        if output_filename:
+            with open(os.path.join(output_dir, output_filename), "wb") as of:
+                try:
+                    of.write(attachment.get_payload(decode=True))
+                except TypeError:
+                    print(f"Couldn't get payload for {output_filename}")
+    
+    return "Done"
+
+
+
 def extract_emails():
     rich.print(f"in {storage_dir}, extracting emails")
     pool = Pool(None)
     eml_files = glob.glob(os.path.join(storage_dir, f"*.{EXTENSION}"))
     res = pool.map(extract, eml_files)
     pool.close()
     pool.join()
-
+    
     numfiles = [sum(i) for i in zip(*res)]
-    rich.print(f"Done: Processed {numfiles[0]} files with {numfiles[1]} attachments.")
+    rich.print(f"Done: Processed {numfiles}.")
```

### Comparing `emreader-0.1.7/src/core/parse_tab.py` & `emreader-0.1.8/src/core/parse_tab.py`

 * *Files identical despite different names*

### Comparing `emreader-0.1.7/src/core/util.py` & `emreader-0.1.8/src/core/util.py`

 * *Files identical despite different names*

### Comparing `emreader-0.1.7/PKG-INFO` & `emreader-0.1.8/PKG-INFO`

 * *Files 8% similar despite different names*

```diff
@@ -1,28 +1,30 @@
 Metadata-Version: 2.1
 Name: emreader
-Version: 0.1.7
+Version: 0.1.8
 Summary: 
 License: Commercial
 Author: themba
 Author-email: themba@advantch.com
 Requires-Python: >=3.9, !=2.7.*, !=3.0.*, !=3.1.*, !=3.2.*, !=3.3.*, !=3.4.*, !=3.5.*, !=3.6.*, !=3.7.*, !=3.8.*
 Classifier: License :: Other/Proprietary License
 Classifier: Programming Language :: Python :: 3
 Classifier: Programming Language :: Python :: 3.9
 Classifier: Programming Language :: Python :: 3.10
 Classifier: Programming Language :: Python :: 3.11
 Requires-Dist: PyPDF2 (==2.0)
+Requires-Dist: aiofiles (>=23.1.0,<24.0.0)
 Requires-Dist: cffi (>=1.15.1,<2.0.0)
 Requires-Dist: chardet (>=5.1.0,<6.0.0)
 Requires-Dist: charset-normalizer (>=3.1.0,<4.0.0)
 Requires-Dist: click (>=8.1.3,<9.0.0)
 Requires-Dist: cryptography (>=41.0.1,<42.0.0)
 Requires-Dist: distro (>=1.8.0,<2.0.0)
 Requires-Dist: et-xmlfile (>=1.1.0,<2.0.0)
+Requires-Dist: filestorage (>=0.0.6,<0.0.7)
 Requires-Dist: numpy (>=1.25.0,<2.0.0)
 Requires-Dist: opencv-python (>=4.7.0.72,<5.0.0.0)
 Requires-Dist: openpyxl (>=3.1.2,<4.0.0)
 Requires-Dist: pandas (>=2.0.2,<3.0.0)
 Requires-Dist: pip (>=23.1.2,<24.0.0)
 Requires-Dist: pycparser (>=2.21,<3.0)
 Requires-Dist: pymupdf (>=1.22.5,<2.0.0)
```

